Workbook

Sheet Stock
F8: Gennemsnit | G8: Danmark | H8: Europa | I8: USA | J8: Total
F9: ='Ranglisten DK'!D1 -> Q1 2026 | G9: =AVERAGE('Ranglisten DK'!D17:D27) -> 3.1240364 | H9: =AVERAGE('Ranglisten EU'!D17:D27) -> 3.1669818 | I9: =AVERAGE('Ranglisten USA'!D17:D27) -> 3.1922273 | J9: =AVERAGE(G9:I9) -> 3.1610818
F10: ='Ranglisten DK'!E1 -> Q2 2026 | G10: =AVERAGE('Ranglisten DK'!D31:D41) -> 3.2503182 | H10: =AVERAGE('Ranglisten EU'!D31:D41) -> 3.0710091 | I10: =AVERAGE('Ranglisten USA'!D33:D43) -> 3.0583727 | J10: =AVERAGE(G10:I10) -> 3.1265667
F11: Gennemsnit | G11: =AVERAGE(G9:G10) -> 3.1871773 | H11: =AVERAGE(H9:H10) -> 3.1189955 | I11: =AVERAGE(I9:I10) -> 3.1253 | J11: =AVERAGE(G11:I11) -> 3.1438242
F13: Best performer | G13: =G8 -> Danmark | H13: =H8 -> Europa | I13: =I8 -> USA | J13: =J8 -> Total
F14: =F9 -> Q1 2026 | G14: ='Ranglisten DK'!C17 -> Information Technology | H14: ='Ranglisten EU'!C17 -> Information Technology | I14: ='Ranglisten USA'!C17 -> Energy
F15: =F10 -> Q2 2026 | G15: ='Ranglisten DK'!C31 -> Industrials | H15: ='Ranglisten EU'!C31 -> Information Technology | I15: ='Ranglisten USA'!C33 -> Information Technology
D19: Til enkelt aktier
D20: EPS Growth - The Fair Value Journal
D22: Stock ticker
D25: Total Revenue
D26: Total Cash and Cash Equivalents
D27: Total Equity
D28: Total Debt
D29: Minority Interests
D30: Non-operating Assets
D31: Shares Outstanding
D32: Revenue Growth (%) – Year 1
D33: Revenue Growth (%) – Years 2–5
... D40: Terminal Operating Margin (%)

Sheet Ranglisten DK
C1: Sektor | D1: ='Makro analyse'!K29 -> Q1 2026 | E1: ='Makro analyse'!T29 -> Q2 2026
C2: Financials | D2: ='Makro analyse'!K31 -> 3.5836 | E2: ='Makro analyse'!T31 -> 3.6948
C3: Real Estate | D3: ='Makro analyse'!K32 -> 2.3891 | E3: ='Makro analyse'!T32 -> 3.3614
C4: Consumer Discretionary | D4: ='Makro analyse'!K33 -> 3.6947 | E4: ='Makro analyse'!T33 -> 3.3336
C5: Information Technology | D5: ='Makro analyse'!K34 -> 4.4726 | E5: ='Makro analyse'!T34 -> 3.8337
C6: Industrials | D6: ='Makro analyse'!K35 -> 3.6947 | E6: ='Makro analyse'!T35 -> 3.9448
C7: Materials | D7: ='Makro analyse'!K36 -> 2.278 | E7: ='Makro analyse'!T36 -> 3.1114
C8: Consumer Staples | D8: ='Makro analyse'!K37 -> 2.417 | E8: ='Makro analyse'!T37 -> 2.3058
C9: Health Care | D9: ='Makro analyse'!K38 -> 2.8892 | E9: ='Makro analyse'!T38 -> 2.7503
C10: Energy | D10: ='Makro analyse'!K39 -> 3.0004 | E10: ='Makro analyse'!T39 -> 3.3615
C11: Communications Services | D11: ='Makro analyse'!K40 -> 3.8337 | E11: ='Makro analyse'!T40 -> 3.4448
C12: Utilities | D12: ='Makro analyse'!K41 -> 2.1114 | E12: ='Makro analyse'!T41 -> 2.6114
B15: =D1 -> Q1 2026
B16: Nr. | C16: Sektor | D16: Markedscore | E16: ETF | F16: Aktier
B17: 1 | C17: =_xlfn.XLOOKUP(D17,$D$2:$D$12,$C$2:$C$12) -> Information Technology | D17: =LARGE($D$2:$D$12,1) -> 4.4726 | E17: =_xlfn.XLOOKUP(C17,'ETF - Liste'!E:E,'ETF - Liste'!B:B) -> Invesco Nasdaq-100 UCITS | F17: {=_xlfn.TEXTJOIN(", ",TRUE,IF(C17='Aktieliste DK'!F:F,'Aktieliste DK'!H:H,""))}
B18: 2 | C18: =_xlfn.XLOOKUP(D18,$D$2:$D$12,$C$2:$C$12) -> Communications Services | D18: =LARGE($D$2:$D$12,2) -> 3.8337 | E18: =_xlfn.XLOOKUP(C18,'ETF - Liste'!E:E,'ETF - Liste'!B:B) -> Lyxor STOXX Europe Comm. Services | F18: {=_xlfn.TEXTJOIN(", ",TRUE,IF(C18='Aktieliste DK'!F:F,'Aktieliste DK'!H:H,""))}
B19: 3 | C19: =_xlfn.XLOOKUP(D19,$D$2:$D$12,$C$2:$C$12) -> Consumer Discretionary | D19: =LARGE($D$2:$D$12,3) -> 3.6947 | E19: =_xlfn.XLOOKUP(C19,'ETF - Liste'!E:E,'ETF - Liste'!B:B) -> iShares Global Consumer Discretionary | F19: {=_xlfn.TEXTJOIN(", ",TRUE,IF(C19='Aktieliste DK'!F:F,'Aktieliste DK'!H:H,""))} -> CARL B, PNDORA
B20: 4 | C20: =_xlfn.XLOOKUP(D20,$D$2:$D$12,$C$2:$C$12) -> Consumer Discretionary | D20: =LARGE($D$2:$D$12,4) -> 3.6947 | E20: =_xlfn.XLOOKUP(C20,'ETF - Liste'!E:E,'ETF - Liste'!B:B) -> iShares Global Consumer Discretionary | F20: {=_xlfn.TEXTJOIN(", ",TRUE,IF(C20='Aktieliste DK'!F:F,'Aktieliste DK'!H:H,""))} -> CARL B, PNDORA
B21: 5 | C21: =_xlfn.XLOOKUP(D21,$D$2:$D$12,$C$2:$C$12) -> Financials | D21: =LARGE($D$2:$D$12,5) -> 3.5836 | E21: =_xlfn.XLOOKUP(C21,'ETF - Liste'!E:E,'ETF - Liste'!B:B) -> iShares MSCI World Financials | F21: {=_xlfn.TEXTJOIN(", ",TRUE,IF(C21='Aktieliste DK'!F:F,'Aktieliste DK'!H:H,""))} -> DANSKE, TRYG, NDA SE, JYSK, ALSYDB
B22: 6 | C22: =_xlfn.XLOOKUP(D22,$D$2:$D$12,$C$2:$C$12) -> Energy | D22: =LARGE($D$2:$D$12,6) -> 3.0004 | E22: =_xlfn.XLOOKUP(C22,'ETF - Liste'!E:E,'ETF - Liste'!B:B) -> SPDR MSCI World Energy | F22: {=_xlfn.TEXTJOIN(", ",TRUE,IF(C22='Aktieliste DK'!F:F,'Aktieliste DK'!H:H,""))} -> ORSTED
B23: 7 | C23: =_xlfn.XLOOKUP(D23,$D$2:$D$12,$C$2:$C$12) -> Health Care | D23: =LARGE($D$2:$D$12,7) -> 2.8892 | E23: =_xlfn.XLOOKUP(C23,'ETF - Liste'!E:E,'ETF - Liste'!B:B) -> iShares Global Healthcare ETF | F23: {=_xlfn.TEXTJOIN(", ",TRUE,IF(C23='Aktieliste DK'!F:F,'Aktieliste DK'!H:H,""))} -> NOVO B, NSIS B, COLO B, GMAB, DEMANT, ZEAL, AMBU B, GN, BAVA
B24: 8 | C24: =_xlfn.XLOOKUP(D24,$D$2:$D$12,$C$2:$C$12) -> Consumer Staples | D24: =LARGE($D$2:$D$12,8) -> 2.417 | E24: =_xlfn.XLOOKUP(C24,'ETF - Liste'!E:E,'ETF - Liste'!B:B) -> iShares MSCI Consumer Staples | F24: {=_xlfn.TEXTJOIN(", ",TRUE,IF(C24='Aktieliste DK'!F:F,'Aktieliste DK'!H:H,""))} -> RBREW
B25: 9 | C25: =_xlfn.XLOOKUP(D25,$D$2:$D$12,$C$2:$C$12) -> Real Estate | D25: =LARGE($D$2:$D$12,9) -> 2.3891 | E25: =_xlfn.XLOOKUP(C25,'ETF - Liste'!E:E,'ETF - Liste'!B:B) -> SPDR Dow Jones Global Real Estate | F25: {=_xlfn.TEXTJOIN(", ",TRUE,IF(C25='Aktieliste DK'!F:F,'Aktieliste DK'!H:H,""))}
B26: 10 | C26: =_xlfn.XLOOKUP(D26,$D$2:$D$12,$C$2:$C$12) -> Materials | D26: =LARGE($D$2:$D$12,10) -> 2.278 | E26: =_xlfn.XLOOKUP(C26,'ETF - Liste'!E:E,'ETF - Liste'!B:B) -> Lyxor MSCI World Materials | F26: {=_xlfn.TEXTJOIN(", ",TRUE,IF(C26='Aktieliste DK'!F:F,'Aktieliste DK'!H:H,""))} -> ROCK B
B27: 11 | C27: =_xlfn.XLOOKUP(D27,$D$2:$D$12,$C$2:$C$12) -> Utilities | D27: =LARGE($D$2:$D$12,11) -> 2.1114 | E27: =_xlfn.XLOOKUP(C27,'ETF - Liste'!E:E,'ETF - Liste'!B:B) -> iShares Global Utilities | F27: {=_xlfn.TEXTJOIN(", ",TRUE,IF(C27='Aktieliste DK'!F:F,'Aktieliste DK'!H:H,""))}
B29: =E1 -> Q2 2026
B30: Nr. | C30: Sektor | D30: Markedscore | E30: ETF | F30: Aktier
B31: 1 | C31: =_xlfn.XLOOKUP(D31,$E$2:$E$12,$C$2:$C$12) -> Industrials | D31: =LARGE($E$2:$E$12,1) -> 3.9448 | E31: =_xlfn.XLOOKUP(C31,'ETF - Liste'!E:E,'ETF - Liste'!B:B) -> iShares MSCI World Industrials | F31: {=_xlfn.TEXTJOIN(", ",TRUE,IF(C31='Aktieliste DK'!F:F,'Aktieliste DK'!H:H,""))} -> DSV, MAERSK B, VWS, ISS, NKT
B32: 2 | C32: =_xlfn.XLOOKUP(D32,$E$2:$E$12,$C$2:$C$12) -> Information Technology | D32: =LARGE($E$2:$E$12,2) -> 3.8337 | E32: =_xlfn.XLOOKUP(C32,'ETF - Liste'!E:E,'ETF - Liste'!B:B) -> Invesco Nasdaq-100 UCITS | F32: {=_xlfn.TEXTJOIN(", ",TRUE,IF(C32='Aktieliste DK'!F:F,'Aktieliste DK'!H:H,""))}
B33: 3 | C33: =_xlfn.XLOOKUP(D33,$E$2:$E$12,$C$2:$C$12) -> Financials | D33: =LARGE($E$2:$E$12,3) -> 3.6948 | E33: =_xlfn.XLOOKUP(C33,'ETF - Liste'!E:E,'ETF - Liste'!B:B) -> iShares MSCI World Financials | F33: {=_xlfn.TEXTJOIN(", ",TRUE,IF(C33='Aktieliste DK'!F:F,'Aktieliste DK'!H:H,""))} -> DANSKE, TRYG, NDA SE, JYSK, ALSYDB
B34: 4 | C34: =_xlfn.XLOOKUP(D34,$E$2:$E$12,$C$2:$C$12) -> Communications Services | D34: =LARGE($E$2:$E$12,4) -> 3.4448 | E34: =_xlfn.XLOOKUP(C34,'ETF - Liste'!E:E,'ETF - Liste'!B:B) -> Lyxor STOXX Europe Comm. Services | F34: {=_xlfn.TEXTJOIN(", ",TRUE,IF(C34='Aktieliste DK'!F:F,'Aktieliste DK'!H:H,""))}
B35: 5 | C35: =_xlfn.XLOOKUP(D35,$E$2:$E$12,$C$2:$C$12) -> Energy | D35: =LARGE($E$2:$E$12,5) -> 3.3615 | E35: =_xlfn.XLOOKUP(C35,'ETF - Liste'!E:E,'ETF - Liste'!B:B) -> SPDR MSCI World Energy | F35: {=_xlfn.TEXTJOIN(", ",TRUE,IF(C35='Aktieliste DK'!F:F,'Aktieliste DK'!H:H,""))} -> ORSTED
B36: 6 | C36: =_xlfn.XLOOKUP(D36,$E$2:$E$12,$C$2:$C$12) -> Real Estate | D36: =LARGE($E$2:$E$12,6) -> 3.3614 | E36: =_xlfn.XLOOKUP(C36,'ETF - Liste'!E:E,'ETF - Liste'!B:B) -> SPDR Dow Jones Global Real Estate | F36: {=_xlfn.TEXTJOIN(", ",TRUE,IF(C36='Aktieliste DK'!F:F,'Aktieliste DK'!H:H,""))}
B37: 7 | C37: =_xlfn.XLOOKUP(D37,$E$2:$E$12,$C$2:$C$12) -> Consumer Discretionary | D37: =LARGE($E$2:$E$12,7) -> 3.3336 | E37: =_xlfn.XLOOKUP(C37,'ETF - Liste'!E:E,'ETF - Liste'!B:B) -> iShares Global Consumer Discretionary | F37: {=_xlfn.TEXTJOIN(", ",TRUE,IF(C37='Aktieliste DK'!F:F,'Aktieliste DK'!H:H,""))} -> CARL B, PNDORA
B38: 8 | C38: =_xlfn.XLOOKUP(D38,$E$2:$E$12,$C$2:$C$12) -> Materials | D38: =LARGE($E$2:$E$12,8) -> 3.1114 | E38: =_xlfn.XLOOKUP(C38,'ETF - Liste'!E:E,'ETF - Liste'!B:B) -> Lyxor MSCI World Materials | F38: {=_xlfn.TEXTJOIN(", ",TRUE,IF(C38='Aktieliste DK'!F:F,'Aktieliste DK'!H:H,""))} -> ROCK B
B39: 9 | C39: =_xlfn.XLOOKUP(D39,$E$2:$E$12,$C$2:$C$12) -> Health Care | D39: =LARGE($E$2:$E$12,9) -> 2.7503 | E39: =_xlfn.XLOOKUP(C39,'ETF - Liste'!E:E,'ETF - Liste'!B:B) -> iShares Global Healthcare ETF | F39: {=_xlfn.TEXTJOIN(", ",TRUE,IF(C39='Aktieliste DK'!F:F,'Aktieliste DK'!H:H,""))} -> NOVO B, NSIS B, COLO B, GMAB, DEMANT, ZEAL, AMBU B, GN, BAVA
B40: 10 | C40: =_xlfn.XLOOKUP(D40,$E$2:$E$12,$C$2:$C$12) -> Utilities | D40: =LARGE($E$2:$E$12,10) -> 2.6114 | E40: =_xlfn.XLOOKUP(C40,'ETF - Liste'!E:E,'ETF - Liste'!B:B) -> iShares Global Utilities | F40: {=_xlfn.TEXTJOIN(", ",TRUE,IF(C40='Aktieliste DK'!F:F,'Aktieliste DK'!H:H,""))}
B41: 11 | C41: =_xlfn.XLOOKUP(D41,$E$2:$E$12,$C$2:$C$12) -> Consumer Staples | D41: =LARGE($E$2:$E$12,11) -> 2.3058 | E41: =_xlfn.XLOOKUP(C41,'ETF - Liste'!E:E,'ETF - Liste'!B:B) -> iShares MSCI Consumer Staples | F41: {=_xlfn.TEXTJOIN(", ",TRUE,IF(C41='Aktieliste DK'!F:F,'Aktieliste DK'!H:H,""))} -> RBREW

Sheet Ranglisten EU
B1: Sektor | C1: Makroscore DK (Q2 2025) | D1: ='Makro analyse'!K69 -> Q1 2026 | E1: ='Makro analyse'!T69 -> Q2 2026
B2: Financials | D2: ='Makro analyse'!K71 -> 3.3614 | E2: ='Makro analyse'!T71 -> 3.4726
B3: Real Estate | D3: ='Makro analyse'!K72 -> 3.0837 | E3: ='Makro analyse'!T72 -> 2.528
B4: Consumer Discretionary | D4: ='Makro analyse'!K73 -> 3.9726 | E4: ='Makro analyse'!T73 -> 3.6115
B5: Information Technology | D5: ='Makro analyse'!K74 -> 4.3615 | E5: ='Makro analyse'!T74 -> 4.3338
B6: Industrials | D6: ='Makro analyse'!K75 -> 3.9726 | E6: ='Makro analyse'!T75 -> 3.6115
B7: Materials | D7: ='Makro analyse'!K76 -> 2.7781 | E7: ='Makro analyse'!T76 -> 2.0835
B8: Consumer Staples | D8: ='Makro analyse'!K77 -> 2.6392 | E8: ='Makro analyse'!T77 -> 2.2224
B9: Health Care | D9: ='Makro analyse'!K78 -> 2.3891 | E9: ='Makro analyse'!T78 -> 2.8614
B10: Energy | D10: ='Makro analyse'!K79 -> 2.7225 | E10: ='Makro analyse'!T79 -> 3.0836
B11: Communications Services | D11: ='Makro analyse'!K80 -> 3.5281 | E11: ='Makro analyse'!T80 -> 3.7504
B12: Utilities | D12: ='Makro analyse'!K81 -> 2.028 | E12: ='Makro analyse'!T81 -> 2.2224
B15: =D1 -> Q1 2026
B16: Nr. | C16: Sektor | D16: Markedscore | E16: ETF | F16: Aktier
B17: 1 | C17: =_xlfn.XLOOKUP(D17,$D$2:$D$12,$B$2:$B$12) -> Information Technology | D17: =LARGE($D$2:$D$12,1) -> 4.3615 | E17: =_xlfn.XLOOKUP(C17,'ETF - Liste'!E:E,'ETF - Liste'!B:B) -> Invesco Nasdaq-100 UCITS | F17: {=_xlfn.TEXTJOIN(", ",TRUE,IF(C17='Aktieliste EU'!F:F,'Aktieliste EU'!G:G,""))} -> SU, SAP, WLN
B18: 2 | C18: =_xlfn.XLOOKUP(D18,$D$2:$D$12,$B$2:$B$12) -> Consumer Discretionary | D18: =LARGE($D$2:$D$12,2) -> 3.9726 | E18: =_xlfn.XLOOKUP(C18,'ETF - Liste'!E:E,'ETF - Liste'!B:B) -> iShares Global Consumer Discretionary | F18: {=_xlfn.TEXTJOIN(", ",TRUE,IF(C18='Aktieliste EU'!F:F,'Aktieliste EU'!G:G,""))} -> EL, RMS, ITX, KER, MMO, MBG, STLA, VOW3, ZAL
B19: 3 | C19: =_xlfn.XLOOKUP(D19,$D$2:$D$12,$B$2:$B$12) -> Consumer Discretionary | D19: =LARGE($D$2:$D$12,3) -> 3.9726 | E19: =_xlfn.XLOOKUP(C19,'ETF - Liste'!E:E,'ETF - Liste'!B:B) -> iShares Global Consumer Discretionary | F19: {=_xlfn.TEXTJOIN(", ",TRUE,IF(C19='Aktieliste EU'!F:F,'Aktieliste EU'!G:G,""))} -> EL, RMS, ITX, KER, MMO, MBG, STLA, VOW3, ZAL
B20: 4 | C20: =_xlfn.XLOOKUP(D20,$D$2:$D$12,$B$2:$B$12) -> Communications Services | D20: =LARGE($D$2:$D$12,4) -> 3.5281 | E20: =_xlfn.XLOOKUP(C20,'ETF - Liste'!E:E,'ETF - Liste'!B:B) -> Lyxor STOXX Europe Comm. Services | F20: {=_xlfn.TEXTJOIN(", ",TRUE,IF(C20='Aktieliste EU'!F:F,'Aktieliste EU'!G:G,""))}
B21: 5 | C21: =_xlfn.XLOOKUP(D21,$D$2:$D$12,$B$2:$B$12) -> Financials | D21: =LARGE($D$2:$D$12,5) -> 3.3614 | E21: =_xlfn.XLOOKUP(C21,'ETF - Liste'!E:E,'ETF - Liste'!B:B) -> iShares MSCI World Financials | F21: {=_xlfn.TEXTJOIN(", ",TRUE,IF(C21='Aktieliste EU'!F:F,'Aktieliste EU'!G:G,""))} -> ALV, CS, BBVA, BNP, DBK, G, INGA, ISP, MUV2, UCG, SAN
B22: 6 | C22: =_xlfn.XLOOKUP(D22,$D$2:$D$12,$B$2:$B$12) -> Real Estate | D22: =LARGE($D$2:$D$12,6) -> 3.0837 | E22: =_xlfn.XLOOKUP(C22,'ETF - Liste'!E:E,'ETF - Liste'!B:B) -> SPDR Dow Jones Global Real Estate | F22: {=_xlfn.TEXTJOIN(", ",TRUE,IF(C22='Aktieliste EU'!F:F,'Aktieliste EU'!G:G,""))} -> VNA
B23: 7 | C23: =_xlfn.XLOOKUP(D23,$D$2:$D$12,$B$2:$B$12) -> Materials | D23: =LARGE($D$2:$D$12,7) -> 2.7781 | E23: =_xlfn.XLOOKUP(C23,'ETF - Liste'!E:E,'ETF - Liste'!B:B) -> Lyxor MSCI World Materials | F23: {=_xlfn.TEXTJOIN(", ",TRUE,IF(C23='Aktieliste EU'!F:F,'Aktieliste EU'!G:G,""))} -> BAS
B24: 8 | C24: =_xlfn.XLOOKUP(D24,$D$2:$D$12,$B$2:$B$12) -> Energy | D24: =LARGE($D$2:$D$12,8) -> 2.7225 | E24: =_xlfn.XLOOKUP(C24,'ETF - Liste'!E:E,'ETF - Liste'!B:B) -> SPDR MSCI World Energy | F24: {=_xlfn.TEXTJOIN(", ",TRUE,IF(C24='Aktieliste EU'!F:F,'Aktieliste EU'!G:G,""))} -> ENEL, ENI, TTE
B25: 9 | C25: =_xlfn.XLOOKUP(D25,$D$2:$D$12,$B$2:$B$12) -> Consumer Staples | D25: =LARGE($D$2:$D$12,9) -> 2.6392 | E25: =_xlfn.XLOOKUP(C25,'ETF - Liste'!E:E,'ETF - Liste'!B:B) -> iShares MSCI Consumer Staples | F25: {=_xlfn.TEXTJOIN(", ",TRUE,IF(C25='Aktieliste EU'!F:F,'Aktieliste EU'!G:G,""))} -> ABI, BN, OR
B26: 10 | C26: =_xlfn.XLOOKUP(D26,$D$2:$D$12,$B$2:$B$12) -> Health Care | D26: =LARGE($D$2:$D$12,10) -> 2.3891 | E26: =_xlfn.XLOOKUP(C26,'ETF - Liste'!E:E,'ETF - Liste'!B:B) -> iShares Global Healthcare ETF | F26: {=_xlfn.TEXTJOIN(", ",TRUE,IF(C26='Aktieliste EU'!F:F,'Aktieliste EU'!G:G,""))} -> SHL, PHIA, SAN
B27: 11 | C27: =_xlfn.XLOOKUP(D27,$D$2:$D$12,$B$2:$B$12) -> Utilities | D27: =LARGE($D$2:$D$12,11) -> 2.028 | E27: =_xlfn.XLOOKUP(C27,'ETF - Liste'!E:E,'ETF - Liste'!B:B) -> iShares Global Utilities | F27: {=_xlfn.TEXTJOIN(", ",TRUE,IF(C27='Aktieliste EU'!F:F,'Aktieliste EU'!G:G,""))} -> ENGI, IBE, ORAT
B29: =E1 -> Q2 2026
B30: Nr. | C30: Sektor | D30: Markedscore | E30: ETF | F30: Aktier
B31: 1 | C31: =_xlfn.XLOOKUP(D31,$E$2:$E$12,$B$2:$B$12) -> Information Technology | D31: =LARGE($E$2:$E$12,1) -> 4.3338 | E31: =_xlfn.XLOOKUP(C31,'ETF - Liste'!E:E,'ETF - Liste'!B:B) -> Invesco Nasdaq-100 UCITS | F31: {=_xlfn.TEXTJOIN(", ",TRUE,IF(C31='Aktieliste EU'!F:F,'Aktieliste EU'!G:G,""))} -> SU, SAP, WLN
B32: 2 | C32: =_xlfn.XLOOKUP(D32,$E$2:$E$12,$B$2:$B$12) -> Communications Services | D32: =LARGE($E$2:$E$12,2) -> 3.7504 | E32: =_xlfn.XLOOKUP(C32,'ETF - Liste'!E:E,'ETF - Liste'!B:B) -> Lyxor STOXX Europe Comm. Services | F32: {=_xlfn.TEXTJOIN(", ",TRUE,IF(C32='Aktieliste EU'!F:F,'Aktieliste EU'!G:G,""))}
B33: 3 | C33: =_xlfn.XLOOKUP(D33,$E$2:$E$12,$B$2:$B$12) -> Consumer Discretionary | D33: =LARGE($E$2:$E$12,3) -> 3.6115 | E33: =_xlfn.XLOOKUP(C33,'ETF - Liste'!E:E,'ETF - Liste'!B:B) -> iShares Global Consumer Discretionary | F33: {=_xlfn.TEXTJOIN(", ",TRUE,IF(C33='Aktieliste EU'!F:F,'Aktieliste EU'!G:G,""))} -> EL, RMS, ITX, KER, MMO, MBG, STLA, VOW3, ZAL
B34: 4 | C34: =_xlfn.XLOOKUP(D34,$E$2:$E$12,$B$2:$B$12) -> Consumer Discretionary | D34: =LARGE($E$2:$E$12,4) -> 3.6115 | E34: =_xlfn.XLOOKUP(C34,'ETF - Liste'!E:E,'ETF - Liste'!B:B) -> iShares Global Consumer Discretionary | F34: {=_xlfn.TEXTJOIN(", ",TRUE,IF(C34='Aktieliste EU'!F:F,'Aktieliste EU'!G:G,""))} -> EL, RMS, ITX, KER, MMO, MBG, STLA, VOW3, ZAL
B35: 5 | C35: =_xlfn.XLOOKUP(D35,$E$2:$E$12,$B$2:$B$12) -> Financials | D35: =LARGE($E$2:$E$12,5) -> 3.4726 | E35: =_xlfn.XLOOKUP(C35,'ETF - Liste'!E:E,'ETF - Liste'!B:B) -> iShares MSCI World Financials | F35: {=_xlfn.TEXTJOIN(", ",TRUE,IF(C35='Aktieliste EU'!F:F,'Aktieliste EU'!G:G,""))} -> ALV, CS, BBVA, BNP, DBK, G, INGA, ISP, MUV2, UCG, SAN
B36: 6 | C36: =_xlfn.XLOOKUP(D36,$E$2:$E$12,$B$2:$B$12) -> Energy | D36: =LARGE($E$2:$E$12,6) -> 3.0836 | E36: =_xlfn.XLOOKUP(C36,'ETF - Liste'!E:E,'ETF - Liste'!B:B) -> SPDR MSCI World Energy | F36: {=_xlfn.TEXTJOIN(", ",TRUE,IF(C36='Aktieliste EU'!F:F,'Aktieliste EU'!G:G,""))} -> ENEL, ENI, TTE
B37: 7 | C37: =_xlfn.XLOOKUP(D37,$E$2:$E$12,$B$2:$B$12) -> Health Care | D37: =LARGE($E$2:$E$12,7) -> 2.8614 | E37: =_xlfn.XLOOKUP(C37,'ETF - Liste'!E:E,'ETF - Liste'!B:B) -> iShares Global Healthcare ETF | F37: {=_xlfn.TEXTJOIN(", ",TRUE,IF(C37='Aktieliste EU'!F:F,'Aktieliste EU'!G:G,""))} -> SHL, PHIA, SAN
B38: 8 | C38: =_xlfn.XLOOKUP(D38,$E$2:$E$12,$B$2:$B$12) -> Real Estate | D38: =LARGE($E$2:$E$12,8) -> 2.528 | E38: =_xlfn.XLOOKUP(C38,'ETF - Liste'!E:E,'ETF - Liste'!B:B) -> SPDR Dow Jones Global Real Estate | F38: {=_xlfn.TEXTJOIN(", ",TRUE,IF(C38='Aktieliste EU'!F:F,'Aktieliste EU'!G:G,""))} -> VNA
B39: 9 | C39: =_xlfn.XLOOKUP(D39,$E$2:$E$12,$B$2:$B$12) -> Consumer Staples | D39: =LARGE($E$2:$E$12,9) -> 2.2224 | E39: =_xlfn.XLOOKUP(C39,'ETF - Liste'!E:E,'ETF - Liste'!B:B) -> iShares MSCI Consumer Staples | F39: {=_xlfn.TEXTJOIN(", ",TRUE,IF(C39='Aktieliste EU'!F:F,'Aktieliste EU'!G:G,""))} -> ABI, BN, OR
B40: 10 | C40: =_xlfn.XLOOKUP(D40,$E$2:$E$12,$B$2:$B$12) -> Consumer Staples | D40: =LARGE($E$2:$E$12,10) -> 2.2224 | E40: =_xlfn.XLOOKUP(C40,'ETF - Liste'!E:E,'ETF - Liste'!B:B) -> iShares MSCI Consumer Staples | F40: {=_xlfn.TEXTJOIN(", ",TRUE,IF(C40='Aktieliste EU'!F:F,'Aktieliste EU'!G:G,""))} -> ABI, BN, OR
B41: 11 | C41: =_xlfn.XLOOKUP(D41,$E$2:$E$12,$B$2:$B$12) -> Materials | D41: =LARGE($E$2:$E$12,11) -> 2.0835 | E41: =_xlfn.XLOOKUP(C41,'ETF - Liste'!E:E,'ETF - Liste'!B:B) -> Lyxor MSCI World Materials | F41: {=_xlfn.TEXTJOIN(", ",TRUE,IF(C41='Aktieliste EU'!F:F,'Aktieliste EU'!G:G,""))} -> BAS

Sheet Ranglisten USA
B1: Sektor | E1: ='Makro analyse'!K109 -> Q1 2026 | F1: ='Makro analyse'!T109 -> Q2 2026
B2: Financials | E2: ='Makro analyse'!K111 -> 3.2502 | F2: ='Makro analyse'!T111 -> 3.3614
B3: Real Estate | E3: ='Makro analyse'!K112 -> 3.167 | F3: ='Makro analyse'!T112 -> 2.5002
B4: Consumer Discretionary | E4: ='Makro analyse'!K113 -> 2.7501 | F4: ='Makro analyse'!T113 -> 3.4725
B5: Information Technology | E5: ='Makro analyse'!K114 -> 3.528 | F5: ='Makro analyse'!T114 -> 4.2504
B6: Industrials | E6: ='Makro analyse'!K115 -> 3.3613 | F6: ='Makro analyse'!T115 -> 3.4725
B7: Materials | E7: ='Makro analyse'!K116 -> 2.7503 | F7: ='Makro analyse'!T116 -> 2.0835
B8: Consumer Staples | E8: ='Makro analyse'!K117 -> 3.056 | F8: ='Makro analyse'!T117 -> 2.3336
B9: Health Care | E9: ='Makro analyse'!K118 -> 2.8892 | F9: ='Makro analyse'!T118 -> 2.8892
B10: Energy | E10: ='Makro analyse'!K119 -> 3.945 | F10: ='Makro analyse'!T119 -> 3.2226
B11: Communications Services | E11: ='Makro analyse'!K120 -> 3.3614 | F11: ='Makro analyse'!T120 -> 3.7226
B12: Utilities | E12: ='Makro analyse'!K121 -> 3.056 | F12: ='Makro analyse'!T121 -> 2.3336
B15: =E1 -> Q1 2026
B16: Nr. | C16: Sektor | D16: Markedscore | E16: ETF | F16: Aktier
B17: 1 | C17: =_xlfn.XLOOKUP(D17,$E$2:$E$12,$B$2:$B$12) -> Energy | D17: =LARGE($E$2:$E$12,1) -> 3.945 | E17: =_xlfn.XLOOKUP(C17,'ETF - Liste'!E:E,'ETF - Liste'!B:B) -> SPDR MSCI World Energy | F17: {=_xlfn.TEXTJOIN(", ",TRUE,IF(C17='Aktieliste USA'!F:F,'Aktieliste USA'!G:G,""))} -> CVX, XOM
B18: 2 | C18: =_xlfn.XLOOKUP(D18,$E$2:$E$12,$B$2:$B$12) -> Information Technology | D18: =LARGE($E$2:$E$12,2) -> 3.528 | E18: =_xlfn.XLOOKUP(C18,'ETF - Liste'!E:E,'ETF - Liste'!B:B) -> Invesco Nasdaq-100 UCITS | F18: {=_xlfn.TEXTJOIN(", ",TRUE,IF(C18='Aktieliste USA'!F:F,'Aktieliste USA'!G:G,""))} -> NVDA, ORCL, ADBE, INTC, CRM, INTU, AVGO, QCOM, AAPL, MSFT, TXN, CSCO
B19: 3 | C19: =_xlfn.XLOOKUP(D19,$E$2:$E$12,$B$2:$B$12) -> Communications Services | D19: =LARGE($E$2:$E$12,3) -> 3.3614 | E19: =_xlfn.XLOOKUP(C19,'ETF - Liste'!E:E,'ETF - Liste'!B:B) -> Lyxor STOXX Europe Comm. Services | F19: {=_xlfn.TEXTJOIN(", ",TRUE,IF(C19='Aktieliste USA'!F:F,'Aktieliste USA'!G:G,""))}
B20: 4 | C20: =_xlfn.XLOOKUP(D20,$E$2:$E$12,$B$2:$B$12) -> Industrials | D20: =LARGE($E$2:$E$12,4) -> 3.3613 | E20: =_xlfn.XLOOKUP(C20,'ETF - Liste'!E:E,'ETF - Liste'!B:B) -> iShares MSCI World Industrials | F20: {=_xlfn.TEXTJOIN(", ",TRUE,IF(C20='Aktieliste USA'!F:F,'Aktieliste USA'!G:G,""))} -> CAT, GE, MMM, RTX
B21: 5 | C21: =_xlfn.XLOOKUP(D21,$E$2:$E$12,$B$2:$B$12) -> Financials | D21: =LARGE($E$2:$E$12,5) -> 3.2502 | E21: =_xlfn.XLOOKUP(C21,'ETF - Liste'!E:E,'ETF - Liste'!B:B) -> iShares MSCI World Financials | F21: {=_xlfn.TEXTJOIN(", ",TRUE,IF(C21='Aktieliste USA'!F:F,'Aktieliste USA'!G:G,""))} -> BAC, AXP, WFC, JPM, MA, V, BRK.B
B22: 6 | C22: =_xlfn.XLOOKUP(D22,$E$2:$E$12,$B$2:$B$12) -> Real Estate | D22: =LARGE($E$2:$E$12,6) -> 3.167 | E22: =_xlfn.XLOOKUP(C22,'ETF - Liste'!E:E,'ETF - Liste'!B:B) -> SPDR Dow Jones Global Real Estate | F22: {=_xlfn.TEXTJOIN(", ",TRUE,IF(C22='Aktieliste USA'!F:F,'Aktieliste USA'!G:G,""))} -> WELL
B23: 7 | C23: =_xlfn.XLOOKUP(D23,$E$2:$E$12,$B$2:$B$12) -> Consumer Staples | D23: =LARGE($E$2:$E$12,7) -> 3.056 | E23: =_xlfn.XLOOKUP(C23,'ETF - Liste'!E:E,'ETF - Liste'!B:B) -> iShares MSCI Consumer Staples | F23: {=_xlfn.TEXTJOIN(", ",TRUE,IF(C23='Aktieliste USA'!F:F,'Aktieliste USA'!G:G,""))} -> COST, WMT, PEP, KO
B24: 8 | C24: =_xlfn.XLOOKUP(D24,$E$2:$E$12,$B$2:$B$12) -> Consumer Staples | D24: =LARGE($E$2:$E$12,8) -> 3.056 | E24: =_xlfn.XLOOKUP(C24,'ETF - Liste'!E:E,'ETF - Liste'!B:B) -> iShares MSCI Consumer Staples | F24: {=_xlfn.TEXTJOIN(", ",TRUE,IF(C24='Aktieliste USA'!F:F,'Aktieliste USA'!G:G,""))} -> COST, WMT, PEP, KO
B25: 9 | C25: =_xlfn.XLOOKUP(D25,$E$2:$E$12,$B$2:$B$12) -> Health Care | D25: =LARGE($E$2:$E$12,9) -> 2.8892 | E25: =_xlfn.XLOOKUP(C25,'ETF - Liste'!E:E,'ETF - Liste'!B:B) -> iShares Global Healthcare ETF | F25: {=_xlfn.TEXTJOIN(", ",TRUE,IF(C25='Aktieliste USA'!F:F,'Aktieliste USA'!G:G,""))} -> ABT, AMGN, PFE, UNH, LLY, ABBV, MRK
B26: 10 | C26: =_xlfn.XLOOKUP(D26,$E$2:$E$12,$B$2:$B$12) -> Materials | D26: =LARGE($E$2:$E$12,10) -> 2.7503 | E26: =_xlfn.XLOOKUP(C26,'ETF - Liste'!E:E,'ETF - Liste'!B:B) -> Lyxor MSCI World Materials | F26: {=_xlfn.TEXTJOIN(", ",TRUE,IF(C26='Aktieliste USA'!F:F,'Aktieliste USA'!G:G,""))}
B27: 11 | C27: =_xlfn.XLOOKUP(D27,$E$2:$E$12,$B$2:$B$12) -> Consumer Discretionary | D27: =LARGE($E$2:$E$12,11) -> 2.7501 | E27: =_xlfn.XLOOKUP(C27,'ETF - Liste'!E:E,'ETF - Liste'!B:B) -> iShares Global Consumer Discretionary | F27: {=_xlfn.TEXTJOIN(", ",TRUE,IF(C27='Aktieliste USA'!F:F,'Aktieliste USA'!G:G,""))} -> TSLA, AMZN, NKE, HD, SBUX, MCD
B31: =F1 -> Q2 2026
B32: Nr. | C32: Sektor | D32: Markedscore | E32: ETF | F32: Aktier
B33: 1 | C33: =_xlfn.XLOOKUP(D33,$F$2:$F$12,$B$2:$B$12) -> Information Technology | D33: =LARGE($F$2:$F$12,1) -> 4.2504 | E33: =_xlfn.XLOOKUP(C33,'ETF - Liste'!E:E,'ETF - Liste'!B:B) -> Invesco Nasdaq-100 UCITS | F33: {=_xlfn.TEXTJOIN(", ",TRUE,IF(C33='Aktieliste USA'!F:F,'Aktieliste USA'!G:G,""))} -> NVDA, ORCL, ADBE, INTC, CRM, INTU, AVGO, QCOM, AAPL, MSFT, TXN, CSCO
B34: 2 | C34: =_xlfn.XLOOKUP(D34,$F$2:$F$12,$B$2:$B$12) -> Communications Services | D34: =LARGE($F$2:$F$12,2) -> 3.7226 | E34: =_xlfn.XLOOKUP(C34,'ETF - Liste'!E:E,'ETF - Liste'!B:B) -> Lyxor STOXX Europe Comm. Services | F34: {=_xlfn.TEXTJOIN(", ",TRUE,IF(C34='Aktieliste USA'!F:F,'Aktieliste USA'!G:G,""))}
B35: 3 | C35: =_xlfn.XLOOKUP(D35,$F$2:$F$12,$B$2:$B$12) -> Consumer Discretionary | D35: =LARGE($F$2:$F$12,3) -> 3.4725 | E35: =_xlfn.XLOOKUP(C35,'ETF - Liste'!E:E,'ETF - Liste'!B:B) -> iShares Global Consumer Discretionary | F35: {=_xlfn.TEXTJOIN(", ",TRUE,IF(C35='Aktieliste USA'!F:F,'Aktieliste USA'!G:G,""))} -> TSLA, AMZN, NKE, HD, SBUX, MCD
B36: 4 | C36: =_xlfn.XLOOKUP(D36,$F$2:$F$12,$B$2:$B$12) -> Consumer Discretionary | D36: =LARGE($F$2:$F$12,4) -> 3.4725 | E36: =_xlfn.XLOOKUP(C36,'ETF - Liste'!E:E,'ETF - Liste'!B:B) -> iShares Global Consumer Discretionary | F36: {=_xlfn.TEXTJOIN(", ",TRUE,IF(C36='Aktieliste USA'!F:F,'Aktieliste USA'!G:G,""))} -> TSLA, AMZN, NKE, HD, SBUX, MCD
B37: 5 | C37: =_xlfn.XLOOKUP(D37,$F$2:$F$12,$B$2:$B$12) -> Financials | D37: =LARGE($F$2:$F$12,5) -> 3.3614 | E37: =_xlfn.XLOOKUP(C37,'ETF - Liste'!E:E,'ETF - Liste'!B:B) -> iShares MSCI World Financials | F37: {=_xlfn.TEXTJOIN(", ",TRUE,IF(C37='Aktieliste USA'!F:F,'Aktieliste USA'!G:G,""))} -> BAC, AXP, WFC, JPM, MA, V, BRK.B
B38: 6 | C38: =_xlfn.XLOOKUP(D38,$F$2:$F$12,$B$2:$B$12) -> Energy | D38: =LARGE($F$2:$F$12,6) -> 3.2226 | E38: =_xlfn.XLOOKUP(C38,'ETF - Liste'!E:E,'ETF - Liste'!B:B) -> SPDR MSCI World Energy | F38: {=_xlfn.TEXTJOIN(", ",TRUE,IF(C38='Aktieliste USA'!F:F,'Aktieliste USA'!G:G,""))} -> CVX, XOM
B39: 7 | C39: =_xlfn.XLOOKUP(D39,$F$2:$F$12,$B$2:$B$12) -> Health Care | D39: =LARGE($F$2:$F$12,7) -> 2.8892 | E39: =_xlfn.XLOOKUP(C39,'ETF - Liste'!E:E,'ETF - Liste'!B:B) -> iShares Global Healthcare ETF | F39: {=_xlfn.TEXTJOIN(", ",TRUE,IF(C39='Aktieliste USA'!F:F,'Aktieliste USA'!G:G,""))} -> ABT, AMGN, PFE, UNH, LLY, ABBV, MRK
B40: 8 | C40: =_xlfn.XLOOKUP(D40,$F$2:$F$12,$B$2:$B$12) -> Real Estate | D40: =LARGE($F$2:$F$12,8) -> 2.5002 | E40: =_xlfn.XLOOKUP(C40,'ETF - Liste'!E:E,'ETF - Liste'!B:B) -> SPDR Dow Jones Global Real Estate | F40: {=_xlfn.TEXTJOIN(", ",TRUE,IF(C40='Aktieliste USA'!F:F,'Aktieliste USA'!G:G,""))} -> WELL
B41: 9 | C41: =_xlfn.XLOOKUP(D41,$F$2:$F$12,$B$2:$B$12) -> Consumer Staples | D41: =LARGE($F$2:$F$12,9) -> 2.3336 | E41: =_xlfn.XLOOKUP(C41,'ETF - Liste'!E:E,'ETF - Liste'!B:B) -> iShares MSCI Consumer Staples | F41: {=_xlfn.TEXTJOIN(", ",TRUE,IF(C41='Aktieliste USA'!F:F,'Aktieliste USA'!G:G,""))} -> COST, WMT, PEP, KO
B42: 10 | C42: =_xlfn.XLOOKUP(D42,$F$2:$F$12,$B$2:$B$12) -> Consumer Staples | D42: =LARGE($F$2:$F$12,10) -> 2.3336 | E42: =_xlfn.XLOOKUP(C42,'ETF - Liste'!E:E,'ETF - Liste'!B:B) -> iShares MSCI Consumer Staples | F42: {=_xlfn.TEXTJOIN(", ",TRUE,IF(C42='Aktieliste USA'!F:F,'Aktieliste USA'!G:G,""))} -> COST, WMT, PEP, KO
B43: 11 | C43: =_xlfn.XLOOKUP(D43,$F$2:$F$12,$B$2:$B$12) -> Materials | D43: =LARGE($F$2:$F$12,11) -> 2.0835 | E43: =_xlfn.XLOOKUP(C43,'ETF - Liste'!E:E,'ETF - Liste'!B:B) -> Lyxor MSCI World Materials | F43: {=_xlfn.TEXTJOIN(", ",TRUE,IF(C43='Aktieliste USA'!F:F,'Aktieliste USA'!G:G,""))}

Sheet Risikoprofiler -> 

Sheet  Profil
C3: Hvis jeg invester: | D3: 50000 | E3: DKK
B6: =Profiler!#REF! -> #REF! | H6: Obligationer 60%, ETF 20%, Aktier 10%, Alternative 10%
B7: Kategori | C7: Markedscore | D7: ETF | E7: Aktier
B8: =_xlfn.XLOOKUP(C8,#REF!,#REF!) -> #REF! | C8: =LARGE(#REF!,1) -> #REF! | D8: =_xlfn.XLOOKUP(B8,'ETF - Liste'!E:E,'ETF - Liste'!B:B) -> #REF! | E8: =IFERROR(_xlfn.XLOOKUP(B8,'Aktieliste DK'!F:F,'Aktieliste DK'!H:H),"")
B9: =_xlfn.XLOOKUP(C9,C1:C1,B1:B1) -> #REF! | C9: =LARGE(#REF!,2) -> #REF! | D9: =_xlfn.XLOOKUP(B9,'ETF - Liste'!E:E,'ETF - Liste'!B:B) -> #REF! | E9: =IFERROR(_xlfn.XLOOKUP(B9,'Aktieliste DK'!F:F,'Aktieliste DK'!H:H),"")
B10: =_xlfn.XLOOKUP(C10,#REF!,#REF!) -> #REF! | C10: =LARGE(#REF!,3) -> #REF! | D10: =_xlfn.XLOOKUP(B10,'ETF - Liste'!E:E,'ETF - Liste'!B:B) -> #REF! | E10: =IFERROR(_xlfn.XLOOKUP(B10,'Aktieliste DK'!F:F,'Aktieliste DK'!H:H),"")
B13: =Profiler!A2 -> Konservativ
B14: Sektor | C14: Markedscore | D14: ETF | E14: Aktier
B15: =_xlfn.XLOOKUP(C15,#REF!,#REF!) -> #REF! | C15: =SMALL(#REF!,1) -> #REF! | D15: =_xlfn.XLOOKUP(B15,'ETF - Liste'!E:E,'ETF - Liste'!B:B) -> #REF! | E15: =IFERROR(_xlfn.XLOOKUP(B15,'Aktieliste DK'!F:F,'Aktieliste DK'!H:H),"")
B16: =_xlfn.XLOOKUP(C16,#REF!,#REF!) -> #REF! | C16: =SMALL(#REF!,2) -> #REF! | D16: =_xlfn.XLOOKUP(B16,'ETF - Liste'!E:E,'ETF - Liste'!B:B) -> #REF! | E16: =IFERROR(_xlfn.XLOOKUP(B16,'Aktieliste DK'!F:F,'Aktieliste DK'!H:H),"")
B17: =_xlfn.XLOOKUP(C17,#REF!,#REF!) -> #REF! | C17: =SMALL(#REF!,3) -> #REF! | D17: =_xlfn.XLOOKUP(B17,'ETF - Liste'!E:E,'ETF - Liste'!B:B) -> #REF! | E17: =IFERROR(_xlfn.XLOOKUP(B17,'Aktieliste DK'!F:F,'Aktieliste DK'!H:H),"")
B21: =Profiler!A3 -> Balanceret
B22: Sektor | C22: Markedscore | D22: ETF | E22: Aktier
B23: =_xlfn.XLOOKUP(C23,#REF!,#REF!) -> #REF! | C23: =SMALL(#REF!,1) -> #REF! | D23: =_xlfn.XLOOKUP(B23,'ETF - Liste'!E:E,'ETF - Liste'!B:B) -> #REF! | E23: =IFERROR(_xlfn.XLOOKUP(B23,'Aktieliste DK'!F:F,'Aktieliste DK'!H:H),"")
B24: =_xlfn.XLOOKUP(C24,#REF!,#REF!) -> #REF! | C24: =SMALL(#REF!,2) -> #REF! | D24: =_xlfn.XLOOKUP(B24,'ETF - Liste'!E:E,'ETF - Liste'!B:B) -> #REF! | E24: =IFERROR(_xlfn.XLOOKUP(B24,'Aktieliste DK'!F:F,'Aktieliste DK'!H:H),"")
B25: =_xlfn.XLOOKUP(C25,#REF!,#REF!) -> #REF! | C25: =SMALL(#REF!,3) -> #REF! | D25: =_xlfn.XLOOKUP(B25,'ETF - Liste'!E:E,'ETF - Liste'!B:B) -> #REF! | E25: =IFERROR(_xlfn.XLOOKUP(B25,'Aktieliste DK'!F:F,'Aktieliste DK'!H:H),"")
B29: =Profiler!A4 -> Vækstorienteret
B30: Sektor | C30: Markedscore | D30: ETF | E30: Aktier
B31: =_xlfn.XLOOKUP(C31,#REF!,#REF!) -> #REF! | C31: =SMALL(#REF!,1) -> #REF! | D31: =_xlfn.XLOOKUP(B31,'ETF - Liste'!E:E,'ETF - Liste'!B:B) -> #REF! | E31: =IFERROR(_xlfn.XLOOKUP(B31,'Aktieliste DK'!F:F,'Aktieliste DK'!H:H),"")
B32: =_xlfn.XLOOKUP(C32,#REF!,#REF!) -> #REF! | C32: =SMALL(#REF!,2) -> #REF! | D32: =_xlfn.XLOOKUP(B32,'ETF - Liste'!E:E,'ETF - Liste'!B:B) -> #REF! | E32: =IFERROR(_xlfn.XLOOKUP(B32,'Aktieliste DK'!F:F,'Aktieliste DK'!H:H),"")
B33: =_xlfn.XLOOKUP(C33,#REF!,#REF!) -> #REF! | C33: =SMALL(#REF!,3) -> #REF! | D33: =_xlfn.XLOOKUP(B33,'ETF - Liste'!E:E,'ETF - Liste'!B:B) -> #REF! | E33: =IFERROR(_xlfn.XLOOKUP(B33,'Aktieliste DK'!F:F,'Aktieliste DK'!H:H),"")
B36: =Profiler!A5 -> Dynamisk
B37: Sektor | C37: Markedscore | D37: ETF | E37: Aktier
B38: =_xlfn.XLOOKUP(C38,#REF!,#REF!) -> #REF! | C38: =SMALL(#REF!,1) -> #REF! | D38: =_xlfn.XLOOKUP(B38,'ETF - Liste'!E:E,'ETF - Liste'!B:B) -> #REF! | E38: =IFERROR(_xlfn.XLOOKUP(B38,'Aktieliste DK'!F:F,'Aktieliste DK'!H:H),"")
B39: =_xlfn.XLOOKUP(C39,#REF!,#REF!) -> #REF! | C39: =SMALL(#REF!,2) -> #REF! | D39: =_xlfn.XLOOKUP(B39,'ETF - Liste'!E:E,'ETF - Liste'!B:B) -> #REF! | E39: =IFERROR(_xlfn.XLOOKUP(B39,'Aktieliste DK'!F:F,'Aktieliste DK'!H:H),"")
B40: =_xlfn.XLOOKUP(C40,#REF!,#REF!) -> #REF! | C40: =SMALL(#REF!,3) -> #REF! | D40: =_xlfn.XLOOKUP(B40,'ETF - Liste'!E:E,'ETF - Liste'!B:B) -> #REF! | E40: =IFERROR(_xlfn.XLOOKUP(B40,'Aktieliste DK'!F:F,'Aktieliste DK'!H:H),"")
B43: =Profiler!#REF! -> #REF!
B44: Sektor | C44: Markedscore | D44: ETF | E44: Aktier
B45: =_xlfn.XLOOKUP(C45,#REF!,#REF!) -> #REF! | C45: =SMALL(#REF!,1) -> #REF! | D45: =_xlfn.XLOOKUP(B45,'ETF - Liste'!E:E,'ETF - Liste'!B:B) -> #REF! | E45: =IFERROR(_xlfn.XLOOKUP(B45,'Aktieliste DK'!F:F,'Aktieliste DK'!H:H),"")
B46: =_xlfn.XLOOKUP(C46,#REF!,#REF!) -> #REF! | C46: =SMALL(#REF!,2) -> #REF! | D46: =_xlfn.XLOOKUP(B46,'ETF - Liste'!E:E,'ETF - Liste'!B:B) -> #REF! | E46: =IFERROR(_xlfn.XLOOKUP(B46,'Aktieliste DK'!F:F,'Aktieliste DK'!H:H),"")
B47: =_xlfn.XLOOKUP(C47,#REF!,#REF!) -> #REF! | C47: =SMALL(#REF!,3) -> #REF! | D47: =_xlfn.XLOOKUP(B47,'ETF - Liste'!E:E,'ETF - Liste'!B:B) -> #REF! | E47: =IFERROR(_xlfn.XLOOKUP(B47,'Aktieliste DK'!F:F,'Aktieliste DK'!H:H),"")

Sheet Spørgeskema
A1: Spørgsmål | B1: Svar 1 | C1: Svar 2 | D1: Svar 3 | E1: Svar 4 | F1: Score 1 | G1: Score 2 | H1: Score 3 | I1: Score 4 | J1: Brugerens Valg (indtast 1-4)
A2: 1. Hvor lang tid ønsker du at investere? | B2: 0–3 år | C2: 3–5 år | D2: 5–10 år | E2: 10+ år | F2: 1 | G2: 2 | H2: 3 | I2: 5
A3: 2. Hvor stor andel af dine opsparing investerer du? | B3: 0–10% | C3: 10–30% | D3: 30–50% | E3: 50%+ | F3: 1 | G3: 2 | H3: 3 | I3: 5
A4: 3. Hvordan reagerer du, hvis din portefølje falder 20% på 1 måned? | B4: Sælger alt | C4: Reducerer | D4: Holder | E4: Køber mere | F4: 1 | G4: 2 | H4: 3 | I4: 5
A5: 4. Hvor vigtigt er stabilt afkast vs. højt afkast? | B5: Stabilt | C5: Balanceret | E5: Højt afkast | F5: 1 | G5: 2 | H5: 3 | I5: 5
A6: 5. Hvad er din erfaring med investering? | B6: Ingen | C6: Lidt | D6: En del | E6: Meget | F6: 1 | G6: 2 | H6: 3 | I6: 5
A7: 6. Hvilket mål har du? | B7: Kapitalbevarelse | C7: Indkomst | E7: Vækst | F7: 1 | G7: 2 | H7: 3 | I7: 5
A8: 7. Hvor ofte følger du dine investeringer? | B8: Aldrig | C8: Årligt | D8: Kvartalsvis | E8: Ugentligt | F8: 1 | G8: 2 | H8: 3 | I8: 5
A9: 8. Hvor stor buffer har du uden for investering? | B9: <1 måned | C9: 1–3 mdr. | D9: 3–6 mdr. | E9: 6+ mdr. | F9: 1 | G9: 2 | H9: 3 | I9: 5

Sheet Profiler
A1: Profilnavn | B1: Score interval (fra) | C1: Score interval (til) | D1: Beskrivelse | E1: Aktivfordeling | F1: Alternativer (eksempler)
A2: Konservativ | B2: 0.3 | C2: 0.45 | D2: Lav risiko. Overvej guld og stabile alternativer udover ETF'er. | E2: Obligationer 50%, ETF 25%, Aktier 15%, Alternative 10% | F2: Guld, råvarer
A3: Balanceret | B3: 0.45 | C3: 0.6 | D3: Balanceret risiko. ETF’er kombineres med lidt guld og råvarer. | E3: Obligationer 0%, ETF 55%, Aktier 35%, Alternative 10% | F3: Guld, råvarer
A4: Vækstorienteret | B4: 0.6 | C4: 0.75 | D4: Vækstfokus. Mulighed for mindre eksponering mod bitcoin og råvarer. | E4: Obligationer 0%, ETF 35%, Aktier 50%, Alternative 15% | F4: Bitcoin, guld, råvarer
A5: Dynamisk | B5: 0.75 | C5: 0.85 | D5: Større risiko. Brug af både aktier og alternative investeringer (inkl. krypto). | E5: Obligationer 0%, ETF 15%, Aktier 70%, Alternative 15% | F5: Bitcoin, guld, ejendom

Sheet Markoscore ->

Sheet Fremtid vækst
B1: Markovækst
B3: Danmark | C3: Q1 2026 | D3: Q2 2026
B4: BNP | C4: 0.02 | D4: 0.019
B5: PMI | C5: 52 | D5: 52.5
B6: 10 YR rate | C6: 3 | D6: 3.05
B7: CPI | C7: 0.02 | D7: 0.019
B8: Baltic Dry Index | C8: 1 760 | D8: 1 800
B9: VIX | C9: 15 | D9: 17
B10: Currency (EUR/USD) | C10: 1.17 | D10: 1.18
B11: Unemployment | C11: 0.033 | D11: 0.033
B15: Europa | C15: =C3 -> Q1 2026 | D15: =D3 -> Q2 2026
B16: BNP | C16: 0.012 | D16: 0.013
B17: PMI | C17: 52.4 | D17: 52.3
B18: 10 YR rate | C18: 2.9 | D18: 2.95
B19: CPI | C19: 0.019 | D19: 0.018
B20: Baltic Dry Index | C20: 1 760 | D20: 1 800
B21: VIX | C21: 15 | D21: 17
B22: Currency (EUR/USD) | C22: 1.17 | D22: 1.18
B23: Unemployment | C23: 0.063 | D23: 0.062
B27: USA | C27: =C15 -> Q1 2026 | D27: =D15 -> Q2 2026
B28: BNP | C28: 0.017 | D28: 0.018
B29: PMI | C29: 52.8 | D29: 52.5
B30: 10 YR rate | C30: 4.2 | D30: 4.25
B31: CPI | C31: 0.027 | D31: 0.026
B32: Baltic Dry Index | C32: 1 760 | D32: 1 850
B33: VIX | C33: 15 | D33: 17
B34: Currency (EUR/USD) | C34: 1.17 | D34: 1.18
B35: Unemployment | C35: 0.044 | D35: 0.044

Sheet Makro analyse
K29: ='Fremtid vækst'!$C$3 -> Q1 2026 | T29: ='Fremtid vækst'!$D$3 -> Q2 2026
B30: Danmark | C30: PMI | D30: BNP | E30: 10 YR | F30: CPI | G30: Baltic Dry Index | H30: VIX | I30: Currency | J30: Unemployment | K30: Makro score | L30: PMI | M30: BNP | N30: 10 YR | O30: CPI | P30: Baltic Dry Index | Q30: VIX | R30: Currency | S30: Unemployment | T30: Makro score
B31: Financials | C31: =IF(PMI!$F$31=PMI!$B$43,PMI!$B44,IF(PMI!$F$31=PMI!$C$43,PMI!$C44,IF(PMI!$F$31=PMI!$D$43,PMI!$D44,IF(PMI!$F$31=PMI!$E$43,PMI!$E44,1)))) -> 4 | D31: =BNP!I86 -> 3 | E31: =IF('10 yr rate'!$E$30='10 yr rate'!$B$35,'10 yr rate'!$B36,IF('10 yr rate'!$E$30='10 yr rate'!$C$35,'10 yr rate'!$C36,IF('10 yr rate'!$E$30='10 yr rate'!$D$35,'10 yr rate'!$D36,IF('10 yr rate'!$E$30='10 yr rate'!$E$35,'10 yr rate'!$E36,1)))) -> 4 | F31: =IF('CPI(Inflation)'!$E$9='CPI(Inflation)'!$B$33,'CPI(Inflation)'!$B34,IF('CPI(Inflation)'!$E$9='CPI(Inflation)'!$C$33,'CPI(Inflation)'!$C34,IF('CPI(Inflation)'!$E$9='CPI(Inflation)'!$D$33,'CPI(Inflation)'!$D34,IF('CPI(Inflation)'!$E$9='CPI(Inflation)'!$E$33,'CPI(Inflation)'!$E34,1)))) -> 4 | G31: ='Baltic Dry Index'!B34 -> 4 | H31: =IF(VIX!$F$25=VIX!$B$33,VIX!B34,IF(VIX!$F$25=VIX!$C$33,VIX!C34,IF(VIX!$F$25=VIX!$D$33,VIX!D34,IF(VIX!$F$25=VIX!$E$33,VIX!E34,1)))) -> 4 | I31: =IF(Currency!$F$25=Currency!$B$33,Currency!B34,IF(Currency!$F$25=Currency!$C$33,Currency!C34,IF(Currency!$F$25=Currency!$D$33,Currency!D34,IF(Currency!$F$25=Currency!$E$33,Currency!E34,1)))) -> 2 | J31: =IF(Unemployment!$F$25=Unemployment!$B$33,Unemployment!B34,IF(Unemployment!$F$25=Unemployment!$C$33,Unemployment!C34,IF(Unemployment!$F$25=Unemployment!$D$33,Unemployment!D34,IF(Unemployment!$F$25=Unemployment!$E$33,Unemployment!E34,1)))) -> 4 | K31: =AVERAGE(C31*0.2222 + D31*0.3056 + E31*0.1667 + F31*0.1389 + I31*0.0556 + J31*0.1111) -> 3.5836 | L31: =IF(PMI!$F$32=PMI!$B$43,PMI!$B44,IF(PMI!$F$32=PMI!$C$43,PMI!$C44,IF(PMI!$F$32=PMI!$D$43,PMI!$D44,IF(PMI!$F$32=PMI!$E$43,PMI!$E44,1)))) -> 4 | M31: =BNP!J86 -> 3 | N31: =IF('10 yr rate'!$E$31='10 yr rate'!$B$35,'10 yr rate'!$B36,IF('10 yr rate'!$E$31='10 yr rate'!$C$35,'10 yr rate'!$C36,IF('10 yr rate'!$E$31='10 yr rate'!$D$35,'10 yr rate'!$D36,IF('10 yr rate'!$E$31='10 yr rate'!$E$35,'10 yr rate'!$E36,1)))) -> 4 | O31: =IF('CPI(Inflation)'!$E$10='CPI(Inflation)'!$B$33,'CPI(Inflation)'!$B34,IF('CPI(Inflation)'!$E$10='CPI(Inflation)'!$C$33,'CPI(Inflation)'!$C34,IF('CPI(Inflation)'!$E$10='CPI(Inflation)'!$D$33,'CPI(Inflation)'!$D34,IF('CPI(Inflation)'!$E$10='CPI(Inflation)'!$E$33,'CPI(Inflation)'!$E34,1)))) -> 4 | P31: ='Baltic Dry Index'!B34 -> 4 | Q31: =IF(VIX!$F$26=VIX!$B$33,VIX!B34,IF(VIX!$F$26=VIX!$C$33,VIX!C34,IF(VIX!$F$26=VIX!$D$33,VIX!D34,IF(VIX!$F$26=VIX!$E$33,VIX!E34,1)))) -> 1 | R31: =IF(Currency!$F$26=Currency!$B$33,Currency!B34,IF(Currency!$F$26=Currency!$C$33,Currency!C34,IF(Currency!$F$26=Currency!$D$33,Currency!D34,IF(Currency!$F$26=Currency!$E$33,Currency!E34,1)))) -> 4 | S31: =IF(Unemployment!$F$26=Unemployment!$B$33,Unemployment!B34,IF(Unemployment!$F$26=Unemployment!$C$33,Unemployment!C34,IF(Unemployment!$F$26=Unemployment!$D$33,Unemployment!D34,IF(Unemployment!$F$26=Unemployment!$E$33,Unemployment!E34,1)))) -> 4 | T31: =AVERAGE(L31*0.2222 + M31*0.3056 + N31*0.1667 + O31*0.1389 + R31*0.0556 + S31*0.1111) -> 3.6948
B32: Real Estate | C32: =IF(PMI!$F$31=PMI!$B$43,PMI!$B45,IF(PMI!$F$31=PMI!$C$43,PMI!$C45,IF(PMI!$F$31=PMI!$D$43,PMI!$D45,IF(PMI!$F$31=PMI!$E$43,PMI!$E45,1)))) -> 2 | D32: =BNP!I91 -> 2 | E32: =IF('10 yr rate'!$E$30='10 yr rate'!$B$35,'10 yr rate'!$B37,IF('10 yr rate'!$E$30='10 yr rate'!$C$35,'10 yr rate'!$C37,IF('10 yr rate'!$E$30='10 yr rate'!$D$35,'10 yr rate'!$D37,IF('10 yr rate'!$E$30='10 yr rate'!$E$35,'10 yr rate'!$E37,1)))) -> 2 | F32: =IF('CPI(Inflation)'!$E$9='CPI(Inflation)'!$B$33,'CPI(Inflation)'!$B35,IF('CPI(Inflation)'!$E$9='CPI(Inflation)'!$C$33,'CPI(Inflation)'!$C35,IF('CPI(Inflation)'!$E$9='CPI(Inflation)'!$D$33,'CPI(Inflation)'!$D35,IF('CPI(Inflation)'!$E$9='CPI(Inflation)'!$E$33,'CPI(Inflation)'!$E35,1)))) -> 2 | G32: ='Baltic Dry Index'!B35 -> 5 | H32: =IF(VIX!$F$25=VIX!$B$33,VIX!B35,IF(VIX!$F$25=VIX!$C$33,VIX!C35,IF(VIX!$F$25=VIX!$D$33,VIX!D35,IF(VIX!$F$25=VIX!$E$33,VIX!E35,1)))) -> 5 | I32: =IF(Currency!$F$25=Currency!$B$33,Currency!B35,IF(Currency!$F$25=Currency!$C$33,Currency!C35,IF(Currency!$F$25=Currency!$D$33,Currency!D35,IF(Currency!$F$25=Currency!$E$33,Currency!E35,1)))) -> 3 | J32: =IF(Unemployment!$F$25=Unemployment!$B$33,Unemployment!B35,IF(Unemployment!$F$25=Unemployment!$C$33,Unemployment!C35,IF(Unemployment!$F$25=Unemployment!$D$33,Unemployment!D35,IF(Unemployment!$F$25=Unemployment!$E$33,Unemployment!E35,1)))) -> 5 | K32: =AVERAGE(C32*0.2222 + D32*0.3056 + E32*0.1667 + F32*0.1389 + I32*0.0556 + J32*0.1111) -> 2.3891 | L32: =IF(PMI!$F$32=PMI!$B$43,PMI!$B45,IF(PMI!$F$32=PMI!$C$43,PMI!$C45,IF(PMI!$F$32=PMI!$D$43,PMI!$D45,IF(PMI!$F$32=PMI!$E$43,PMI!$E45,1)))) -> 2 | M32: =BNP!J91 -> 4 | N32: =IF('10 yr rate'!$E$31='10 yr rate'!$B$35,'10 yr rate'!$B37,IF('10 yr rate'!$E$31='10 yr rate'!$C$35,'10 yr rate'!$C37,IF('10 yr rate'!$E$31='10 yr rate'!$D$35,'10 yr rate'!$D37,IF('10 yr rate'!$E$31='10 yr rate'!$E$35,'10 yr rate'!$E37,1)))) -> 2 | O32: =IF('CPI(Inflation)'!$E$10='CPI(Inflation)'!$B$33,'CPI(Inflation)'!$B35,IF('CPI(Inflation)'!$E$10='CPI(Inflation)'!$C$33,'CPI(Inflation)'!$C35,IF('CPI(Inflation)'!$E$10='CPI(Inflation)'!$D$33,'CPI(Inflation)'!$D35,IF('CPI(Inflation)'!$E$10='CPI(Inflation)'!$E$33,'CPI(Inflation)'!$E35,1)))) -> 5 | P32: ='Baltic Dry Index'!B35 -> 5 | Q32: =IF(VIX!$F$26=VIX!$B$33,VIX!B35,IF(VIX!$F$26=VIX!$C$33,VIX!C35,IF(VIX!$F$26=VIX!$D$33,VIX!D35,IF(VIX!$F$26=VIX!$E$33,VIX!E35,1)))) -> 1 | R32: =IF(Currency!$F$26=Currency!$B$33,Currency!B35,IF(Currency!$F$26=Currency!$C$33,Currency!C35,IF(Currency!$F$26=Currency!$D$33,Currency!D35,IF(Currency!$F$26=Currency!$E$33,Currency!E35,1)))) -> 2 | S32: =IF(Unemployment!$F$26=Unemployment!$B$33,Unemployment!B35,IF(Unemployment!$F$26=Unemployment!$C$33,Unemployment!C35,IF(Unemployment!$F$26=Unemployment!$D$33,Unemployment!D35,IF(Unemployment!$F$26=Unemployment!$E$33,Unemployment!E35,1)))) -> 5 | T32: =AVERAGE(L32*0.2222 + M32*0.3056 + N32*0.1667 + O32*0.1389 + R32*0.0556 + S32*0.1111) -> 3.3614
B33: Consumer Discretionary | C33: =IF(PMI!$F$31=PMI!$B$43,PMI!$B46,IF(PMI!$F$31=PMI!$C$43,PMI!$C46,IF(PMI!$F$31=PMI!$D$43,PMI!$D46,IF(PMI!$F$31=PMI!$E$43,PMI!$E46,1)))) -> 4 | D33: =BNP!I96 -> 3 | E33: =IF('10 yr rate'!$E$30='10 yr rate'!$B$35,'10 yr rate'!$B38,IF('10 yr rate'!$E$30='10 yr rate'!$C$35,'10 yr rate'!$C38,IF('10 yr rate'!$E$30='10 yr rate'!$D$35,'10 yr rate'!$D38,IF('10 yr rate'!$E$30='10 yr rate'!$E$35,'10 yr rate'!$E38,1)))) -> 4 | F33: =IF('CPI(Inflation)'!$E$9='CPI(Inflation)'!$B$33,'CPI(Inflation)'!$B36,IF('CPI(Inflation)'!$E$9='CPI(Inflation)'!$C$33,'CPI(Inflation)'!$C36,IF('CPI(Inflation)'!$E$9='CPI(Inflation)'!$D$33,'CPI(Inflation)'!$D36,IF('CPI(Inflation)'!$E$9='CPI(Inflation)'!$E$33,'CPI(Inflation)'!$E36,1)))) -> 4 | G33: ='Baltic Dry Index'!B36 -> 5 | H33: =IF(VIX!$F$25=VIX!$B$33,VIX!B36,IF(VIX!$F$25=VIX!$C$33,VIX!C36,IF(VIX!$F$25=VIX!$D$33,VIX!D36,IF(VIX!$F$25=VIX!$E$33,VIX!E36,1)))) -> 5 | I33: =IF(Currency!$F$25=Currency!$B$33,Currency!B36,IF(Currency!$F$25=Currency!$C$33,Currency!C36,IF(Currency!$F$25=Currency!$D$33,Currency!D36,IF(Currency!$F$25=Currency!$E$33,Currency!E36,1)))) -> 2 | J33: =IF(Unemployment!$F$25=Unemployment!$B$33,Unemployment!B36,IF(Unemployment!$F$25=Unemployment!$C$33,Unemployment!C36,IF(Unemployment!$F$25=Unemployment!$D$33,Unemployment!D36,IF(Unemployment!$F$25=Unemployment!$E$33,Unemployment!E36,1)))) -> 5 | K33: =AVERAGE(C33*0.2222 + D33*0.3056 + E33*0.1667 + F33*0.1389 + I33*0.0556 + J33*0.1111) -> 3.6947 | L33: =IF(PMI!$F$32=PMI!$B$43,PMI!$B46,IF(PMI!$F$32=PMI!$C$43,PMI!$C46,IF(PMI!$F$32=PMI!$D$43,PMI!$D46,IF(PMI!$F$32=PMI!$E$43,PMI!$E46,1)))) -> 4 | M33: =BNP!J96 -> 1 | N33: =IF('10 yr rate'!$E$31='10 yr rate'!$B$35,'10 yr rate'!$B38,IF('10 yr rate'!$E$31='10 yr rate'!$C$35,'10 yr rate'!$C38,IF('10 yr rate'!$E$31='10 yr rate'!$D$35,'10 yr rate'!$D38,IF('10 yr rate'!$E$31='10 yr rate'!$E$35,'10 yr rate'!$E38,1)))) -> 4 | O33: =IF('CPI(Inflation)'!$E$10='CPI(Inflation)'!$B$33,'CPI(Inflation)'!$B36,IF('CPI(Inflation)'!$E$10='CPI(Inflation)'!$C$33,'CPI(Inflation)'!$C36,IF('CPI(Inflation)'!$E$10='CPI(Inflation)'!$D$33,'CPI(Inflation)'!$D36,IF('CPI(Inflation)'!$E$10='CPI(Inflation)'!$E$33,'CPI(Inflation)'!$E36,1)))) -> 5 | P33: ='Baltic Dry Index'!B36 -> 5 | Q33: =IF(VIX!$F$26=VIX!$B$33,VIX!B36,IF(VIX!$F$26=VIX!$C$33,VIX!C36,IF(VIX!$F$26=VIX!$D$33,VIX!D36,IF(VIX!$F$26=VIX!$E$33,VIX!E36,1)))) -> 1 | R33: =IF(Currency!$F$26=Currency!$B$33,Currency!B36,IF(Currency!$F$26=Currency!$C$33,Currency!C36,IF(Currency!$F$26=Currency!$D$33,Currency!D36,IF(Currency!$F$26=Currency!$E$33,Currency!E36,1)))) -> 4 | S33: =IF(Unemployment!$F$26=Unemployment!$B$33,Unemployment!B36,IF(Unemployment!$F$26=Unemployment!$C$33,Unemployment!C36,IF(Unemployment!$F$26=Unemployment!$D$33,Unemployment!D36,IF(Unemployment!$F$26=Unemployment!$E$33,Unemployment!E36,1)))) -> 5 | T33: =AVERAGE(L33*0.2222 + M33*0.3056 + N33*0.1667 + O33*0.1389 + R33*0.0556 + S33*0.1111) -> 3.3336
B34: Information Technology | C34: =IF(PMI!$F$31=PMI!$B$43,PMI!$B47,IF(PMI!$F$31=PMI!$C$43,PMI!$C47,IF(PMI!$F$31=PMI!$D$43,PMI!$D47,IF(PMI!$F$31=PMI!$E$43,PMI!$E47,1)))) -> 5 | D34: =BNP!I101 -> 4 | E34: =IF('10 yr rate'!$E$30='10 yr rate'!$B$35,'10 yr rate'!$B39,IF('10 yr rate'!$E$30='10 yr rate'!$C$35,'10 yr rate'!$C39,IF('10 yr rate'!$E$30='10 yr rate'!$D$35,'10 yr rate'!$D39,IF('10 yr rate'!$E$30='10 yr rate'!$E$35,'10 yr rate'!$E39,1)))) -> 5 | F34: =IF('CPI(Inflation)'!$E$9='CPI(Inflation)'!$B$33,'CPI(Inflation)'!$B37,IF('CPI(Inflation)'!$E$9='CPI(Inflation)'!$C$33,'CPI(Inflation)'!$C37,IF('CPI(Inflation)'!$E$9='CPI(Inflation)'!$D$33,'CPI(Inflation)'!$D37,IF('CPI(Inflation)'!$E$9='CPI(Inflation)'!$E$33,'CPI(Inflation)'!$E37,1)))) -> 5 | G34: ='Baltic Dry Index'!B37 -> 4 | H34: =IF(VIX!$F$25=VIX!$B$33,VIX!B37,IF(VIX!$F$25=VIX!$C$33,VIX!C37,IF(VIX!$F$25=VIX!$D$33,VIX!D37,IF(VIX!$F$25=VIX!$E$33,VIX!E37,1)))) -> 4 | I34: =IF(Currency!$F$25=Currency!$B$33,Currency!B37,IF(Currency!$F$25=Currency!$C$33,Currency!C37,IF(Currency!$F$25=Currency!$D$33,Currency!D37,IF(Currency!$F$25=Currency!$E$33,Currency!E37,1)))) -> 3 | J34: =IF(Unemployment!$F$25=Unemployment!$B$33,Unemployment!B37,IF(Unemployment!$F$25=Unemployment!$C$33,Unemployment!C37,IF(Unemployment!$F$25=Unemployment!$D$33,Unemployment!D37,IF(Unemployment!$F$25=Unemployment!$E$33,Unemployment!E37,1)))) -> 4 | K34: =AVERAGE(C34*0.2222 + D34*0.3056 + E34*0.1667 + F34*0.1389 + I34*0.0556 + J34*0.1111) -> 4.4726 | L34: =IF(PMI!$F$32=PMI!$B$43,PMI!$B47,IF(PMI!$F$32=PMI!$C$43,PMI!$C47,IF(PMI!$F$32=PMI!$D$43,PMI!$D47,IF(PMI!$F$32=PMI!$E$43,PMI!$E47,1)))) -> 5 | M34: =BNP!J101 -> 2 | N34: =IF('10 yr rate'!$E$31='10 yr rate'!$B$35,'10 yr rate'!$B39,IF('10 yr rate'!$E$31='10 yr rate'!$C$35,'10 yr rate'!$C39,IF('10 yr rate'!$E$31='10 yr rate'!$D$35,'10 yr rate'!$D39,IF('10 yr rate'!$E$31='10 yr rate'!$E$35,'10 yr rate'!$E39,1)))) -> 5 | O34: =IF('CPI(Inflation)'!$E$10='CPI(Inflation)'!$B$33,'CPI(Inflation)'!$B37,IF('CPI(Inflation)'!$E$10='CPI(Inflation)'!$C$33,'CPI(Inflation)'!$C37,IF('CPI(Inflation)'!$E$10='CPI(Inflation)'!$D$33,'CPI(Inflation)'!$D37,IF('CPI(Inflation)'!$E$10='CPI(Inflation)'!$E$33,'CPI(Inflation)'!$E37,1)))) -> 4 | P34: ='Baltic Dry Index'!B37 -> 4 | Q34: =IF(VIX!$F$26=VIX!$B$33,VIX!B37,IF(VIX!$F$26=VIX!$C$33,VIX!C37,IF(VIX!$F$26=VIX!$D$33,VIX!D37,IF(VIX!$F$26=VIX!$E$33,VIX!E37,1)))) -> 1 | R34: =IF(Currency!$F$26=Currency!$B$33,Currency!B37,IF(Currency!$F$26=Currency!$C$33,Currency!C37,IF(Currency!$F$26=Currency!$D$33,Currency!D37,IF(Currency!$F$26=Currency!$E$33,Currency!E37,1)))) -> 5 | S34: =IF(Unemployment!$F$26=Unemployment!$B$33,Unemployment!B37,IF(Unemployment!$F$26=Unemployment!$C$33,Unemployment!C37,IF(Unemployment!$F$26=Unemployment!$D$33,Unemployment!D37,IF(Unemployment!$F$26=Unemployment!$E$33,Unemployment!E37,1)))) -> 4 | T34: =AVERAGE(L34*0.2222 + M34*0.3056 + N34*0.1667 + O34*0.1389 + R34*0.0556 + S34*0.1111) -> 3.8337
B35: Industrials | C35: =IF(PMI!$F$31=PMI!$B$43,PMI!$B48,IF(PMI!$F$31=PMI!$C$43,PMI!$C48,IF(PMI!$F$31=PMI!$D$43,PMI!$D48,IF(PMI!$F$31=PMI!$E$43,PMI!$E48,1)))) -> 4 | D35: =BNP!I106 -> 3 | E35: =IF('10 yr rate'!$E$30='10 yr rate'!$B$35,'10 yr rate'!$B40,IF('10 yr rate'!$E$30='10 yr rate'!$C$35,'10 yr rate'!$C40,IF('10 yr rate'!$E$30='10 yr rate'!$D$35,'10 yr rate'!$D40,IF('10 yr rate'!$E$30='10 yr rate'!$E$35,'10 yr rate'!$E40,1)))) -> 4 | F35: =IF('CPI(Inflation)'!$E$9='CPI(Inflation)'!$B$33,'CPI(Inflation)'!$B38,IF('CPI(Inflation)'!$E$9='CPI(Inflation)'!$C$33,'CPI(Inflation)'!$C38,IF('CPI(Inflation)'!$E$9='CPI(Inflation)'!$D$33,'CPI(Inflation)'!$D38,IF('CPI(Inflation)'!$E$9='CPI(Inflation)'!$E$33,'CPI(Inflation)'!$E38,1)))) -> 4 | G35: ='Baltic Dry Index'!B38 -> 5 | H35: =IF(VIX!$F$25=VIX!$B$33,VIX!B38,IF(VIX!$F$25=VIX!$C$33,VIX!C38,IF(VIX!$F$25=VIX!$D$33,VIX!D38,IF(VIX!$F$25=VIX!$E$33,VIX!E38,1)))) -> 5 | I35: =IF(Currency!$F$25=Currency!$B$33,Currency!B38,IF(Currency!$F$25=Currency!$C$33,Currency!C38,IF(Currency!$F$25=Currency!$D$33,Currency!D38,IF(Currency!$F$25=Currency!$E$33,Currency!E38,1)))) -> 2 | J35: =IF(Unemployment!$F$25=Unemployment!$B$33,Unemployment!B38,IF(Unemployment!$F$25=Unemployment!$C$33,Unemployment!C38,IF(Unemployment!$F$25=Unemployment!$D$33,Unemployment!D38,IF(Unemployment!$F$25=Unemployment!$E$33,Unemployment!E38,1)))) -> 5 | K35: =AVERAGE(C35*0.2222 + D35*0.3056 + E35*0.1667 + F35*0.1389 + I35*0.0556 + J35*0.1111) -> 3.6947 | L35: =IF(PMI!$F$32=PMI!$B$43,PMI!$B48,IF(PMI!$F$32=PMI!$C$43,PMI!$C48,IF(PMI!$F$32=PMI!$D$43,PMI!$D48,IF(PMI!$F$32=PMI!$E$43,PMI!$E48,1)))) -> 4 | M35: =BNP!J106 -> 3 | N35: =IF('10 yr rate'!$E$31='10 yr rate'!$B$35,'10 yr rate'!$B40,IF('10 yr rate'!$E$31='10 yr rate'!$C$35,'10 yr rate'!$C40,IF('10 yr rate'!$E$31='10 yr rate'!$D$35,'10 yr rate'!$D40,IF('10 yr rate'!$E$31='10 yr rate'!$E$35,'10 yr rate'!$E40,1)))) -> 4 | O35: =IF('CPI(Inflation)'!$E$10='CPI(Inflation)'!$B$33,'CPI(Inflation)'!$B38,IF('CPI(Inflation)'!$E$10='CPI(Inflation)'!$C$33,'CPI(Inflation)'!$C38,IF('CPI(Inflation)'!$E$10='CPI(Inflation)'!$D$33,'CPI(Inflation)'!$D38,IF('CPI(Inflation)'!$E$10='CPI(Inflation)'!$E$33,'CPI(Inflation)'!$E38,1)))) -> 5 | P35: ='Baltic Dry Index'!B38 -> 5 | Q35: =IF(VIX!$F$26=VIX!$B$33,VIX!B38,IF(VIX!$F$26=VIX!$C$33,VIX!C38,IF(VIX!$F$26=VIX!$D$33,VIX!D38,IF(VIX!$F$26=VIX!$E$33,VIX!E38,1)))) -> 1 | R35: =IF(Currency!$F$26=Currency!$B$33,Currency!B38,IF(Currency!$F$26=Currency!$C$33,Currency!C38,IF(Currency!$F$26=Currency!$D$33,Currency!D38,IF(Currency!$F$26=Currency!$E$33,Currency!E38,1)))) -> 4 | S35: =IF(Unemployment!$F$26=Unemployment!$B$33,Unemployment!B38,IF(Unemployment!$F$26=Unemployment!$C$33,Unemployment!C38,IF(Unemployment!$F$26=Unemployment!$D$33,Unemployment!D38,IF(Unemployment!$F$26=Unemployment!$E$33,Unemployment!E38,1)))) -> 5 | T35: =AVERAGE(L35*0.2222 + M35*0.3056 + N35*0.1667 + O35*0.1389 + R35*0.0556 + S35*0.1111) -> 3.9448
B36: Materials | C36: =IF(PMI!$F$31=PMI!$B$43,PMI!$B49,IF(PMI!$F$31=PMI!$C$43,PMI!$C49,IF(PMI!$F$31=PMI!$D$43,PMI!$D49,IF(PMI!$F$31=PMI!$E$43,PMI!$E49,1)))) -> 2 | D36: =BNP!I116 -> 2 | E36: =IF('10 yr rate'!$E$30='10 yr rate'!$B$35,'10 yr rate'!$B41,IF('10 yr rate'!$E$30='10 yr rate'!$C$35,'10 yr rate'!$C41,IF('10 yr rate'!$E$30='10 yr rate'!$D$35,'10 yr rate'!$D41,IF('10 yr rate'!$E$30='10 yr rate'!$E$35,'10 yr rate'!$E41,1)))) -> 2 | F36: =IF('CPI(Inflation)'!$E$9='CPI(Inflation)'!$B$33,'CPI(Inflation)'!$B39,IF('CPI(Inflation)'!$E$9='CPI(Inflation)'!$C$33,'CPI(Inflation)'!$C39,IF('CPI(Inflation)'!$E$9='CPI(Inflation)'!$D$33,'CPI(Inflation)'!$D39,IF('CPI(Inflation)'!$E$9='CPI(Inflation)'!$E$33,'CPI(Inflation)'!$E39,1)))) -> 2 | G36: ='Baltic Dry Index'!B39 -> 4 | H36: =IF(VIX!$F$25=VIX!$B$33,VIX!B39,IF(VIX!$F$25=VIX!$C$33,VIX!C39,IF(VIX!$F$25=VIX!$D$33,VIX!D39,IF(VIX!$F$25=VIX!$E$33,VIX!E39,1)))) -> 4 | I36: =IF(Currency!$F$25=Currency!$B$33,Currency!B39,IF(Currency!$F$25=Currency!$C$33,Currency!C39,IF(Currency!$F$25=Currency!$D$33,Currency!D39,IF(Currency!$F$25=Currency!$E$33,Currency!E39,1)))) -> 3 | J36: =IF(Unemployment!$F$25=Unemployment!$B$33,Unemployment!B39,IF(Unemployment!$F$25=Unemployment!$C$33,Unemployment!C39,IF(Unemployment!$F$25=Unemployment!$D$33,Unemployment!D39,IF(Unemployment!$F$25=Unemployment!$E$33,Unemployment!E39,1)))) -> 4 | K36: =AVERAGE(C36*0.2222 + D36*0.3056 + E36*0.1667 + F36*0.1389 + I36*0.0556 + J36*0.1111) -> 2.278 | L36: =IF(PMI!$F$32=PMI!$B$43,PMI!$B49,IF(PMI!$F$32=PMI!$C$43,PMI!$C49,IF(PMI!$F$32=PMI!$D$43,PMI!$D49,IF(PMI!$F$32=PMI!$E$43,PMI!$E49,1)))) -> 2 | M36: =BNP!J116 -> 4 | N36: =IF('10 yr rate'!$E$31='10 yr rate'!$B$35,'10 yr rate'!$B41,IF('10 yr rate'!$E$31='10 yr rate'!$C$35,'10 yr rate'!$C41,IF('10 yr rate'!$E$31='10 yr rate'!$D$35,'10 yr rate'!$D41,IF('10 yr rate'!$E$31='10 yr rate'!$E$35,'10 yr rate'!$E41,1)))) -> 2 | O36: =IF('CPI(Inflation)'!$E$10='CPI(Inflation)'!$B$33,'CPI(Inflation)'!$B39,IF('CPI(Inflation)'!$E$10='CPI(Inflation)'!$C$33,'CPI(Inflation)'!$C39,IF('CPI(Inflation)'!$E$10='CPI(Inflation)'!$D$33,'CPI(Inflation)'!$D39,IF('CPI(Inflation)'!$E$10='CPI(Inflation)'!$E$33,'CPI(Inflation)'!$E39,1)))) -> 4 | P36: ='Baltic Dry Index'!B39 -> 4 | Q36: =IF(VIX!$F$26=VIX!$B$33,VIX!B39,IF(VIX!$F$26=VIX!$C$33,VIX!C39,IF(VIX!$F$26=VIX!$D$33,VIX!D39,IF(VIX!$F$26=VIX!$E$33,VIX!E39,1)))) -> 2 | R36: =IF(Currency!$F$26=Currency!$B$33,Currency!B39,IF(Currency!$F$26=Currency!$C$33,Currency!C39,IF(Currency!$F$26=Currency!$D$33,Currency!D39,IF(Currency!$F$26=Currency!$E$33,Currency!E39,1)))) -> 2 | S36: =IF(Unemployment!$F$26=Unemployment!$B$33,Unemployment!B39,IF(Unemployment!$F$26=Unemployment!$C$33,Unemployment!C39,IF(Unemployment!$F$26=Unemployment!$D$33,Unemployment!D39,IF(Unemployment!$F$26=Unemployment!$E$33,Unemployment!E39,1)))) -> 4 | T36: =AVERAGE(L36*0.2222 + M36*0.3056 + N36*0.1667 + O36*0.1389 + R36*0.0556 + S36*0.1111) -> 3.1114
B37: Consumer Staples | C37: =IF(PMI!$F$31=PMI!$B$43,PMI!$B50,IF(PMI!$F$31=PMI!$C$43,PMI!$C50,IF(PMI!$F$31=PMI!$D$43,PMI!$D50,IF(PMI!$F$31=PMI!$E$43,PMI!$E50,1)))) -> 2 | D37: =BNP!I121 -> 3 | E37: =IF('10 yr rate'!$E$30='10 yr rate'!$B$35,'10 yr rate'!$B42,IF('10 yr rate'!$E$30='10 yr rate'!$C$35,'10 yr rate'!$C42,IF('10 yr rate'!$E$30='10 yr rate'!$D$35,'10 yr rate'!$D42,IF('10 yr rate'!$E$30='10 yr rate'!$E$35,'10 yr rate'!$E42,1)))) -> 2 | F37: =IF('CPI(Inflation)'!$E$9='CPI(Inflation)'!$B$33,'CPI(Inflation)'!$B40,IF('CPI(Inflation)'!$E$9='CPI(Inflation)'!$C$33,'CPI(Inflation)'!$C40,IF('CPI(Inflation)'!$E$9='CPI(Inflation)'!$D$33,'CPI(Inflation)'!$D40,IF('CPI(Inflation)'!$E$9='CPI(Inflation)'!$E$33,'CPI(Inflation)'!$E40,1)))) -> 2 | G37: ='Baltic Dry Index'!B40 -> 2 | H37: =IF(VIX!$F$25=VIX!$B$33,VIX!B40,IF(VIX!$F$25=VIX!$C$33,VIX!C40,IF(VIX!$F$25=VIX!$D$33,VIX!D40,IF(VIX!$F$25=VIX!$E$33,VIX!E40,1)))) -> 2 | I37: =IF(Currency!$F$25=Currency!$B$33,Currency!B40,IF(Currency!$F$25=Currency!$C$33,Currency!C40,IF(Currency!$F$25=Currency!$D$33,Currency!D40,IF(Currency!$F$25=Currency!$E$33,Currency!E40,1)))) -> 4 | J37: =IF(Unemployment!$F$25=Unemployment!$B$33,Unemployment!B40,IF(Unemployment!$F$25=Unemployment!$C$33,Unemployment!C40,IF(Unemployment!$F$25=Unemployment!$D$33,Unemployment!D40,IF(Unemployment!$F$25=Unemployment!$E$33,Unemployment!E40,1)))) -> 2 | K37: =AVERAGE(C37*0.2222 + D37*0.3056 + E37*0.1667 + F37*0.1389 + I37*0.0556 + J37*0.1111) -> 2.417 | L37: =IF(PMI!$F$32=PMI!$B$43,PMI!$B50,IF(PMI!$F$32=PMI!$C$43,PMI!$C50,IF(PMI!$F$32=PMI!$D$43,PMI!$D50,IF(PMI!$F$32=PMI!$E$43,PMI!$E50,1)))) -> 2 | M37: =BNP!J121 -> 3 | N37: =IF('10 yr rate'!$E$31='10 yr rate'!$B$35,'10 yr rate'!$B42,IF('10 yr rate'!$E$31='10 yr rate'!$C$35,'10 yr rate'!$C42,IF('10 yr rate'!$E$31='10 yr rate'!$D$35,'10 yr rate'!$D42,IF('10 yr rate'!$E$31='10 yr rate'!$E$35,'10 yr rate'!$E42,1)))) -> 2 | O37: =IF('CPI(Inflation)'!$E$10='CPI(Inflation)'!$B$33,'CPI(Inflation)'!$B40,IF('CPI(Inflation)'!$E$10='CPI(Inflation)'!$C$33,'CPI(Inflation)'!$C40,IF('CPI(Inflation)'!$E$10='CPI(Inflation)'!$D$33,'CPI(Inflation)'!$D40,IF('CPI(Inflation)'!$E$10='CPI(Inflation)'!$E$33,'CPI(Inflation)'!$E40,1)))) -> 2 | P37: ='Baltic Dry Index'!B40 -> 2 | Q37: =IF(VIX!$F$26=VIX!$B$33,VIX!B40,IF(VIX!$F$26=VIX!$C$33,VIX!C40,IF(VIX!$F$26=VIX!$D$33,VIX!D40,IF(VIX!$F$26=VIX!$E$33,VIX!E40,1)))) -> 5 | R37: =IF(Currency!$F$26=Currency!$B$33,Currency!B40,IF(Currency!$F$26=Currency!$C$33,Currency!C40,IF(Currency!$F$26=Currency!$D$33,Currency!D40,IF(Currency!$F$26=Currency!$E$33,Currency!E40,1)))) -> 2 | S37: =IF(Unemployment!$F$26=Unemployment!$B$33,Unemployment!B40,IF(Unemployment!$F$26=Unemployment!$C$33,Unemployment!C40,IF(Unemployment!$F$26=Unemployment!$D$33,Unemployment!D40,IF(Unemployment!$F$26=Unemployment!$E$33,Unemployment!E40,1)))) -> 2 | T37: =AVERAGE(L37*0.2222 + M37*0.3056 + N37*0.1667 + O37*0.1389 + R37*0.0556 + S37*0.1111) -> 2.3058
B38: Health Care | C38: =IF(PMI!$F$31=PMI!$B$43,PMI!$B51,IF(PMI!$F$31=PMI!$C$43,PMI!$C51,IF(PMI!$F$31=PMI!$D$43,PMI!$D51,IF(PMI!$F$31=PMI!$E$43,PMI!$E51,1)))) -> 3 | D38: =BNP!I121 -> 3 | E38: =IF('10 yr rate'!$E$30='10 yr rate'!$B$35,'10 yr rate'!$B43,IF('10 yr rate'!$E$30='10 yr rate'!$C$35,'10 yr rate'!$C43,IF('10 yr rate'!$E$30='10 yr rate'!$D$35,'10 yr rate'!$D43,IF('10 yr rate'!$E$30='10 yr rate'!$E$35,'10 yr rate'!$E43,1)))) -> 3 | F38: =IF('CPI(Inflation)'!$E$9='CPI(Inflation)'!$B$33,'CPI(Inflation)'!$B41,IF('CPI(Inflation)'!$E$9='CPI(Inflation)'!$C$33,'CPI(Inflation)'!$C41,IF('CPI(Inflation)'!$E$9='CPI(Inflation)'!$D$33,'CPI(Inflation)'!$D41,IF('CPI(Inflation)'!$E$9='CPI(Inflation)'!$E$33,'CPI(Inflation)'!$E41,1)))) -> 3 | G38: ='Baltic Dry Index'!B41 -> 2 | H38: =IF(VIX!$F$25=VIX!$B$33,VIX!B41,IF(VIX!$F$25=VIX!$C$33,VIX!C41,IF(VIX!$F$25=VIX!$D$33,VIX!D41,IF(VIX!$F$25=VIX!$E$33,VIX!E41,1)))) -> 2 | I38: =IF(Currency!$F$25=Currency!$B$33,Currency!B41,IF(Currency!$F$25=Currency!$C$33,Currency!C41,IF(Currency!$F$25=Currency!$D$33,Currency!D41,IF(Currency!$F$25=Currency!$E$33,Currency!E41,1)))) -> 3 | J38: =IF(Unemployment!$F$25=Unemployment!$B$33,Unemployment!B41,IF(Unemployment!$F$25=Unemployment!$C$33,Unemployment!C41,IF(Unemployment!$F$25=Unemployment!$D$33,Unemployment!D41,IF(Unemployment!$F$25=Unemployment!$E$33,Unemployment!E41,1)))) -> 2 | K38: =AVERAGE(C38*0.2222 + D38*0.3056 + E38*0.1667 + F38*0.1389 + I38*0.0556 + J38*0.1111) -> 2.8892 | L38: =IF(PMI!$F$32=PMI!$B$43,PMI!$B51,IF(PMI!$F$32=PMI!$C$43,PMI!$C51,IF(PMI!$F$32=PMI!$D$43,PMI!$D51,IF(PMI!$F$32=PMI!$E$43,PMI!$E51,1)))) -> 3 | M38: =BNP!J121 -> 3 | N38: =IF('10 yr rate'!$E$31='10 yr rate'!$B$35,'10 yr rate'!$B43,IF('10 yr rate'!$E$31='10 yr rate'!$C$35,'10 yr rate'!$C43,IF('10 yr rate'!$E$31='10 yr rate'!$D$35,'10 yr rate'!$D43,IF('10 yr rate'!$E$31='10 yr rate'!$E$35,'10 yr rate'!$E43,1)))) -> 3 | O38: =IF('CPI(Inflation)'!$E$10='CPI(Inflation)'!$B$33,'CPI(Inflation)'!$B41,IF('CPI(Inflation)'!$E$10='CPI(Inflation)'!$C$33,'CPI(Inflation)'!$C41,IF('CPI(Inflation)'!$E$10='CPI(Inflation)'!$D$33,'CPI(Inflation)'!$D41,IF('CPI(Inflation)'!$E$10='CPI(Inflation)'!$E$33,'CPI(Inflation)'!$E41,1)))) -> 2 | P38: ='Baltic Dry Index'!B41 -> 2 | Q38: =IF(VIX!$F$26=VIX!$B$33,VIX!B41,IF(VIX!$F$26=VIX!$C$33,VIX!C41,IF(VIX!$F$26=VIX!$D$33,VIX!D41,IF(VIX!$F$26=VIX!$E$33,VIX!E41,1)))) -> 5 | R38: =IF(Currency!$F$26=Currency!$B$33,Currency!B41,IF(Currency!$F$26=Currency!$C$33,Currency!C41,IF(Currency!$F$26=Currency!$D$33,Currency!D41,IF(Currency!$F$26=Currency!$E$33,Currency!E41,1)))) -> 3 | S38: =IF(Unemployment!$F$26=Unemployment!$B$33,Unemployment!B41,IF(Unemployment!$F$26=Unemployment!$C$33,Unemployment!C41,IF(Unemployment!$F$26=Unemployment!$D$33,Unemployment!D41,IF(Unemployment!$F$26=Unemployment!$E$33,Unemployment!E41,1)))) -> 2 | T38: =AVERAGE(L38*0.2222 + M38*0.3056 + N38*0.1667 + O38*0.1389 + R38*0.0556 + S38*0.1111) -> 2.7503
B39: Energy | C39: =IF(PMI!$F$31=PMI!$B$43,PMI!$B52,IF(PMI!$F$31=PMI!$C$43,PMI!$C52,IF(PMI!$F$31=PMI!$D$43,PMI!$D52,IF(PMI!$F$31=PMI!$E$43,PMI!$E52,1)))) -> 3 | D39: =BNP!I126 -> 3 | E39: =IF('10 yr rate'!$E$30='10 yr rate'!$B$35,'10 yr rate'!$B44,IF('10 yr rate'!$E$30='10 yr rate'!$C$35,'10 yr rate'!$C44,IF('10 yr rate'!$E$30='10 yr rate'!$D$35,'10 yr rate'!$D44,IF('10 yr rate'!$E$30='10 yr rate'!$E$35,'10 yr rate'!$E44,1)))) -> 3 | F39: =IF('CPI(Inflation)'!$E$9='CPI(Inflation)'!$B$33,'CPI(Inflation)'!$B42,IF('CPI(Inflation)'!$E$9='CPI(Inflation)'!$C$33,'CPI(Inflation)'!$C42,IF('CPI(Inflation)'!$E$9='CPI(Inflation)'!$D$33,'CPI(Inflation)'!$D42,IF('CPI(Inflation)'!$E$9='CPI(Inflation)'!$E$33,'CPI(Inflation)'!$E42,1)))) -> 3 | G39: ='Baltic Dry Index'!B42 -> 2 | H39: =IF(VIX!$F$25=VIX!$B$33,VIX!B42,IF(VIX!$F$25=VIX!$C$33,VIX!C42,IF(VIX!$F$25=VIX!$D$33,VIX!D42,IF(VIX!$F$25=VIX!$E$33,VIX!E42,1)))) -> 2 | I39: =IF(Currency!$F$25=Currency!$B$33,Currency!B42,IF(Currency!$F$25=Currency!$C$33,Currency!C42,IF(Currency!$F$25=Currency!$D$33,Currency!D42,IF(Currency!$F$25=Currency!$E$33,Currency!E42,1)))) -> 5 | J39: =IF(Unemployment!$F$25=Unemployment!$B$33,Unemployment!B42,IF(Unemployment!$F$25=Unemployment!$C$33,Unemployment!C42,IF(Unemployment!$F$25=Unemployment!$D$33,Unemployment!D42,IF(Unemployment!$F$25=Unemployment!$E$33,Unemployment!E42,1)))) -> 2 | K39: =AVERAGE(C39*0.2222 + D39*0.3056 + E39*0.1667 + F39*0.1389 + I39*0.0556 + J39*0.1111) -> 3.0004 | L39: =IF(PMI!$F$32=PMI!$B$43,PMI!$B52,IF(PMI!$F$32=PMI!$C$43,PMI!$C52,IF(PMI!$F$32=PMI!$D$43,PMI!$D52,IF(PMI!$F$32=PMI!$E$43,PMI!$E52,1)))) -> 3 | M39: =BNP!J126 -> 5 | N39: =IF('10 yr rate'!$E$31='10 yr rate'!$B$35,'10 yr rate'!$B44,IF('10 yr rate'!$E$31='10 yr rate'!$C$35,'10 yr rate'!$C44,IF('10 yr rate'!$E$31='10 yr rate'!$D$35,'10 yr rate'!$D44,IF('10 yr rate'!$E$31='10 yr rate'!$E$35,'10 yr rate'!$E44,1)))) -> 3 | O39: =IF('CPI(Inflation)'!$E$10='CPI(Inflation)'!$B$33,'CPI(Inflation)'!$B42,IF('CPI(Inflation)'!$E$10='CPI(Inflation)'!$C$33,'CPI(Inflation)'!$C42,IF('CPI(Inflation)'!$E$10='CPI(Inflation)'!$D$33,'CPI(Inflation)'!$D42,IF('CPI(Inflation)'!$E$10='CPI(Inflation)'!$E$33,'CPI(Inflation)'!$E42,1)))) -> 2 | P39: ='Baltic Dry Index'!B42 -> 2 | Q39: =IF(VIX!$F$26=VIX!$B$33,VIX!B42,IF(VIX!$F$26=VIX!$C$33,VIX!C42,IF(VIX!$F$26=VIX!$D$33,VIX!D42,IF(VIX!$F$26=VIX!$E$33,VIX!E42,1)))) -> 1 | R39: =IF(Currency!$F$26=Currency!$B$33,Currency!B42,IF(Currency!$F$26=Currency!$C$33,Currency!C42,IF(Currency!$F$26=Currency!$D$33,Currency!D42,IF(Currency!$F$26=Currency!$E$33,Currency!E42,1)))) -> 3 | S39: =IF(Unemployment!$F$26=Unemployment!$B$33,Unemployment!B42,IF(Unemployment!$F$26=Unemployment!$C$33,Unemployment!C42,IF(Unemployment!$F$26=Unemployment!$D$33,Unemployment!D42,IF(Unemployment!$F$26=Unemployment!$E$33,Unemployment!E42,1)))) -> 2 | T39: =AVERAGE(L39*0.2222 + M39*0.3056 + N39*0.1667 + O39*0.1389 + R39*0.0556 + S39*0.1111) -> 3.3615
B40: Communications Services | C40: =IF(PMI!$F$31=PMI!$B$43,PMI!$B53,IF(PMI!$F$31=PMI!$C$43,PMI!$C53,IF(PMI!$F$31=PMI!$D$43,PMI!$D53,IF(PMI!$F$31=PMI!$E$43,PMI!$E53,1)))) -> 4 | D40: =BNP!I131 -> 4 | E40: =IF('10 yr rate'!$E$30='10 yr rate'!$B$35,'10 yr rate'!$B45,IF('10 yr rate'!$E$30='10 yr rate'!$C$35,'10 yr rate'!$C45,IF('10 yr rate'!$E$30='10 yr rate'!$D$35,'10 yr rate'!$D45,IF('10 yr rate'!$E$30='10 yr rate'!$E$35,'10 yr rate'!$E45,1)))) -> 4 | F40: =IF('CPI(Inflation)'!$E$9='CPI(Inflation)'!$B$33,'CPI(Inflation)'!$B43,IF('CPI(Inflation)'!$E$9='CPI(Inflation)'!$C$33,'CPI(Inflation)'!$C43,IF('CPI(Inflation)'!$E$9='CPI(Inflation)'!$D$33,'CPI(Inflation)'!$D43,IF('CPI(Inflation)'!$E$9='CPI(Inflation)'!$E$33,'CPI(Inflation)'!$E43,1)))) -> 4 | G40: ='Baltic Dry Index'!B43 -> 3 | H40: =IF(VIX!$F$25=VIX!$B$33,VIX!B43,IF(VIX!$F$25=VIX!$C$33,VIX!C43,IF(VIX!$F$25=VIX!$D$33,VIX!D43,IF(VIX!$F$25=VIX!$E$33,VIX!E43,1)))) -> 3 | I40: =IF(Currency!$F$25=Currency!$B$33,Currency!B43,IF(Currency!$F$25=Currency!$C$33,Currency!C43,IF(Currency!$F$25=Currency!$D$33,Currency!D43,IF(Currency!$F$25=Currency!$E$33,Currency!E43,1)))) -> 3 | J40: =IF(Unemployment!$F$25=Unemployment!$B$33,Unemployment!B43,IF(Unemployment!$F$25=Unemployment!$C$33,Unemployment!C43,IF(Unemployment!$F$25=Unemployment!$D$33,Unemployment!D43,IF(Unemployment!$F$25=Unemployment!$E$33,Unemployment!E43,1)))) -> 3 | K40: =AVERAGE(C40*0.2222 + D40*0.3056 + E40*0.1667 + F40*0.1389 + I40*0.0556 + J40*0.1111) -> 3.8337 | L40: =IF(PMI!$F$32=PMI!$B$43,PMI!$B53,IF(PMI!$F$32=PMI!$C$43,PMI!$C53,IF(PMI!$F$32=PMI!$D$43,PMI!$D53,IF(PMI!$F$32=PMI!$E$43,PMI!$E53,1)))) -> 4 | M40: =BNP!J131 -> 3 | N40: =IF('10 yr rate'!$E$31='10 yr rate'!$B$35,'10 yr rate'!$B45,IF('10 yr rate'!$E$31='10 yr rate'!$C$35,'10 yr rate'!$C45,IF('10 yr rate'!$E$31='10 yr rate'!$D$35,'10 yr rate'!$D45,IF('10 yr rate'!$E$31='10 yr rate'!$E$35,'10 yr rate'!$E45,1)))) -> 4 | O40: =IF('CPI(Inflation)'!$E$10='CPI(Inflation)'!$B$33,'CPI(Inflation)'!$B43,IF('CPI(Inflation)'!$E$10='CPI(Inflation)'!$C$33,'CPI(Inflation)'!$C43,IF('CPI(Inflation)'!$E$10='CPI(Inflation)'!$D$33,'CPI(Inflation)'!$D43,IF('CPI(Inflation)'!$E$10='CPI(Inflation)'!$E$33,'CPI(Inflation)'!$E43,1)))) -> 3 | P40: ='Baltic Dry Index'!B43 -> 3 | Q40: =IF(VIX!$F$26=VIX!$B$33,VIX!B43,IF(VIX!$F$26=VIX!$C$33,VIX!C43,IF(VIX!$F$26=VIX!$D$33,VIX!D43,IF(VIX!$F$26=VIX!$E$33,VIX!E43,1)))) -> 2 | R40: =IF(Currency!$F$26=Currency!$B$33,Currency!B43,IF(Currency!$F$26=Currency!$C$33,Currency!C43,IF(Currency!$F$26=Currency!$D$33,Currency!D43,IF(Currency!$F$26=Currency!$E$33,Currency!E43,1)))) -> 4 | S40: =IF(Unemployment!$F$26=Unemployment!$B$33,Unemployment!B43,IF(Unemployment!$F$26=Unemployment!$C$33,Unemployment!C43,IF(Unemployment!$F$26=Unemployment!$D$33,Unemployment!D43,IF(Unemployment!$F$26=Unemployment!$E$33,Unemployment!E43,1)))) -> 3 | T40: =AVERAGE(L40*0.2222 + M40*0.3056 + N40*0.1667 + O40*0.1389 + R40*0.0556 + S40*0.1111) -> 3.4448
B41: Utilities | C41: =IF(PMI!$F$31=PMI!$B$43,PMI!$B54,IF(PMI!$F$31=PMI!$C$43,PMI!$C54,IF(PMI!$F$31=PMI!$D$43,PMI!$D54,IF(PMI!$F$31=PMI!$E$43,PMI!$E54,1)))) -> 2 | D41: =BNP!I136 -> 2 | E41: =IF('10 yr rate'!$E$30='10 yr rate'!$B$35,'10 yr rate'!$B46,IF('10 yr rate'!$E$30='10 yr rate'!$C$35,'10 yr rate'!$C46,IF('10 yr rate'!$E$30='10 yr rate'!$D$35,'10 yr rate'!$D46,IF('10 yr rate'!$E$30='10 yr rate'!$E$35,'10 yr rate'!$E46,1)))) -> 2 | F41: =IF('CPI(Inflation)'!$E$9='CPI(Inflation)'!$B$33,'CPI(Inflation)'!$B44,IF('CPI(Inflation)'!$E$9='CPI(Inflation)'!$C$33,'CPI(Inflation)'!$C44,IF('CPI(Inflation)'!$E$9='CPI(Inflation)'!$D$33,'CPI(Inflation)'!$D44,IF('CPI(Inflation)'!$E$9='CPI(Inflation)'!$E$33,'CPI(Inflation)'!$E44,1)))) -> 2 | G41: ='Baltic Dry Index'!B44 -> 2 | H41: =IF(VIX!$F$25=VIX!$B$33,VIX!B44,IF(VIX!$F$25=VIX!$C$33,VIX!C44,IF(VIX!$F$25=VIX!$D$33,VIX!D44,IF(VIX!$F$25=VIX!$E$33,VIX!E44,1)))) -> 2 | I41: =IF(Currency!$F$25=Currency!$B$33,Currency!B44,IF(Currency!$F$25=Currency!$C$33,Currency!C44,IF(Currency!$F$25=Currency!$D$33,Currency!D44,IF(Currency!$F$25=Currency!$E$33,Currency!E44,1)))) -> 4 | J41: =IF(Unemployment!$F$25=Unemployment!$B$33,Unemployment!B44,IF(Unemployment!$F$25=Unemployment!$C$33,Unemployment!C44,IF(Unemployment!$F$25=Unemployment!$D$33,Unemployment!D44,IF(Unemployment!$F$25=Unemployment!$E$33,Unemployment!E44,1)))) -> 2 | K41: =AVERAGE(C41*0.2222 + D41*0.3056 + E41*0.1667 + F41*0.1389 + I41*0.0556 + J41*0.1111) -> 2.1114 | L41: =IF(PMI!$F$32=PMI!$B$43,PMI!$B54,IF(PMI!$F$32=PMI!$C$43,PMI!$C54,IF(PMI!$F$32=PMI!$D$43,PMI!$D54,IF(PMI!$F$32=PMI!$E$43,PMI!$E54,1)))) -> 2 | M41: =BNP!J136 -> 4 | N41: =IF('10 yr rate'!$E$31='10 yr rate'!$B$35,'10 yr rate'!$B46,IF('10 yr rate'!$E$31='10 yr rate'!$C$35,'10 yr rate'!$C46,IF('10 yr rate'!$E$31='10 yr rate'!$D$35,'10 yr rate'!$D46,IF('10 yr rate'!$E$31='10 yr rate'!$E$35,'10 yr rate'!$E46,1)))) -> 2 | O41: =IF('CPI(Inflation)'!$E$10='CPI(Inflation)'!$B$33,'CPI(Inflation)'!$B44,IF('CPI(Inflation)'!$E$10='CPI(Inflation)'!$C$33,'CPI(Inflation)'!$C44,IF('CPI(Inflation)'!$E$10='CPI(Inflation)'!$D$33,'CPI(Inflation)'!$D44,IF('CPI(Inflation)'!$E$10='CPI(Inflation)'!$E$33,'CPI(Inflation)'!$E44,1)))) -> 2 | P41: ='Baltic Dry Index'!B44 -> 2 | Q41: =IF(VIX!$F$26=VIX!$B$33,VIX!B44,IF(VIX!$F$26=VIX!$C$33,VIX!C44,IF(VIX!$F$26=VIX!$D$33,VIX!D44,IF(VIX!$F$26=VIX!$E$33,VIX!E44,1)))) -> 5 | R41: =IF(Currency!$F$26=Currency!$B$33,Currency!B44,IF(Currency!$F$26=Currency!$C$33,Currency!C44,IF(Currency!$F$26=Currency!$D$33,Currency!D44,IF(Currency!$F$26=Currency!$E$33,Currency!E44,1)))) -> 2 | S41: =IF(Unemployment!$F$26=Unemployment!$B$33,Unemployment!B44,IF(Unemployment!$F$26=Unemployment!$C$33,Unemployment!C44,IF(Unemployment!$F$26=Unemployment!$D$33,Unemployment!D44,IF(Unemployment!$F$26=Unemployment!$E$33,Unemployment!E44,1)))) -> 2 | T41: =AVERAGE(L41*0.2222 + M41*0.3056 + N41*0.1667 + O41*0.1389 + R41*0.0556 + S41*0.1111) -> 2.6114
K69: ='Fremtid vækst'!$C$3 -> Q1 2026 | T69: ='Fremtid vækst'!$D$3 -> Q2 2026
B70: Europa | C70: PMI | D70: BNP | E70: 10 YR | F70: CPI | G70: Baltic Dry Index | H70: VIX | I70: Currency | J70: Unemployment | K70: Makro score | L70: PMI | M70: BNP | N70: 10 YR | O70: CPI | P70: Baltic Dry Index | Q70: VIX | R70: Currency | S70: Unemployment | T70: Makro score
B71: Financials | C71: =IF(PMI!$F$21=PMI!$B$43,PMI!$B44,IF(PMI!$F$21=PMI!$C$43,PMI!$C44,IF(PMI!$F$21=PMI!$D$43,PMI!$D44,IF(PMI!$F$21=PMI!$E$43,PMI!$E44,1)))) -> 4 | D71: =BNP!I87 -> 3 | E71: =IF('10 yr rate'!$E$20='10 yr rate'!$B$35,'10 yr rate'!$B36,IF('10 yr rate'!$E$20='10 yr rate'!$C$35,'10 yr rate'!$C36,IF('10 yr rate'!$E$20='10 yr rate'!$D$35,'10 yr rate'!$D36,IF('10 yr rate'!$E$20='10 yr rate'!$E$35,'10 yr rate'!$E36,1)))) -> 4 | F71: =IF('CPI(Inflation)'!$E$18='CPI(Inflation)'!$B$33,'CPI(Inflation)'!$B34,IF('CPI(Inflation)'!$E$18='CPI(Inflation)'!$C$33,'CPI(Inflation)'!$C34,IF('CPI(Inflation)'!$E$18='CPI(Inflation)'!$D$33,'CPI(Inflation)'!$D34,IF('CPI(Inflation)'!$E$18='CPI(Inflation)'!$E$33,'CPI(Inflation)'!$E34,1)))) -> 4 | G71: ='Baltic Dry Index'!B34 -> 4 | H71: =IF(VIX!$F$5=VIX!$B$33,VIX!B34,IF(VIX!$F$5=VIX!$C$33,VIX!C34,IF(VIX!$F$5=VIX!$D$33,VIX!D34,IF(VIX!$F$5=VIX!$E$33,VIX!E34,1)))) -> 4 | I71: =IF(Currency!$F$5=Currency!$B$33,Currency!B34,IF(Currency!$F$5=Currency!$C$33,Currency!C34,IF(Currency!$F$5=Currency!$D$33,Currency!D34,IF(Currency!$F$5=Currency!$E$33,Currency!E34,1)))) -> 2 | J71: =IF(Unemployment!$F$5=Unemployment!$B$33,Unemployment!B34,IF(Unemployment!$F$5=Unemployment!$C$33,Unemployment!C34,IF(Unemployment!$F$5=Unemployment!$D$33,Unemployment!D34,IF(Unemployment!$F$5=Unemployment!$E$33,Unemployment!E34,1)))) -> 2 | K71: =AVERAGE(C71*0.2222 + D71*0.3056 + E71*0.1667 + F71*0.1389 + I71*0.0556 + J71*0.1111) -> 3.3614 | L71: =IF(PMI!$F$22=PMI!$B$43,PMI!$B44,IF(PMI!$F$22=PMI!$C$43,PMI!$C44,IF(PMI!$F$22=PMI!$D$44,PMI!$D44,IF(PMI!$F$22=PMI!$E$43,PMI!$E44,1)))) -> 4 | M71: =BNP!J87 -> 3 | N71: =IF('10 yr rate'!$E$21='10 yr rate'!$B$35,'10 yr rate'!$B36,IF('10 yr rate'!$E$21='10 yr rate'!$C$35,'10 yr rate'!$C36,IF('10 yr rate'!$E$21='10 yr rate'!$D$35,'10 yr rate'!$D36,IF('10 yr rate'!$E$21='10 yr rate'!$E$35,'10 yr rate'!$E36,1)))) -> 4 | O71: =IF('CPI(Inflation)'!$E$19='CPI(Inflation)'!$B$33,'CPI(Inflation)'!$B34,IF('CPI(Inflation)'!$E$19='CPI(Inflation)'!$C$33,'CPI(Inflation)'!$C34,IF('CPI(Inflation)'!$E$19='CPI(Inflation)'!$D$33,'CPI(Inflation)'!$D34,IF('CPI(Inflation)'!$E$19='CPI(Inflation)'!$E$33,'CPI(Inflation)'!$E34,1)))) -> 4 | P71: ='Baltic Dry Index'!B34 -> 4 | Q71: =IF(VIX!$F$6=VIX!$B$33,VIX!B34,IF(VIX!$F$6=VIX!$C$33,VIX!C34,IF(VIX!$F$6=VIX!$D$33,VIX!D34,IF(VIX!$F$6=VIX!$E$33,VIX!E34,1)))) -> 1 | R71: =IF(Currency!$F$6=Currency!$B$33,Currency!B34,IF(Currency!$F$6=Currency!$C$33,Currency!C34,IF(Currency!$F$6=Currency!$D$33,Currency!D34,IF(Currency!$F$6=Currency!$E$33,Currency!E34,1)))) -> 4 | S71: =IF(Unemployment!$F$6=Unemployment!$B$33,Unemployment!B34,IF(Unemployment!$F$6=Unemployment!$C$33,Unemployment!C34,IF(Unemployment!$F$6=Unemployment!$D$33,Unemployment!D34,IF(Unemployment!$F$6=Unemployment!$E$33,Unemployment!E34,1)))) -> 2 | T71: =AVERAGE(L71*0.2222 + M71*0.3056 + N71*0.1667 + O71*0.1389 + R71*0.0556 + S71*0.1111) -> 3.4726
B72: Real Estate | C72: =IF(PMI!$F$21=PMI!$B$43,PMI!$B45,IF(PMI!$F$21=PMI!$C$43,PMI!$C45,IF(PMI!$F$21=PMI!$D$43,PMI!$D45,IF(PMI!$F$21=PMI!$E$43,PMI!$E45,1)))) -> 2 | D72: =BNP!I92 -> 5 | E72: =IF('10 yr rate'!$E$20='10 yr rate'!$B$35,'10 yr rate'!$B37,IF('10 yr rate'!$E$20='10 yr rate'!$C$35,'10 yr rate'!$C37,IF('10 yr rate'!$E$20='10 yr rate'!$D$35,'10 yr rate'!$D37,IF('10 yr rate'!$E$20='10 yr rate'!$E$35,'10 yr rate'!$E37,1)))) -> 2 | F72: =IF('CPI(Inflation)'!$E$18='CPI(Inflation)'!$B$33,'CPI(Inflation)'!$B35,IF('CPI(Inflation)'!$E$18='CPI(Inflation)'!$C$33,'CPI(Inflation)'!$C35,IF('CPI(Inflation)'!$E$18='CPI(Inflation)'!$D$33,'CPI(Inflation)'!$D35,IF('CPI(Inflation)'!$E$18='CPI(Inflation)'!$E$33,'CPI(Inflation)'!$E35,1)))) -> 2 | G72: ='Baltic Dry Index'!B35 -> 5 | H72: =IF(VIX!$F$5=VIX!$B$33,VIX!B35,IF(VIX!$F$5=VIX!$C$33,VIX!C35,IF(VIX!$F$5=VIX!$D$33,VIX!D35,IF(VIX!$F$5=VIX!$E$33,VIX!E35,1)))) -> 5 | I72: =IF(Currency!$F$5=Currency!$B$33,Currency!B35,IF(Currency!$F$5=Currency!$C$33,Currency!C35,IF(Currency!$F$5=Currency!$D$33,Currency!D35,IF(Currency!$F$5=Currency!$E$33,Currency!E35,1)))) -> 3 | J72: =IF(Unemployment!$F$5=Unemployment!$B$33,Unemployment!B35,IF(Unemployment!$F$5=Unemployment!$C$33,Unemployment!C35,IF(Unemployment!$F$5=Unemployment!$D$33,Unemployment!D35,IF(Unemployment!$F$5=Unemployment!$E$33,Unemployment!E35,1)))) -> 3 | K72: =AVERAGE(C72*0.2222 + D72*0.3056 + E72*0.1667 + F72*0.1389 + I72*0.0556 + J72*0.1111) -> 3.0837 | L72: =IF(PMI!$F$22=PMI!$B$43,PMI!$B45,IF(PMI!$F$22=PMI!$C$43,PMI!$C45,IF(PMI!$F$22=PMI!$D$44,PMI!$D45,IF(PMI!$F$22=PMI!$E$43,PMI!$E45,1)))) -> 2 | M72: =BNP!J92 -> 2 | N72: =IF('10 yr rate'!$E$21='10 yr rate'!$B$35,'10 yr rate'!$B37,IF('10 yr rate'!$E$21='10 yr rate'!$C$35,'10 yr rate'!$C37,IF('10 yr rate'!$E$21='10 yr rate'!$D$35,'10 yr rate'!$D37,IF('10 yr rate'!$E$21='10 yr rate'!$E$35,'10 yr rate'!$E37,1)))) -> 2 | O72: =IF('CPI(Inflation)'!$E$19='CPI(Inflation)'!$B$33,'CPI(Inflation)'!$B35,IF('CPI(Inflation)'!$E$19='CPI(Inflation)'!$C$33,'CPI(Inflation)'!$C35,IF('CPI(Inflation)'!$E$19='CPI(Inflation)'!$D$33,'CPI(Inflation)'!$D35,IF('CPI(Inflation)'!$E$19='CPI(Inflation)'!$E$33,'CPI(Inflation)'!$E35,1)))) -> 5 | P72: ='Baltic Dry Index'!B35 -> 5 | Q72: =IF(VIX!$F$6=VIX!$B$33,VIX!B35,IF(VIX!$F$6=VIX!$C$33,VIX!C35,IF(VIX!$F$6=VIX!$D$33,VIX!D35,IF(VIX!$F$6=VIX!$E$33,VIX!E35,1)))) -> 1 | R72: =IF(Currency!$F$6=Currency!$B$33,Currency!B35,IF(Currency!$F$6=Currency!$C$33,Currency!C35,IF(Currency!$F$6=Currency!$D$33,Currency!D35,IF(Currency!$F$6=Currency!$E$33,Currency!E35,1)))) -> 2 | S72: =IF(Unemployment!$F$6=Unemployment!$B$33,Unemployment!B35,IF(Unemployment!$F$6=Unemployment!$C$33,Unemployment!C35,IF(Unemployment!$F$6=Unemployment!$D$33,Unemployment!D35,IF(Unemployment!$F$6=Unemployment!$E$33,Unemployment!E35,1)))) -> 3 | T72: =AVERAGE(L72*0.2222 + M72*0.3056 + N72*0.1667 + O72*0.1389 + R72*0.0556 + S72*0.1111) -> 2.528
B73: Consumer Discretionary | C73: =IF(PMI!$F$21=PMI!$B$43,PMI!$B46,IF(PMI!$F$21=PMI!$C$43,PMI!$C46,IF(PMI!$F$21=PMI!$D$43,PMI!$D46,IF(PMI!$F$21=PMI!$E$43,PMI!$E46,1)))) -> 4 | D73: =BNP!I97 -> 5 | E73: =IF('10 yr rate'!$E$20='10 yr rate'!$B$35,'10 yr rate'!$B38,IF('10 yr rate'!$E$20='10 yr rate'!$C$35,'10 yr rate'!$C38,IF('10 yr rate'!$E$20='10 yr rate'!$D$35,'10 yr rate'!$D38,IF('10 yr rate'!$E$20='10 yr rate'!$E$35,'10 yr rate'!$E38,1)))) -> 4 | F73: =IF('CPI(Inflation)'!$E$18='CPI(Inflation)'!$B$33,'CPI(Inflation)'!$B36,IF('CPI(Inflation)'!$E$18='CPI(Inflation)'!$C$33,'CPI(Inflation)'!$C36,IF('CPI(Inflation)'!$E$18='CPI(Inflation)'!$D$33,'CPI(Inflation)'!$D36,IF('CPI(Inflation)'!$E$18='CPI(Inflation)'!$E$33,'CPI(Inflation)'!$E36,1)))) -> 4 | G73: ='Baltic Dry Index'!B36 -> 5 | H73: =IF(VIX!$F$5=VIX!$B$33,VIX!B36,IF(VIX!$F$5=VIX!$C$33,VIX!C36,IF(VIX!$F$5=VIX!$D$33,VIX!D36,IF(VIX!$F$5=VIX!$E$33,VIX!E36,1)))) -> 5 | I73: =IF(Currency!$F$5=Currency!$B$33,Currency!B36,IF(Currency!$F$5=Currency!$C$33,Currency!C36,IF(Currency!$F$5=Currency!$D$33,Currency!D36,IF(Currency!$F$5=Currency!$E$33,Currency!E36,1)))) -> 2 | J73: =IF(Unemployment!$F$5=Unemployment!$B$33,Unemployment!B36,IF(Unemployment!$F$5=Unemployment!$C$33,Unemployment!C36,IF(Unemployment!$F$5=Unemployment!$D$33,Unemployment!D36,IF(Unemployment!$F$5=Unemployment!$E$33,Unemployment!E36,1)))) -> 2 | K73: =AVERAGE(C73*0.2222 + D73*0.3056 + E73*0.1667 + F73*0.1389 + I73*0.0556 + J73*0.1111) -> 3.9726 | L73: =IF(PMI!$F$22=PMI!$B$43,PMI!$B46,IF(PMI!$F$22=PMI!$C$43,PMI!$C46,IF(PMI!$F$22=PMI!$D$44,PMI!$D46,IF(PMI!$F$22=PMI!$E$43,PMI!$E46,1)))) -> 4 | M73: =BNP!J97 -> 3 | N73: =IF('10 yr rate'!$E$21='10 yr rate'!$B$35,'10 yr rate'!$B38,IF('10 yr rate'!$E$21='10 yr rate'!$C$35,'10 yr rate'!$C38,IF('10 yr rate'!$E$21='10 yr rate'!$D$35,'10 yr rate'!$D38,IF('10 yr rate'!$E$21='10 yr rate'!$E$35,'10 yr rate'!$E38,1)))) -> 4 | O73: =IF('CPI(Inflation)'!$E$19='CPI(Inflation)'!$B$33,'CPI(Inflation)'!$B36,IF('CPI(Inflation)'!$E$19='CPI(Inflation)'!$C$33,'CPI(Inflation)'!$C36,IF('CPI(Inflation)'!$E$19='CPI(Inflation)'!$D$33,'CPI(Inflation)'!$D36,IF('CPI(Inflation)'!$E$19='CPI(Inflation)'!$E$33,'CPI(Inflation)'!$E36,1)))) -> 5 | P73: ='Baltic Dry Index'!B36 -> 5 | Q73: =IF(VIX!$F$6=VIX!$B$33,VIX!B36,IF(VIX!$F$6=VIX!$C$33,VIX!C36,IF(VIX!$F$6=VIX!$D$33,VIX!D36,IF(VIX!$F$6=VIX!$E$33,VIX!E36,1)))) -> 1 | R73: =IF(Currency!$F$6=Currency!$B$33,Currency!B36,IF(Currency!$F$6=Currency!$C$33,Currency!C36,IF(Currency!$F$6=Currency!$D$33,Currency!D36,IF(Currency!$F$6=Currency!$E$33,Currency!E36,1)))) -> 4 | S73: =IF(Unemployment!$F$6=Unemployment!$B$33,Unemployment!B36,IF(Unemployment!$F$6=Unemployment!$C$33,Unemployment!C36,IF(Unemployment!$F$6=Unemployment!$D$33,Unemployment!D36,IF(Unemployment!$F$6=Unemployment!$E$33,Unemployment!E36,1)))) -> 2 | T73: =AVERAGE(L73*0.2222 + M73*0.3056 + N73*0.1667 + O73*0.1389 + R73*0.0556 + S73*0.1111) -> 3.6115
B74: Information Technology | C74: =IF(PMI!$F$21=PMI!$B$43,PMI!$B47,IF(PMI!$F$21=PMI!$C$43,PMI!$C47,IF(PMI!$F$21=PMI!$D$43,PMI!$D47,IF(PMI!$F$21=PMI!$E$43,PMI!$E47,1)))) -> 5 | D74: =BNP!I102 -> 4 | E74: =IF('10 yr rate'!$E$20='10 yr rate'!$B$35,'10 yr rate'!$B39,IF('10 yr rate'!$E$20='10 yr rate'!$C$35,'10 yr rate'!$C39,IF('10 yr rate'!$E$20='10 yr rate'!$D$35,'10 yr rate'!$D39,IF('10 yr rate'!$E$20='10 yr rate'!$E$35,'10 yr rate'!$E39,1)))) -> 5 | F74: =IF('CPI(Inflation)'!$E$18='CPI(Inflation)'!$B$33,'CPI(Inflation)'!$B37,IF('CPI(Inflation)'!$E$18='CPI(Inflation)'!$C$33,'CPI(Inflation)'!$C37,IF('CPI(Inflation)'!$E$18='CPI(Inflation)'!$D$33,'CPI(Inflation)'!$D37,IF('CPI(Inflation)'!$E$18='CPI(Inflation)'!$E$33,'CPI(Inflation)'!$E37,1)))) -> 5 | G74: ='Baltic Dry Index'!B37 -> 4 | H74: =IF(VIX!$F$5=VIX!$B$33,VIX!B37,IF(VIX!$F$5=VIX!$C$33,VIX!C37,IF(VIX!$F$5=VIX!$D$33,VIX!D37,IF(VIX!$F$5=VIX!$E$33,VIX!E37,1)))) -> 4 | I74: =IF(Currency!$F$5=Currency!$B$33,Currency!B37,IF(Currency!$F$5=Currency!$C$33,Currency!C37,IF(Currency!$F$5=Currency!$D$33,Currency!D37,IF(Currency!$F$5=Currency!$E$33,Currency!E37,1)))) -> 3 | J74: =IF(Unemployment!$F$5=Unemployment!$B$33,Unemployment!B37,IF(Unemployment!$F$5=Unemployment!$C$33,Unemployment!C37,IF(Unemployment!$F$5=Unemployment!$D$33,Unemployment!D37,IF(Unemployment!$F$5=Unemployment!$E$33,Unemployment!E37,1)))) -> 3 | K74: =AVERAGE(C74*0.2222 + D74*0.3056 + E74*0.1667 + F74*0.1389 + I74*0.0556 + J74*0.1111) -> 4.3615 | L74: =IF(PMI!$F$22=PMI!$B$43,PMI!$B47,IF(PMI!$F$22=PMI!$C$43,PMI!$C47,IF(PMI!$F$22=PMI!$D$44,PMI!$D47,IF(PMI!$F$22=PMI!$E$43,PMI!$E47,1)))) -> 5 | M74: =BNP!J102 -> 4 | N74: =IF('10 yr rate'!$E$21='10 yr rate'!$B$35,'10 yr rate'!$B39,IF('10 yr rate'!$E$21='10 yr rate'!$C$35,'10 yr rate'!$C39,IF('10 yr rate'!$E$21='10 yr rate'!$D$35,'10 yr rate'!$D39,IF('10 yr rate'!$E$21='10 yr rate'!$E$35,'10 yr rate'!$E39,1)))) -> 5 | O74: =IF('CPI(Inflation)'!$E$19='CPI(Inflation)'!$B$33,'CPI(Inflation)'!$B37,IF('CPI(Inflation)'!$E$19='CPI(Inflation)'!$C$33,'CPI(Inflation)'!$C37,IF('CPI(Inflation)'!$E$19='CPI(Inflation)'!$D$33,'CPI(Inflation)'!$D37,IF('CPI(Inflation)'!$E$19='CPI(Inflation)'!$E$33,'CPI(Inflation)'!$E37,1)))) -> 4 | P74: ='Baltic Dry Index'!B37 -> 4 | Q74: =IF(VIX!$F$6=VIX!$B$33,VIX!B37,IF(VIX!$F$6=VIX!$C$33,VIX!C37,IF(VIX!$F$6=VIX!$D$33,VIX!D37,IF(VIX!$F$6=VIX!$E$33,VIX!E37,1)))) -> 1 | R74: =IF(Currency!$F$6=Currency!$B$33,Currency!B37,IF(Currency!$F$6=Currency!$C$33,Currency!C37,IF(Currency!$F$6=Currency!$D$33,Currency!D37,IF(Currency!$F$6=Currency!$E$33,Currency!E37,1)))) -> 5 | S74: =IF(Unemployment!$F$6=Unemployment!$B$33,Unemployment!B37,IF(Unemployment!$F$6=Unemployment!$C$33,Unemployment!C37,IF(Unemployment!$F$6=Unemployment!$D$33,Unemployment!D37,IF(Unemployment!$F$6=Unemployment!$E$33,Unemployment!E37,1)))) -> 3 | T74: =AVERAGE(L74*0.2222 + M74*0.3056 + N74*0.1667 + O74*0.1389 + R74*0.0556 + S74*0.1111) -> 4.3338
B75: Industrials | C75: =IF(PMI!$F$21=PMI!$B$43,PMI!$B48,IF(PMI!$F$21=PMI!$C$43,PMI!$C48,IF(PMI!$F$21=PMI!$D$43,PMI!$D48,IF(PMI!$F$21=PMI!$E$43,PMI!$E48,1)))) -> 4 | D75: =BNP!I107 -> 5 | E75: =IF('10 yr rate'!$E$20='10 yr rate'!$B$35,'10 yr rate'!$B40,IF('10 yr rate'!$E$20='10 yr rate'!$C$35,'10 yr rate'!$C40,IF('10 yr rate'!$E$20='10 yr rate'!$D$35,'10 yr rate'!$D40,IF('10 yr rate'!$E$20='10 yr rate'!$E$35,'10 yr rate'!$E40,1)))) -> 4 | F75: =IF('CPI(Inflation)'!$E$18='CPI(Inflation)'!$B$33,'CPI(Inflation)'!$B38,IF('CPI(Inflation)'!$E$18='CPI(Inflation)'!$C$33,'CPI(Inflation)'!$C38,IF('CPI(Inflation)'!$E$18='CPI(Inflation)'!$D$33,'CPI(Inflation)'!$D38,IF('CPI(Inflation)'!$E$18='CPI(Inflation)'!$E$33,'CPI(Inflation)'!$E38,1)))) -> 4 | G75: ='Baltic Dry Index'!B38 -> 5 | H75: =IF(VIX!$F$5=VIX!$B$33,VIX!B38,IF(VIX!$F$5=VIX!$C$33,VIX!C38,IF(VIX!$F$5=VIX!$D$33,VIX!D38,IF(VIX!$F$5=VIX!$E$33,VIX!E38,1)))) -> 5 | I75: =IF(Currency!$F$5=Currency!$B$33,Currency!B38,IF(Currency!$F$5=Currency!$C$33,Currency!C38,IF(Currency!$F$5=Currency!$D$33,Currency!D38,IF(Currency!$F$5=Currency!$E$33,Currency!E38,1)))) -> 2 | J75: =IF(Unemployment!$F$5=Unemployment!$B$33,Unemployment!B38,IF(Unemployment!$F$5=Unemployment!$C$33,Unemployment!C38,IF(Unemployment!$F$5=Unemployment!$D$33,Unemployment!D38,IF(Unemployment!$F$5=Unemployment!$E$33,Unemployment!E38,1)))) -> 2 | K75: =AVERAGE(C75*0.2222 + D75*0.3056 + E75*0.1667 + F75*0.1389 + I75*0.0556 + J75*0.1111) -> 3.9726 | L75: =IF(PMI!$F$22=PMI!$B$43,PMI!$B48,IF(PMI!$F$22=PMI!$C$43,PMI!$C48,IF(PMI!$F$22=PMI!$D$44,PMI!$D48,IF(PMI!$F$22=PMI!$E$43,PMI!$E48,1)))) -> 4 | M75: =BNP!J107 -> 3 | N75: =IF('10 yr rate'!$E$21='10 yr rate'!$B$35,'10 yr rate'!$B40,IF('10 yr rate'!$E$21='10 yr rate'!$C$35,'10 yr rate'!$C40,IF('10 yr rate'!$E$21='10 yr rate'!$D$35,'10 yr rate'!$D40,IF('10 yr rate'!$E$21='10 yr rate'!$E$35,'10 yr rate'!$E40,1)))) -> 4 | O75: =IF('CPI(Inflation)'!$E$19='CPI(Inflation)'!$B$33,'CPI(Inflation)'!$B38,IF('CPI(Inflation)'!$E$19='CPI(Inflation)'!$C$33,'CPI(Inflation)'!$C38,IF('CPI(Inflation)'!$E$19='CPI(Inflation)'!$D$33,'CPI(Inflation)'!$D38,IF('CPI(Inflation)'!$E$19='CPI(Inflation)'!$E$33,'CPI(Inflation)'!$E38,1)))) -> 5 | P75: ='Baltic Dry Index'!B38 -> 5 | Q75: =IF(VIX!$F$6=VIX!$B$33,VIX!B38,IF(VIX!$F$6=VIX!$C$33,VIX!C38,IF(VIX!$F$6=VIX!$D$33,VIX!D38,IF(VIX!$F$6=VIX!$E$33,VIX!E38,1)))) -> 1 | R75: =IF(Currency!$F$6=Currency!$B$33,Currency!B38,IF(Currency!$F$6=Currency!$C$33,Currency!C38,IF(Currency!$F$6=Currency!$D$33,Currency!D38,IF(Currency!$F$6=Currency!$E$33,Currency!E38,1)))) -> 4 | S75: =IF(Unemployment!$F$6=Unemployment!$B$33,Unemployment!B38,IF(Unemployment!$F$6=Unemployment!$C$33,Unemployment!C38,IF(Unemployment!$F$6=Unemployment!$D$33,Unemployment!D38,IF(Unemployment!$F$6=Unemployment!$E$33,Unemployment!E38,1)))) -> 2 | T75: =AVERAGE(L75*0.2222 + M75*0.3056 + N75*0.1667 + O75*0.1389 + R75*0.0556 + S75*0.1111) -> 3.6115
B76: Materials | C76: =IF(PMI!$F$21=PMI!$B$43,PMI!$B49,IF(PMI!$F$21=PMI!$C$43,PMI!$C49,IF(PMI!$F$21=PMI!$D$43,PMI!$D49,IF(PMI!$F$21=PMI!$E$43,PMI!$E49,1)))) -> 2 | D76: =BNP!I112 -> 4 | E76: =IF('10 yr rate'!$E$20='10 yr rate'!$B$35,'10 yr rate'!$B41,IF('10 yr rate'!$E$20='10 yr rate'!$C$35,'10 yr rate'!$C41,IF('10 yr rate'!$E$20='10 yr rate'!$D$35,'10 yr rate'!$D41,IF('10 yr rate'!$E$20='10 yr rate'!$E$35,'10 yr rate'!$E41,1)))) -> 2 | F76: =IF('CPI(Inflation)'!$E$18='CPI(Inflation)'!$B$33,'CPI(Inflation)'!$B39,IF('CPI(Inflation)'!$E$18='CPI(Inflation)'!$C$33,'CPI(Inflation)'!$C39,IF('CPI(Inflation)'!$E$18='CPI(Inflation)'!$D$33,'CPI(Inflation)'!$D39,IF('CPI(Inflation)'!$E$18='CPI(Inflation)'!$E$33,'CPI(Inflation)'!$E39,1)))) -> 2 | G76: ='Baltic Dry Index'!B39 -> 4 | H76: =IF(VIX!$F$5=VIX!$B$33,VIX!B39,IF(VIX!$F$5=VIX!$C$33,VIX!C39,IF(VIX!$F$5=VIX!$D$33,VIX!D39,IF(VIX!$F$5=VIX!$E$33,VIX!E39,1)))) -> 4 | I76: =IF(Currency!$F$5=Currency!$B$33,Currency!B39,IF(Currency!$F$5=Currency!$C$33,Currency!C39,IF(Currency!$F$5=Currency!$D$33,Currency!D39,IF(Currency!$F$5=Currency!$E$33,Currency!E39,1)))) -> 3 | J76: =IF(Unemployment!$F$5=Unemployment!$B$33,Unemployment!B39,IF(Unemployment!$F$5=Unemployment!$C$33,Unemployment!C39,IF(Unemployment!$F$5=Unemployment!$D$33,Unemployment!D39,IF(Unemployment!$F$5=Unemployment!$E$33,Unemployment!E39,1)))) -> 3 | K76: =AVERAGE(C76*0.2222 + D76*0.3056 + E76*0.1667 + F76*0.1389 + I76*0.0556 + J76*0.1111) -> 2.7781 | L76: =IF(PMI!$F$22=PMI!$B$43,PMI!$B49,IF(PMI!$F$22=PMI!$C$43,PMI!$C49,IF(PMI!$F$22=PMI!$D$44,PMI!$D49,IF(PMI!$F$22=PMI!$E$43,PMI!$E49,1)))) -> 2 | M76: =BNP!J112 -> 1 | N76: =IF('10 yr rate'!$E$21='10 yr rate'!$B$35,'10 yr rate'!$B41,IF('10 yr rate'!$E$21='10 yr rate'!$C$35,'10 yr rate'!$C41,IF('10 yr rate'!$E$21='10 yr rate'!$D$35,'10 yr rate'!$D41,IF('10 yr rate'!$E$21='10 yr rate'!$E$35,'10 yr rate'!$E41,1)))) -> 2 | O76: =IF('CPI(Inflation)'!$E$19='CPI(Inflation)'!$B$33,'CPI(Inflation)'!$B39,IF('CPI(Inflation)'!$E$19='CPI(Inflation)'!$C$33,'CPI(Inflation)'!$C39,IF('CPI(Inflation)'!$E$19='CPI(Inflation)'!$D$33,'CPI(Inflation)'!$D39,IF('CPI(Inflation)'!$E$19='CPI(Inflation)'!$E$33,'CPI(Inflation)'!$E39,1)))) -> 4 | P76: ='Baltic Dry Index'!B39 -> 4 | Q76: =IF(VIX!$F$6=VIX!$B$33,VIX!B39,IF(VIX!$F$6=VIX!$C$33,VIX!C39,IF(VIX!$F$6=VIX!$D$33,VIX!D39,IF(VIX!$F$6=VIX!$E$33,VIX!E39,1)))) -> 2 | R76: =IF(Currency!$F$6=Currency!$B$33,Currency!B39,IF(Currency!$F$6=Currency!$C$33,Currency!C39,IF(Currency!$F$6=Currency!$D$33,Currency!D39,IF(Currency!$F$6=Currency!$E$33,Currency!E39,1)))) -> 2 | S76: =IF(Unemployment!$F$6=Unemployment!$B$33,Unemployment!B39,IF(Unemployment!$F$6=Unemployment!$C$33,Unemployment!C39,IF(Unemployment!$F$6=Unemployment!$D$33,Unemployment!D39,IF(Unemployment!$F$6=Unemployment!$E$33,Unemployment!E39,1)))) -> 3 | T76: =AVERAGE(L76*0.2222 + M76*0.3056 + N76*0.1667 + O76*0.1389 + R76*0.0556 + S76*0.1111) -> 2.0835
B77: Consumer Staples | C77: =IF(PMI!$F$21=PMI!$B$43,PMI!$B50,IF(PMI!$F$21=PMI!$C$43,PMI!$C50,IF(PMI!$F$21=PMI!$D$43,PMI!$D50,IF(PMI!$F$21=PMI!$E$43,PMI!$E50,1)))) -> 2 | D77: =BNP!I117 -> 3 | E77: =IF('10 yr rate'!$E$20='10 yr rate'!$B$35,'10 yr rate'!$B42,IF('10 yr rate'!$E$20='10 yr rate'!$C$35,'10 yr rate'!$C42,IF('10 yr rate'!$E$20='10 yr rate'!$D$35,'10 yr rate'!$D42,IF('10 yr rate'!$E$20='10 yr rate'!$E$35,'10 yr rate'!$E42,1)))) -> 2 | F77: =IF('CPI(Inflation)'!$E$18='CPI(Inflation)'!$B$33,'CPI(Inflation)'!$B40,IF('CPI(Inflation)'!$E$18='CPI(Inflation)'!$C$33,'CPI(Inflation)'!$C40,IF('CPI(Inflation)'!$E$18='CPI(Inflation)'!$D$33,'CPI(Inflation)'!$D40,IF('CPI(Inflation)'!$E$18='CPI(Inflation)'!$E$33,'CPI(Inflation)'!$E40,1)))) -> 2 | G77: ='Baltic Dry Index'!B40 -> 2 | H77: =IF(VIX!$F$5=VIX!$B$33,VIX!B40,IF(VIX!$F$5=VIX!$C$33,VIX!C40,IF(VIX!$F$5=VIX!$D$33,VIX!D40,IF(VIX!$F$5=VIX!$E$33,VIX!E40,1)))) -> 2 | I77: =IF(Currency!$F$5=Currency!$B$33,Currency!B40,IF(Currency!$F$5=Currency!$C$33,Currency!C40,IF(Currency!$F$5=Currency!$D$33,Currency!D40,IF(Currency!$F$5=Currency!$E$33,Currency!E40,1)))) -> 4 | J77: =IF(Unemployment!$F$5=Unemployment!$B$33,Unemployment!B40,IF(Unemployment!$F$5=Unemployment!$C$33,Unemployment!C40,IF(Unemployment!$F$5=Unemployment!$D$33,Unemployment!D40,IF(Unemployment!$F$5=Unemployment!$E$33,Unemployment!E40,1)))) -> 4 | K77: =AVERAGE(C77*0.2222 + D77*0.3056 + E77*0.1667 + F77*0.1389 + I77*0.0556 + J77*0.1111) -> 2.6392 | L77: =IF(PMI!$F$22=PMI!$B$43,PMI!$B50,IF(PMI!$F$22=PMI!$C$43,PMI!$C50,IF(PMI!$F$22=PMI!$D$44,PMI!$D50,IF(PMI!$F$22=PMI!$E$43,PMI!$E50,1)))) -> 2 | M77: =BNP!J117 -> 2 | N77: =IF('10 yr rate'!$E$21='10 yr rate'!$B$35,'10 yr rate'!$B42,IF('10 yr rate'!$E$21='10 yr rate'!$C$35,'10 yr rate'!$C42,IF('10 yr rate'!$E$21='10 yr rate'!$D$35,'10 yr rate'!$D42,IF('10 yr rate'!$E$21='10 yr rate'!$E$35,'10 yr rate'!$E42,1)))) -> 2 | O77: =IF('CPI(Inflation)'!$E$19='CPI(Inflation)'!$B$33,'CPI(Inflation)'!$B40,IF('CPI(Inflation)'!$E$19='CPI(Inflation)'!$C$33,'CPI(Inflation)'!$C40,IF('CPI(Inflation)'!$E$19='CPI(Inflation)'!$D$33,'CPI(Inflation)'!$D40,IF('CPI(Inflation)'!$E$19='CPI(Inflation)'!$E$33,'CPI(Inflation)'!$E40,1)))) -> 2 | P77: ='Baltic Dry Index'!B40 -> 2 | Q77: =IF(VIX!$F$6=VIX!$B$33,VIX!B40,IF(VIX!$F$6=VIX!$C$33,VIX!C40,IF(VIX!$F$6=VIX!$D$33,VIX!D40,IF(VIX!$F$6=VIX!$E$33,VIX!E40,1)))) -> 5 | R77: =IF(Currency!$F$6=Currency!$B$33,Currency!B40,IF(Currency!$F$6=Currency!$C$33,Currency!C40,IF(Currency!$F$6=Currency!$D$33,Currency!D40,IF(Currency!$F$6=Currency!$E$33,Currency!E40,1)))) -> 2 | S77: =IF(Unemployment!$F$6=Unemployment!$B$33,Unemployment!B40,IF(Unemployment!$F$6=Unemployment!$C$33,Unemployment!C40,IF(Unemployment!$F$6=Unemployment!$D$33,Unemployment!D40,IF(Unemployment!$F$6=Unemployment!$E$33,Unemployment!E40,1)))) -> 4 | T77: =AVERAGE(L77*0.2222 + M77*0.3056 + N77*0.1667 + O77*0.1389 + R77*0.0556 + S77*0.1111) -> 2.2224
B78: Health Care | C78: =IF(PMI!$F$21=PMI!$B$43,PMI!$B51,IF(PMI!$F$21=PMI!$C$43,PMI!$C51,IF(PMI!$F$21=PMI!$D$43,PMI!$D51,IF(PMI!$F$21=PMI!$E$43,PMI!$E51,1)))) -> 3 | D78: =BNP!I122 -> 1 | E78: =IF('10 yr rate'!$E$20='10 yr rate'!$B$35,'10 yr rate'!$B43,IF('10 yr rate'!$E$20='10 yr rate'!$C$35,'10 yr rate'!$C43,IF('10 yr rate'!$E$20='10 yr rate'!$D$35,'10 yr rate'!$D43,IF('10 yr rate'!$E$20='10 yr rate'!$E$35,'10 yr rate'!$E43,1)))) -> 3 | F78: =IF('CPI(Inflation)'!$E$18='CPI(Inflation)'!$B$33,'CPI(Inflation)'!$B41,IF('CPI(Inflation)'!$E$18='CPI(Inflation)'!$C$33,'CPI(Inflation)'!$C41,IF('CPI(Inflation)'!$E$18='CPI(Inflation)'!$D$33,'CPI(Inflation)'!$D41,IF('CPI(Inflation)'!$E$18='CPI(Inflation)'!$E$33,'CPI(Inflation)'!$E41,1)))) -> 3 | G78: ='Baltic Dry Index'!B41 -> 2 | H78: =IF(VIX!$F$5=VIX!$B$33,VIX!B41,IF(VIX!$F$5=VIX!$C$33,VIX!C41,IF(VIX!$F$5=VIX!$D$33,VIX!D41,IF(VIX!$F$5=VIX!$E$33,VIX!E41,1)))) -> 2 | I78: =IF(Currency!$F$5=Currency!$B$33,Currency!B41,IF(Currency!$F$5=Currency!$C$33,Currency!C41,IF(Currency!$F$5=Currency!$D$33,Currency!D41,IF(Currency!$F$5=Currency!$E$33,Currency!E41,1)))) -> 3 | J78: =IF(Unemployment!$F$5=Unemployment!$B$33,Unemployment!B41,IF(Unemployment!$F$5=Unemployment!$C$33,Unemployment!C41,IF(Unemployment!$F$5=Unemployment!$D$33,Unemployment!D41,IF(Unemployment!$F$5=Unemployment!$E$33,Unemployment!E41,1)))) -> 3 | K78: =AVERAGE(C78*0.2222 + D78*0.3056 + E78*0.1667 + F78*0.1389 + I78*0.0556 + J78*0.1111) -> 2.3891 | L78: =IF(PMI!$F$22=PMI!$B$43,PMI!$B51,IF(PMI!$F$22=PMI!$C$43,PMI!$C51,IF(PMI!$F$22=PMI!$D$44,PMI!$D51,IF(PMI!$F$22=PMI!$E$43,PMI!$E51,1)))) -> 3 | M78: =BNP!J122 -> 3 | N78: =IF('10 yr rate'!$E$21='10 yr rate'!$B$35,'10 yr rate'!$B43,IF('10 yr rate'!$E$21='10 yr rate'!$C$35,'10 yr rate'!$C43,IF('10 yr rate'!$E$21='10 yr rate'!$D$35,'10 yr rate'!$D43,IF('10 yr rate'!$E$21='10 yr rate'!$E$35,'10 yr rate'!$E43,1)))) -> 3 | O78: =IF('CPI(Inflation)'!$E$19='CPI(Inflation)'!$B$33,'CPI(Inflation)'!$B41,IF('CPI(Inflation)'!$E$19='CPI(Inflation)'!$C$33,'CPI(Inflation)'!$C41,IF('CPI(Inflation)'!$E$19='CPI(Inflation)'!$D$33,'CPI(Inflation)'!$D41,IF('CPI(Inflation)'!$E$19='CPI(Inflation)'!$E$33,'CPI(Inflation)'!$E41,1)))) -> 2 | P78: ='Baltic Dry Index'!B41 -> 2 | Q78: =IF(VIX!$F$6=VIX!$B$33,VIX!B41,IF(VIX!$F$6=VIX!$C$33,VIX!C41,IF(VIX!$F$6=VIX!$D$33,VIX!D41,IF(VIX!$F$6=VIX!$E$33,VIX!E41,1)))) -> 5 | R78: =IF(Currency!$F$6=Currency!$B$33,Currency!B41,IF(Currency!$F$6=Currency!$C$33,Currency!C41,IF(Currency!$F$6=Currency!$D$33,Currency!D41,IF(Currency!$F$6=Currency!$E$33,Currency!E41,1)))) -> 3 | S78: =IF(Unemployment!$F$6=Unemployment!$B$33,Unemployment!B41,IF(Unemployment!$F$6=Unemployment!$C$33,Unemployment!C41,IF(Unemployment!$F$6=Unemployment!$D$33,Unemployment!D41,IF(Unemployment!$F$6=Unemployment!$E$33,Unemployment!E41,1)))) -> 3 | T78: =AVERAGE(L78*0.2222 + M78*0.3056 + N78*0.1667 + O78*0.1389 + R78*0.0556 + S78*0.1111) -> 2.8614
B79: Energy | C79: =IF(PMI!$F$21=PMI!$B$43,PMI!$B52,IF(PMI!$F$21=PMI!$C$43,PMI!$C52,IF(PMI!$F$21=PMI!$D$43,PMI!$D52,IF(PMI!$F$21=PMI!$E$43,PMI!$E52,1)))) -> 3 | D79: =BNP!I127 -> 1 | E79: =IF('10 yr rate'!$E$20='10 yr rate'!$B$35,'10 yr rate'!$B44,IF('10 yr rate'!$E$20='10 yr rate'!$C$35,'10 yr rate'!$C44,IF('10 yr rate'!$E$20='10 yr rate'!$D$35,'10 yr rate'!$D44,IF('10 yr rate'!$E$20='10 yr rate'!$E$35,'10 yr rate'!$E44,1)))) -> 3 | F79: =IF('CPI(Inflation)'!$E$18='CPI(Inflation)'!$B$33,'CPI(Inflation)'!$B42,IF('CPI(Inflation)'!$E$18='CPI(Inflation)'!$C$33,'CPI(Inflation)'!$C42,IF('CPI(Inflation)'!$E$18='CPI(Inflation)'!$D$33,'CPI(Inflation)'!$D42,IF('CPI(Inflation)'!$E$18='CPI(Inflation)'!$E$33,'CPI(Inflation)'!$E42,1)))) -> 3 | G79: ='Baltic Dry Index'!B42 -> 2 | H79: =IF(VIX!$F$5=VIX!$B$33,VIX!B42,IF(VIX!$F$5=VIX!$C$33,VIX!C42,IF(VIX!$F$5=VIX!$D$33,VIX!D42,IF(VIX!$F$5=VIX!$E$33,VIX!E42,1)))) -> 2 | I79: =IF(Currency!$F$5=Currency!$B$33,Currency!B42,IF(Currency!$F$5=Currency!$C$33,Currency!C42,IF(Currency!$F$5=Currency!$D$33,Currency!D42,IF(Currency!$F$5=Currency!$E$33,Currency!E42,1)))) -> 5 | J79: =IF(Unemployment!$F$5=Unemployment!$B$33,Unemployment!B42,IF(Unemployment!$F$5=Unemployment!$C$33,Unemployment!C42,IF(Unemployment!$F$5=Unemployment!$D$33,Unemployment!D42,IF(Unemployment!$F$5=Unemployment!$E$33,Unemployment!E42,1)))) -> 5 | K79: =AVERAGE(C79*0.2222 + D79*0.3056 + E79*0.1667 + F79*0.1389 + I79*0.0556 + J79*0.1111) -> 2.7225 | L79: =IF(PMI!$F$22=PMI!$B$43,PMI!$B52,IF(PMI!$F$22=PMI!$C$43,PMI!$C52,IF(PMI!$F$22=PMI!$D$44,PMI!$D52,IF(PMI!$F$22=PMI!$E$43,PMI!$E52,1)))) -> 3 | M79: =BNP!J127 -> 3 | N79: =IF('10 yr rate'!$E$21='10 yr rate'!$B$35,'10 yr rate'!$B44,IF('10 yr rate'!$E$21='10 yr rate'!$C$35,'10 yr rate'!$C44,IF('10 yr rate'!$E$21='10 yr rate'!$D$35,'10 yr rate'!$D44,IF('10 yr rate'!$E$21='10 yr rate'!$E$35,'10 yr rate'!$E44,1)))) -> 3 | O79: =IF('CPI(Inflation)'!$E$19='CPI(Inflation)'!$B$33,'CPI(Inflation)'!$B42,IF('CPI(Inflation)'!$E$19='CPI(Inflation)'!$C$33,'CPI(Inflation)'!$C42,IF('CPI(Inflation)'!$E$19='CPI(Inflation)'!$D$33,'CPI(Inflation)'!$D42,IF('CPI(Inflation)'!$E$19='CPI(Inflation)'!$E$33,'CPI(Inflation)'!$E42,1)))) -> 2 | P79: ='Baltic Dry Index'!B42 -> 2 | Q79: =IF(VIX!$F$6=VIX!$B$33,VIX!B42,IF(VIX!$F$6=VIX!$C$33,VIX!C42,IF(VIX!$F$6=VIX!$D$33,VIX!D42,IF(VIX!$F$6=VIX!$E$33,VIX!E42,1)))) -> 1 | R79: =IF(Currency!$F$6=Currency!$B$33,Currency!B42,IF(Currency!$F$6=Currency!$C$33,Currency!C42,IF(Currency!$F$6=Currency!$D$33,Currency!D42,IF(Currency!$F$6=Currency!$E$33,Currency!E42,1)))) -> 3 | S79: =IF(Unemployment!$F$6=Unemployment!$B$33,Unemployment!B42,IF(Unemployment!$F$6=Unemployment!$C$33,Unemployment!C42,IF(Unemployment!$F$6=Unemployment!$D$33,Unemployment!D42,IF(Unemployment!$F$6=Unemployment!$E$33,Unemployment!E42,1)))) -> 5 | T79: =AVERAGE(L79*0.2222 + M79*0.3056 + N79*0.1667 + O79*0.1389 + R79*0.0556 + S79*0.1111) -> 3.0836
B80: Communications Services | C80: =IF(PMI!$F$21=PMI!$B$43,PMI!$B53,IF(PMI!$F$21=PMI!$C$43,PMI!$C53,IF(PMI!$F$21=PMI!$D$43,PMI!$D53,IF(PMI!$F$21=PMI!$E$43,PMI!$E53,1)))) -> 4 | D80: =BNP!I132 -> 3 | E80: =IF('10 yr rate'!$E$20='10 yr rate'!$B$35,'10 yr rate'!$B45,IF('10 yr rate'!$E$20='10 yr rate'!$C$35,'10 yr rate'!$C45,IF('10 yr rate'!$E$20='10 yr rate'!$D$35,'10 yr rate'!$D45,IF('10 yr rate'!$E$20='10 yr rate'!$E$35,'10 yr rate'!$E45,1)))) -> 4 | F80: =IF('CPI(Inflation)'!$E$18='CPI(Inflation)'!$B$33,'CPI(Inflation)'!$B43,IF('CPI(Inflation)'!$E$18='CPI(Inflation)'!$C$33,'CPI(Inflation)'!$C43,IF('CPI(Inflation)'!$E$18='CPI(Inflation)'!$D$33,'CPI(Inflation)'!$D43,IF('CPI(Inflation)'!$E$18='CPI(Inflation)'!$E$33,'CPI(Inflation)'!$E43,1)))) -> 4 | G80: ='Baltic Dry Index'!B43 -> 3 | H80: =IF(VIX!$F$5=VIX!$B$33,VIX!B43,IF(VIX!$F$5=VIX!$C$33,VIX!C43,IF(VIX!$F$5=VIX!$D$33,VIX!D43,IF(VIX!$F$5=VIX!$E$33,VIX!E43,1)))) -> 3 | I80: =IF(Currency!$F$5=Currency!$B$33,Currency!B43,IF(Currency!$F$5=Currency!$C$33,Currency!C43,IF(Currency!$F$5=Currency!$D$33,Currency!D43,IF(Currency!$F$5=Currency!$E$33,Currency!E43,1)))) -> 3 | J80: =IF(Unemployment!$F$5=Unemployment!$B$33,Unemployment!B43,IF(Unemployment!$F$5=Unemployment!$C$33,Unemployment!C43,IF(Unemployment!$F$5=Unemployment!$D$33,Unemployment!D43,IF(Unemployment!$F$5=Unemployment!$E$33,Unemployment!E43,1)))) -> 3 | K80: =AVERAGE(C80*0.2222 + D80*0.3056 + E80*0.1667 + F80*0.1389 + I80*0.0556 + J80*0.1111) -> 3.5281 | L80: =IF(PMI!$F$22=PMI!$B$43,PMI!$B53,IF(PMI!$F$22=PMI!$C$43,PMI!$C53,IF(PMI!$F$22=PMI!$D$44,PMI!$D53,IF(PMI!$F$22=PMI!$E$43,PMI!$E53,1)))) -> 4 | M80: =BNP!J132 -> 4 | N80: =IF('10 yr rate'!$E$21='10 yr rate'!$B$35,'10 yr rate'!$B45,IF('10 yr rate'!$E$21='10 yr rate'!$C$35,'10 yr rate'!$C45,IF('10 yr rate'!$E$21='10 yr rate'!$D$35,'10 yr rate'!$D45,IF('10 yr rate'!$E$21='10 yr rate'!$E$35,'10 yr rate'!$E45,1)))) -> 4 | O80: =IF('CPI(Inflation)'!$E$19='CPI(Inflation)'!$B$33,'CPI(Inflation)'!$B43,IF('CPI(Inflation)'!$E$19='CPI(Inflation)'!$C$33,'CPI(Inflation)'!$C43,IF('CPI(Inflation)'!$E$19='CPI(Inflation)'!$D$33,'CPI(Inflation)'!$D43,IF('CPI(Inflation)'!$E$19='CPI(Inflation)'!$E$33,'CPI(Inflation)'!$E43,1)))) -> 3 | P80: ='Baltic Dry Index'!B43 -> 3 | Q80: =IF(VIX!$F$6=VIX!$B$33,VIX!B43,IF(VIX!$F$6=VIX!$C$33,VIX!C43,IF(VIX!$F$6=VIX!$D$33,VIX!D43,IF(VIX!$F$6=VIX!$E$33,VIX!E43,1)))) -> 2 | R80: =IF(Currency!$F$6=Currency!$B$33,Currency!B43,IF(Currency!$F$6=Currency!$C$33,Currency!C43,IF(Currency!$F$6=Currency!$D$33,Currency!D43,IF(Currency!$F$6=Currency!$E$33,Currency!E43,1)))) -> 4 | S80: =IF(Unemployment!$F$6=Unemployment!$B$33,Unemployment!B43,IF(Unemployment!$F$6=Unemployment!$C$33,Unemployment!C43,IF(Unemployment!$F$6=Unemployment!$D$33,Unemployment!D43,IF(Unemployment!$F$6=Unemployment!$E$33,Unemployment!E43,1)))) -> 3 | T80: =AVERAGE(L80*0.2222 + M80*0.3056 + N80*0.1667 + O80*0.1389 + R80*0.0556 + S80*0.1111) -> 3.7504
B81: Utilities | C81: =IF(PMI!$F$21=PMI!$B$43,PMI!$B54,IF(PMI!$F$21=PMI!$C$43,PMI!$C54,IF(PMI!$F$21=PMI!$D$43,PMI!$D54,IF(PMI!$F$21=PMI!$E$43,PMI!$E54,1)))) -> 2 | D81: =BNP!I137 -> 1 | E81: =IF('10 yr rate'!$E$20='10 yr rate'!$B$35,'10 yr rate'!$B46,IF('10 yr rate'!$E$20='10 yr rate'!$C$35,'10 yr rate'!$C46,IF('10 yr rate'!$E$20='10 yr rate'!$D$35,'10 yr rate'!$D46,IF('10 yr rate'!$E$20='10 yr rate'!$E$35,'10 yr rate'!$E46,1)))) -> 2 | F81: =IF('CPI(Inflation)'!$E$18='CPI(Inflation)'!$B$33,'CPI(Inflation)'!$B44,IF('CPI(Inflation)'!$E$18='CPI(Inflation)'!$C$33,'CPI(Inflation)'!$C44,IF('CPI(Inflation)'!$E$18='CPI(Inflation)'!$D$33,'CPI(Inflation)'!$D44,IF('CPI(Inflation)'!$E$18='CPI(Inflation)'!$E$33,'CPI(Inflation)'!$E44,1)))) -> 2 | G81: ='Baltic Dry Index'!B44 -> 2 | H81: =IF(VIX!$F$5=VIX!$B$33,VIX!B44,IF(VIX!$F$5=VIX!$C$33,VIX!C44,IF(VIX!$F$5=VIX!$D$33,VIX!D44,IF(VIX!$F$5=VIX!$E$33,VIX!E44,1)))) -> 2 | I81: =IF(Currency!$F$5=Currency!$B$33,Currency!B44,IF(Currency!$F$5=Currency!$C$33,Currency!C44,IF(Currency!$F$5=Currency!$D$33,Currency!D44,IF(Currency!$F$5=Currency!$E$33,Currency!E44,1)))) -> 4 | J81: =IF(Unemployment!$F$5=Unemployment!$B$33,Unemployment!B44,IF(Unemployment!$F$5=Unemployment!$C$33,Unemployment!C44,IF(Unemployment!$F$5=Unemployment!$D$33,Unemployment!D44,IF(Unemployment!$F$5=Unemployment!$E$33,Unemployment!E44,1)))) -> 4 | K81: =AVERAGE(C81*0.2222 + D81*0.3056 + E81*0.1667 + F81*0.1389 + I81*0.0556 + J81*0.1111) -> 2.028 | L81: =IF(PMI!$F$22=PMI!$B$43,PMI!$B54,IF(PMI!$F$22=PMI!$C$43,PMI!$C54,IF(PMI!$F$22=PMI!$D$44,PMI!$D54,IF(PMI!$F$22=PMI!$E$43,PMI!$E54,1)))) -> 2 | M81: =BNP!J137 -> 2 | N81: =IF('10 yr rate'!$E$21='10 yr rate'!$B$35,'10 yr rate'!$B46,IF('10 yr rate'!$E$21='10 yr rate'!$C$35,'10 yr rate'!$C46,IF('10 yr rate'!$E$21='10 yr rate'!$D$35,'10 yr rate'!$D46,IF('10 yr rate'!$E$21='10 yr rate'!$E$35,'10 yr rate'!$E46,1)))) -> 2 | O81: =IF('CPI(Inflation)'!$E$19='CPI(Inflation)'!$B$33,'CPI(Inflation)'!$B44,IF('CPI(Inflation)'!$E$19='CPI(Inflation)'!$C$33,'CPI(Inflation)'!$C44,IF('CPI(Inflation)'!$E$19='CPI(Inflation)'!$D$33,'CPI(Inflation)'!$D44,IF('CPI(Inflation)'!$E$19='CPI(Inflation)'!$E$33,'CPI(Inflation)'!$E44,1)))) -> 2 | P81: ='Baltic Dry Index'!B44 -> 2 | Q81: =IF(VIX!$F$6=VIX!$B$33,VIX!B44,IF(VIX!$F$6=VIX!$C$33,VIX!C44,IF(VIX!$F$6=VIX!$D$33,VIX!D44,IF(VIX!$F$6=VIX!$E$33,VIX!E44,1)))) -> 5 | R81: =IF(Currency!$F$6=Currency!$B$33,Currency!B44,IF(Currency!$F$6=Currency!$C$33,Currency!C44,IF(Currency!$F$6=Currency!$D$33,Currency!D44,IF(Currency!$F$6=Currency!$E$33,Currency!E44,1)))) -> 2 | S81: =IF(Unemployment!$F$6=Unemployment!$B$33,Unemployment!B44,IF(Unemployment!$F$6=Unemployment!$C$33,Unemployment!C44,IF(Unemployment!$F$6=Unemployment!$D$33,Unemployment!D44,IF(Unemployment!$F$6=Unemployment!$E$33,Unemployment!E44,1)))) -> 4 | T81: =AVERAGE(L81*0.2222 + M81*0.3056 + N81*0.1667 + O81*0.1389 + R81*0.0556 + S81*0.1111) -> 2.2224
K109: ='Fremtid vækst'!$C$3 -> Q1 2026 | T109: ='Fremtid vækst'!$D$3 -> Q2 2026
B110: USA | C110: PMI | D110: BNP | E110: 10 YR | F110: CPI | G110: Baltic Dry Index | H110: VIX | I110: Currency | J110: Unemployment | K110: Makro score | L110: PMI | M110: BNP | N110: 10 YR | O110: CPI | P110: Baltic Dry Index | Q110: VIX | R110: Currency | S110: Unemployment | T110: Makro score
B111: Financials | C111: =IF(PMI!$F$11=PMI!$B$43,PMI!$B44,IF(PMI!$F$11=PMI!$C$43,PMI!$C44,IF(PMI!$F$11=PMI!$D$43,PMI!$D44,IF(PMI!$F$11=PMI!$E$43,PMI!$E44,1)))) -> 4 | D111: =BNP!I88 -> 3 | E111: =IF('10 yr rate'!$E$10='10 yr rate'!$B$35,'10 yr rate'!$B36,IF('10 yr rate'!$E$10='10 yr rate'!$C$35,'10 yr rate'!$C36,IF('10 yr rate'!$E$10='10 yr rate'!$D$35,'10 yr rate'!$D36,IF('10 yr rate'!$E$10='10 yr rate'!$E$35,'10 yr rate'!$E36,1)))) -> 2 | F111: =IF('CPI(Inflation)'!$E$29='CPI(Inflation)'!$B$33,'CPI(Inflation)'!$B34,IF('CPI(Inflation)'!$E$29='CPI(Inflation)'!$C$33,'CPI(Inflation)'!$C34,IF('CPI(Inflation)'!$E$29='CPI(Inflation)'!$D$33,'CPI(Inflation)'!$D34,IF('CPI(Inflation)'!$E$29='CPI(Inflation)'!$E$33,'CPI(Inflation)'!$E34,1)))) -> 4 | G111: ='Baltic Dry Index'!B34 -> 4 | H111: =IF(VIX!$F$15=VIX!$B$33,VIX!B34,IF(VIX!$F$15=VIX!$C$33,VIX!C34,IF(VIX!$F$15=VIX!$D$33,VIX!D34,IF(VIX!$F$15=VIX!$E$33,VIX!E34,1)))) -> 4 | I111: =IF(Currency!$F$15=Currency!$B$33,Currency!B34,IF(Currency!$F$15=Currency!$C$33,Currency!C34,IF(Currency!$F$15=Currency!$D$33,Currency!D34,IF(Currency!$F$15=Currency!$E$33,Currency!E34,1)))) -> 2 | J111: =IF(Unemployment!$F$15=Unemployment!$B$33,Unemployment!B34,IF(Unemployment!$F$15=Unemployment!$C$33,Unemployment!C34,IF(Unemployment!$F$15=Unemployment!$D$33,Unemployment!D34,IF(Unemployment!$F$15=Unemployment!$E$33,Unemployment!E34,1)))) -> 4 | K111: =AVERAGE(C111*0.2222 + D111*0.3056 + E111*0.1667 + F111*0.1389 + I111*0.0556 + J111*0.1111) -> 3.2502 | L111: =IF(PMI!$F$12=PMI!$B$43,PMI!$B44,IF(PMI!$F$12=PMI!$C$43,PMI!$C44,IF(PMI!$F$12=PMI!$D$44,PMI!$D44,IF(PMI!$F$12=PMI!$E$43,PMI!$E44,1)))) -> 4 | M111: =BNP!J88 -> 3 | N111: =IF('10 yr rate'!$E$11='10 yr rate'!$B$35,'10 yr rate'!$B36,IF('10 yr rate'!$E$11='10 yr rate'!$C$35,'10 yr rate'!$C36,IF('10 yr rate'!$E$11='10 yr rate'!$D$35,'10 yr rate'!$D36,IF('10 yr rate'!$E$11='10 yr rate'!$E$35,'10 yr rate'!$E36,1)))) -> 2 | O111: =IF('CPI(Inflation)'!$E$30='CPI(Inflation)'!$B$33,'CPI(Inflation)'!$B34,IF('CPI(Inflation)'!$E$30='CPI(Inflation)'!$C$33,'CPI(Inflation)'!$C34,IF('CPI(Inflation)'!$E$30='CPI(Inflation)'!$D$33,'CPI(Inflation)'!$D34,IF('CPI(Inflation)'!$E$30='CPI(Inflation)'!$E$33,'CPI(Inflation)'!$E34,1)))) -> 4 | P111: ='Baltic Dry Index'!B34 -> 4 | Q111: =IF(VIX!$F$16=VIX!$B$33,VIX!B34,IF(VIX!$F$16=VIX!$C$33,VIX!C34,IF(VIX!$F$16=VIX!$D$33,VIX!D34,IF(VIX!$F$16=VIX!$E$33,VIX!E34,1)))) -> 1 | R111: =IF(Currency!$F$16=Currency!$B$33,Currency!B34,IF(Currency!$F$16=Currency!$C$33,Currency!C34,IF(Currency!$F$16=Currency!$D$33,Currency!D34,IF(Currency!$F$16=Currency!$E$33,Currency!E34,1)))) -> 4 | S111: =IF(Unemployment!$F$16=Unemployment!$B$33,Unemployment!B34,IF(Unemployment!$F$16=Unemployment!$C$33,Unemployment!C34,IF(Unemployment!$F$16=Unemployment!$D$33,Unemployment!D34,IF(Unemployment!$F$16=Unemployment!$E$33,Unemployment!E34,1)))) -> 4 | T111: =AVERAGE(L111*0.2222 + M111*0.3056 + N111*0.1667 + O111*0.1389 + R111*0.0556 + S111*0.1111) -> 3.3614
B112: Real Estate | C112: =IF(PMI!$F$11=PMI!$B$43,PMI!$B45,IF(PMI!$F$11=PMI!$C$43,PMI!$C45,IF(PMI!$F$11=PMI!$D$43,PMI!$D45,IF(PMI!$F$11=PMI!$E$43,PMI!$E45,1)))) -> 2 | D112: =BNP!I93 -> 4 | E112: =IF('10 yr rate'!$E$10='10 yr rate'!$B$35,'10 yr rate'!$B37,IF('10 yr rate'!$E$10='10 yr rate'!$C$35,'10 yr rate'!$C37,IF('10 yr rate'!$E$10='10 yr rate'!$D$35,'10 yr rate'!$D37,IF('10 yr rate'!$E$10='10 yr rate'!$E$35,'10 yr rate'!$E37,1)))) -> 3 | F112: =IF('CPI(Inflation)'!$E$29='CPI(Inflation)'!$B$33,'CPI(Inflation)'!$B35,IF('CPI(Inflation)'!$E$29='CPI(Inflation)'!$C$33,'CPI(Inflation)'!$C35,IF('CPI(Inflation)'!$E$29='CPI(Inflation)'!$D$33,'CPI(Inflation)'!$D35,IF('CPI(Inflation)'!$E$29='CPI(Inflation)'!$E$33,'CPI(Inflation)'!$E35,1)))) -> 2 | G112: ='Baltic Dry Index'!B35 -> 5 | H112: =IF(VIX!$F$15=VIX!$B$33,VIX!B35,IF(VIX!$F$15=VIX!$C$33,VIX!C35,IF(VIX!$F$15=VIX!$D$33,VIX!D35,IF(VIX!$F$15=VIX!$E$33,VIX!E35,1)))) -> 5 | I112: =IF(Currency!$F$15=Currency!$B$33,Currency!B35,IF(Currency!$F$15=Currency!$C$33,Currency!C35,IF(Currency!$F$15=Currency!$D$33,Currency!D35,IF(Currency!$F$15=Currency!$E$33,Currency!E35,1)))) -> 3 | J112: =IF(Unemployment!$F$15=Unemployment!$B$33,Unemployment!B35,IF(Unemployment!$F$15=Unemployment!$C$33,Unemployment!C35,IF(Unemployment!$F$15=Unemployment!$D$33,Unemployment!D35,IF(Unemployment!$F$15=Unemployment!$E$33,Unemployment!E35,1)))) -> 5 | K112: =AVERAGE(C112*0.2222 + D112*0.3056 + E112*0.1667 + F112*0.1389 + I112*0.0556 + J112*0.1111) -> 3.167 | L112: =IF(PMI!$F$12=PMI!$B$43,PMI!$B45,IF(PMI!$F$12=PMI!$C$43,PMI!$C45,IF(PMI!$F$12=PMI!$D$44,PMI!$D45,IF(PMI!$F$12=PMI!$E$43,PMI!$E45,1)))) -> 2 | M112: =BNP!J93 -> 2 | N112: =IF('10 yr rate'!$E$11='10 yr rate'!$B$35,'10 yr rate'!$B37,IF('10 yr rate'!$E$11='10 yr rate'!$C$35,'10 yr rate'!$C37,IF('10 yr rate'!$E$11='10 yr rate'!$D$35,'10 yr rate'!$D37,IF('10 yr rate'!$E$11='10 yr rate'!$E$35,'10 yr rate'!$E37,1)))) -> 3 | O112: =IF('CPI(Inflation)'!$E$30='CPI(Inflation)'!$B$33,'CPI(Inflation)'!$B35,IF('CPI(Inflation)'!$E$30='CPI(Inflation)'!$C$33,'CPI(Inflation)'!$C35,IF('CPI(Inflation)'!$E$30='CPI(Inflation)'!$D$33,'CPI(Inflation)'!$D35,IF('CPI(Inflation)'!$E$30='CPI(Inflation)'!$E$33,'CPI(Inflation)'!$E35,1)))) -> 2 | P112: ='Baltic Dry Index'!B35 -> 5 | Q112: =IF(VIX!$F$16=VIX!$B$33,VIX!B35,IF(VIX!$F$16=VIX!$C$33,VIX!C35,IF(VIX!$F$16=VIX!$D$33,VIX!D35,IF(VIX!$F$16=VIX!$E$33,VIX!E35,1)))) -> 1 | R112: =IF(Currency!$F$16=Currency!$B$33,Currency!B35,IF(Currency!$F$16=Currency!$C$33,Currency!C35,IF(Currency!$F$16=Currency!$D$33,Currency!D35,IF(Currency!$F$16=Currency!$E$33,Currency!E35,1)))) -> 2 | S112: =IF(Unemployment!$F$16=Unemployment!$B$33,Unemployment!B35,IF(Unemployment!$F$16=Unemployment!$C$33,Unemployment!C35,IF(Unemployment!$F$16=Unemployment!$D$33,Unemployment!D35,IF(Unemployment!$F$16=Unemployment!$E$33,Unemployment!E35,1)))) -> 5 | T112: =AVERAGE(L112*0.2222 + M112*0.3056 + N112*0.1667 + O112*0.1389 + R112*0.0556 + S112*0.1111) -> 2.5002
B113: Consumer Discretionary | C113: =IF(PMI!$F$11=PMI!$B$43,PMI!$B46,IF(PMI!$F$11=PMI!$C$43,PMI!$C46,IF(PMI!$F$11=PMI!$D$43,PMI!$D46,IF(PMI!$F$11=PMI!$E$43,PMI!$E46,1)))) -> 4 | D113: =BNP!I98 -> 1 | E113: =IF('10 yr rate'!$E$10='10 yr rate'!$B$35,'10 yr rate'!$B38,IF('10 yr rate'!$E$10='10 yr rate'!$C$35,'10 yr rate'!$C38,IF('10 yr rate'!$E$10='10 yr rate'!$D$35,'10 yr rate'!$D38,IF('10 yr rate'!$E$10='10 yr rate'!$E$35,'10 yr rate'!$E38,1)))) -> 2 | F113: =IF('CPI(Inflation)'!$E$29='CPI(Inflation)'!$B$33,'CPI(Inflation)'!$B36,IF('CPI(Inflation)'!$E$29='CPI(Inflation)'!$C$33,'CPI(Inflation)'!$C36,IF('CPI(Inflation)'!$E$29='CPI(Inflation)'!$D$33,'CPI(Inflation)'!$D36,IF('CPI(Inflation)'!$E$29='CPI(Inflation)'!$E$33,'CPI(Inflation)'!$E36,1)))) -> 4 | G113: ='Baltic Dry Index'!B36 -> 5 | H113: =IF(VIX!$F$15=VIX!$B$33,VIX!B36,IF(VIX!$F$15=VIX!$C$33,VIX!C36,IF(VIX!$F$15=VIX!$D$33,VIX!D36,IF(VIX!$F$15=VIX!$E$33,VIX!E36,1)))) -> 5 | I113: =IF(Currency!$F$15=Currency!$B$33,Currency!B36,IF(Currency!$F$15=Currency!$C$33,Currency!C36,IF(Currency!$F$15=Currency!$D$33,Currency!D36,IF(Currency!$F$15=Currency!$E$33,Currency!E36,1)))) -> 2 | J113: =IF(Unemployment!$F$15=Unemployment!$B$33,Unemployment!B36,IF(Unemployment!$F$15=Unemployment!$C$33,Unemployment!C36,IF(Unemployment!$F$15=Unemployment!$D$33,Unemployment!D36,IF(Unemployment!$F$15=Unemployment!$E$33,Unemployment!E36,1)))) -> 5 | K113: =AVERAGE(C113*0.2222 + D113*0.3056 + E113*0.1667 + F113*0.1389 + I113*0.0556 + J113*0.1111) -> 2.7501 | L113: =IF(PMI!$F$12=PMI!$B$43,PMI!$B46,IF(PMI!$F$12=PMI!$C$43,PMI!$C46,IF(PMI!$F$12=PMI!$D$44,PMI!$D46,IF(PMI!$F$12=PMI!$E$43,PMI!$E46,1)))) -> 4 | M113: =BNP!J98 -> 3 | N113: =IF('10 yr rate'!$E$11='10 yr rate'!$B$35,'10 yr rate'!$B38,IF('10 yr rate'!$E$11='10 yr rate'!$C$35,'10 yr rate'!$C38,IF('10 yr rate'!$E$11='10 yr rate'!$D$35,'10 yr rate'!$D38,IF('10 yr rate'!$E$11='10 yr rate'!$E$35,'10 yr rate'!$E38,1)))) -> 2 | O113: =IF('CPI(Inflation)'!$E$30='CPI(Inflation)'!$B$33,'CPI(Inflation)'!$B36,IF('CPI(Inflation)'!$E$30='CPI(Inflation)'!$C$33,'CPI(Inflation)'!$C36,IF('CPI(Inflation)'!$E$30='CPI(Inflation)'!$D$33,'CPI(Inflation)'!$D36,IF('CPI(Inflation)'!$E$30='CPI(Inflation)'!$E$33,'CPI(Inflation)'!$E36,1)))) -> 4 | P113: ='Baltic Dry Index'!B36 -> 5 | Q113: =IF(VIX!$F$16=VIX!$B$33,VIX!B36,IF(VIX!$F$16=VIX!$C$33,VIX!C36,IF(VIX!$F$16=VIX!$D$33,VIX!D36,IF(VIX!$F$16=VIX!$E$33,VIX!E36,1)))) -> 1 | R113: =IF(Currency!$F$16=Currency!$B$33,Currency!B36,IF(Currency!$F$16=Currency!$C$33,Currency!C36,IF(Currency!$F$16=Currency!$D$33,Currency!D36,IF(Currency!$F$16=Currency!$E$33,Currency!E36,1)))) -> 4 | S113: =IF(Unemployment!$F$16=Unemployment!$B$33,Unemployment!B36,IF(Unemployment!$F$16=Unemployment!$C$33,Unemployment!C36,IF(Unemployment!$F$16=Unemployment!$D$33,Unemployment!D36,IF(Unemployment!$F$16=Unemployment!$E$33,Unemployment!E36,1)))) -> 5 | T113: =AVERAGE(L113*0.2222 + M113*0.3056 + N113*0.1667 + O113*0.1389 + R113*0.0556 + S113*0.1111) -> 3.4725
B114: Information Technology | C114: =IF(PMI!$F$11=PMI!$B$43,PMI!$B47,IF(PMI!$F$11=PMI!$C$43,PMI!$C47,IF(PMI!$F$11=PMI!$D$43,PMI!$D47,IF(PMI!$F$11=PMI!$E$43,PMI!$E47,1)))) -> 5 | D114: =BNP!I103 -> 2 | E114: =IF('10 yr rate'!$E$10='10 yr rate'!$B$35,'10 yr rate'!$B39,IF('10 yr rate'!$E$10='10 yr rate'!$C$35,'10 yr rate'!$C39,IF('10 yr rate'!$E$10='10 yr rate'!$D$35,'10 yr rate'!$D39,IF('10 yr rate'!$E$10='10 yr rate'!$E$35,'10 yr rate'!$E39,1)))) -> 3 | F114: =IF('CPI(Inflation)'!$E$29='CPI(Inflation)'!$B$33,'CPI(Inflation)'!$B37,IF('CPI(Inflation)'!$E$29='CPI(Inflation)'!$C$33,'CPI(Inflation)'!$C37,IF('CPI(Inflation)'!$E$29='CPI(Inflation)'!$D$33,'CPI(Inflation)'!$D37,IF('CPI(Inflation)'!$E$29='CPI(Inflation)'!$E$33,'CPI(Inflation)'!$E37,1)))) -> 5 | G114: ='Baltic Dry Index'!B37 -> 4 | H114: =IF(VIX!$F$15=VIX!$B$33,VIX!B37,IF(VIX!$F$15=VIX!$C$33,VIX!C37,IF(VIX!$F$15=VIX!$D$33,VIX!D37,IF(VIX!$F$15=VIX!$E$33,VIX!E37,1)))) -> 4 | I114: =IF(Currency!$F$15=Currency!$B$33,Currency!B37,IF(Currency!$F$15=Currency!$C$33,Currency!C37,IF(Currency!$F$15=Currency!$D$33,Currency!D37,IF(Currency!$F$15=Currency!$E$33,Currency!E37,1)))) -> 3 | J114: =IF(Unemployment!$F$15=Unemployment!$B$33,Unemployment!B37,IF(Unemployment!$F$15=Unemployment!$C$33,Unemployment!C37,IF(Unemployment!$F$15=Unemployment!$D$33,Unemployment!D37,IF(Unemployment!$F$15=Unemployment!$E$33,Unemployment!E37,1)))) -> 4 | K114: =AVERAGE(C114*0.2222 + D114*0.3056 + E114*0.1667 + F114*0.1389 + I114*0.0556 + J114*0.1111) -> 3.528 | L114: =IF(PMI!$F$12=PMI!$B$43,PMI!$B47,IF(PMI!$F$12=PMI!$C$43,PMI!$C47,IF(PMI!$F$12=PMI!$D$44,PMI!$D47,IF(PMI!$F$12=PMI!$E$43,PMI!$E47,1)))) -> 5 | M114: =BNP!J103 -> 4 | N114: =IF('10 yr rate'!$E$11='10 yr rate'!$B$35,'10 yr rate'!$B39,IF('10 yr rate'!$E$11='10 yr rate'!$C$35,'10 yr rate'!$C39,IF('10 yr rate'!$E$11='10 yr rate'!$D$35,'10 yr rate'!$D39,IF('10 yr rate'!$E$11='10 yr rate'!$E$35,'10 yr rate'!$E39,1)))) -> 3 | O114: =IF('CPI(Inflation)'!$E$30='CPI(Inflation)'!$B$33,'CPI(Inflation)'!$B37,IF('CPI(Inflation)'!$E$30='CPI(Inflation)'!$C$33,'CPI(Inflation)'!$C37,IF('CPI(Inflation)'!$E$30='CPI(Inflation)'!$D$33,'CPI(Inflation)'!$D37,IF('CPI(Inflation)'!$E$30='CPI(Inflation)'!$E$33,'CPI(Inflation)'!$E37,1)))) -> 5 | P114: ='Baltic Dry Index'!B37 -> 4 | Q114: =IF(VIX!$F$16=VIX!$B$33,VIX!B37,IF(VIX!$F$16=VIX!$C$33,VIX!C37,IF(VIX!$F$16=VIX!$D$33,VIX!D37,IF(VIX!$F$16=VIX!$E$33,VIX!E37,1)))) -> 1 | R114: =IF(Currency!$F$16=Currency!$B$33,Currency!B37,IF(Currency!$F$16=Currency!$C$33,Currency!C37,IF(Currency!$F$16=Currency!$D$33,Currency!D37,IF(Currency!$F$16=Currency!$E$33,Currency!E37,1)))) -> 5 | S114: =IF(Unemployment!$F$16=Unemployment!$B$33,Unemployment!B37,IF(Unemployment!$F$16=Unemployment!$C$33,Unemployment!C37,IF(Unemployment!$F$16=Unemployment!$D$33,Unemployment!D37,IF(Unemployment!$F$16=Unemployment!$E$33,Unemployment!E37,1)))) -> 4 | T114: =AVERAGE(L114*0.2222 + M114*0.3056 + N114*0.1667 + O114*0.1389 + R114*0.0556 + S114*0.1111) -> 4.2504
B115: Industrials | C115: =IF(PMI!$F$11=PMI!$B$43,PMI!$B48,IF(PMI!$F$11=PMI!$C$43,PMI!$C48,IF(PMI!$F$11=PMI!$D$43,PMI!$D48,IF(PMI!$F$11=PMI!$E$43,PMI!$E48,1)))) -> 4 | D115: =BNP!I108 -> 3 | E115: =IF('10 yr rate'!$E$10='10 yr rate'!$B$35,'10 yr rate'!$B40,IF('10 yr rate'!$E$10='10 yr rate'!$C$35,'10 yr rate'!$C40,IF('10 yr rate'!$E$10='10 yr rate'!$D$35,'10 yr rate'!$D40,IF('10 yr rate'!$E$10='10 yr rate'!$E$35,'10 yr rate'!$E40,1)))) -> 2 | F115: =IF('CPI(Inflation)'!$E$29='CPI(Inflation)'!$B$33,'CPI(Inflation)'!$B38,IF('CPI(Inflation)'!$E$29='CPI(Inflation)'!$C$33,'CPI(Inflation)'!$C38,IF('CPI(Inflation)'!$E$29='CPI(Inflation)'!$D$33,'CPI(Inflation)'!$D38,IF('CPI(Inflation)'!$E$29='CPI(Inflation)'!$E$33,'CPI(Inflation)'!$E38,1)))) -> 4 | G115: ='Baltic Dry Index'!B38 -> 5 | H115: =IF(VIX!$F$15=VIX!$B$33,VIX!B38,IF(VIX!$F$15=VIX!$C$33,VIX!C38,IF(VIX!$F$15=VIX!$D$33,VIX!D38,IF(VIX!$F$15=VIX!$E$33,VIX!E38,1)))) -> 5 | I115: =IF(Currency!$F$15=Currency!$B$33,Currency!B38,IF(Currency!$F$15=Currency!$C$33,Currency!C38,IF(Currency!$F$15=Currency!$D$33,Currency!D38,IF(Currency!$F$15=Currency!$E$33,Currency!E38,1)))) -> 2 | J115: =IF(Unemployment!$F$15=Unemployment!$B$33,Unemployment!B38,IF(Unemployment!$F$15=Unemployment!$C$33,Unemployment!C38,IF(Unemployment!$F$15=Unemployment!$D$33,Unemployment!D38,IF(Unemployment!$F$15=Unemployment!$E$33,Unemployment!E38,1)))) -> 5 | K115: =AVERAGE(C115*0.2222 + D115*0.3056 + E115*0.1667 + F115*0.1389 + I115*0.0556 + J115*0.1111) -> 3.3613 | L115: =IF(PMI!$F$12=PMI!$B$43,PMI!$B48,IF(PMI!$F$12=PMI!$C$43,PMI!$C48,IF(PMI!$F$12=PMI!$D$44,PMI!$D48,IF(PMI!$F$12=PMI!$E$43,PMI!$E48,1)))) -> 4 | M115: =BNP!J108 -> 3 | N115: =IF('10 yr rate'!$E$11='10 yr rate'!$B$35,'10 yr rate'!$B40,IF('10 yr rate'!$E$11='10 yr rate'!$C$35,'10 yr rate'!$C40,IF('10 yr rate'!$E$11='10 yr rate'!$D$35,'10 yr rate'!$D40,IF('10 yr rate'!$E$11='10 yr rate'!$E$35,'10 yr rate'!$E40,1)))) -> 2 | O115: =IF('CPI(Inflation)'!$E$30='CPI(Inflation)'!$B$33,'CPI(Inflation)'!$B38,IF('CPI(Inflation)'!$E$30='CPI(Inflation)'!$C$33,'CPI(Inflation)'!$C38,IF('CPI(Inflation)'!$E$30='CPI(Inflation)'!$D$33,'CPI(Inflation)'!$D38,IF('CPI(Inflation)'!$E$30='CPI(Inflation)'!$E$33,'CPI(Inflation)'!$E38,1)))) -> 4 | P115: ='Baltic Dry Index'!B38 -> 5 | Q115: =IF(VIX!$F$16=VIX!$B$33,VIX!B38,IF(VIX!$F$16=VIX!$C$33,VIX!C38,IF(VIX!$F$16=VIX!$D$33,VIX!D38,IF(VIX!$F$16=VIX!$E$33,VIX!E38,1)))) -> 1 | R115: =IF(Currency!$F$16=Currency!$B$33,Currency!B38,IF(Currency!$F$16=Currency!$C$33,Currency!C38,IF(Currency!$F$16=Currency!$D$33,Currency!D38,IF(Currency!$F$16=Currency!$E$33,Currency!E38,1)))) -> 4 | S115: =IF(Unemployment!$F$16=Unemployment!$B$33,Unemployment!B38,IF(Unemployment!$F$16=Unemployment!$C$33,Unemployment!C38,IF(Unemployment!$F$16=Unemployment!$D$33,Unemployment!D38,IF(Unemployment!$F$16=Unemployment!$E$33,Unemployment!E38,1)))) -> 5 | T115: =AVERAGE(L115*0.2222 + M115*0.3056 + N115*0.1667 + O115*0.1389 + R115*0.0556 + S115*0.1111) -> 3.4725
B116: Materials | C116: =IF(PMI!$F$11=PMI!$B$43,PMI!$B49,IF(PMI!$F$11=PMI!$C$43,PMI!$C49,IF(PMI!$F$11=PMI!$D$43,PMI!$D49,IF(PMI!$F$11=PMI!$E$43,PMI!$E49,1)))) -> 2 | D116: =BNP!I113 -> 3 | E116: =IF('10 yr rate'!$E$10='10 yr rate'!$B$35,'10 yr rate'!$B41,IF('10 yr rate'!$E$10='10 yr rate'!$C$35,'10 yr rate'!$C41,IF('10 yr rate'!$E$10='10 yr rate'!$D$35,'10 yr rate'!$D41,IF('10 yr rate'!$E$10='10 yr rate'!$E$35,'10 yr rate'!$E41,1)))) -> 3 | F116: =IF('CPI(Inflation)'!$E$29='CPI(Inflation)'!$B$33,'CPI(Inflation)'!$B39,IF('CPI(Inflation)'!$E$29='CPI(Inflation)'!$C$33,'CPI(Inflation)'!$C39,IF('CPI(Inflation)'!$E$29='CPI(Inflation)'!$D$33,'CPI(Inflation)'!$D39,IF('CPI(Inflation)'!$E$29='CPI(Inflation)'!$E$33,'CPI(Inflation)'!$E39,1)))) -> 2 | G116: ='Baltic Dry Index'!B39 -> 4 | H116: =IF(VIX!$F$15=VIX!$B$33,VIX!B39,IF(VIX!$F$15=VIX!$C$33,VIX!C39,IF(VIX!$F$15=VIX!$D$33,VIX!D39,IF(VIX!$F$15=VIX!$E$33,VIX!E39,1)))) -> 4 | I116: =IF(Currency!$F$15=Currency!$B$33,Currency!B39,IF(Currency!$F$15=Currency!$C$33,Currency!C39,IF(Currency!$F$15=Currency!$D$33,Currency!D39,IF(Currency!$F$15=Currency!$E$33,Currency!E39,1)))) -> 3 | J116: =IF(Unemployment!$F$15=Unemployment!$B$33,Unemployment!B39,IF(Unemployment!$F$15=Unemployment!$C$33,Unemployment!C39,IF(Unemployment!$F$15=Unemployment!$D$33,Unemployment!D39,IF(Unemployment!$F$15=Unemployment!$E$33,Unemployment!E39,1)))) -> 4 | K116: =AVERAGE(C116*0.2222 + D116*0.3056 + E116*0.1667 + F116*0.1389 + I116*0.0556 + J116*0.1111) -> 2.7503 | L116: =IF(PMI!$F$12=PMI!$B$43,PMI!$B49,IF(PMI!$F$12=PMI!$C$43,PMI!$C49,IF(PMI!$F$12=PMI!$D$44,PMI!$D49,IF(PMI!$F$12=PMI!$E$43,PMI!$E49,1)))) -> 2 | M116: =BNP!J113 -> 1 | N116: =IF('10 yr rate'!$E$11='10 yr rate'!$B$35,'10 yr rate'!$B41,IF('10 yr rate'!$E$11='10 yr rate'!$C$35,'10 yr rate'!$C41,IF('10 yr rate'!$E$11='10 yr rate'!$D$35,'10 yr rate'!$D41,IF('10 yr rate'!$E$11='10 yr rate'!$E$35,'10 yr rate'!$E41,1)))) -> 3 | O116: =IF('CPI(Inflation)'!$E$30='CPI(Inflation)'!$B$33,'CPI(Inflation)'!$B39,IF('CPI(Inflation)'!$E$30='CPI(Inflation)'!$C$33,'CPI(Inflation)'!$C39,IF('CPI(Inflation)'!$E$30='CPI(Inflation)'!$D$33,'CPI(Inflation)'!$D39,IF('CPI(Inflation)'!$E$30='CPI(Inflation)'!$E$33,'CPI(Inflation)'!$E39,1)))) -> 2 | P116: ='Baltic Dry Index'!B39 -> 4 | Q116: =IF(VIX!$F$16=VIX!$B$33,VIX!B39,IF(VIX!$F$16=VIX!$C$33,VIX!C39,IF(VIX!$F$16=VIX!$D$33,VIX!D39,IF(VIX!$F$16=VIX!$E$33,VIX!E39,1)))) -> 2 | R116: =IF(Currency!$F$16=Currency!$B$33,Currency!B39,IF(Currency!$F$16=Currency!$C$33,Currency!C39,IF(Currency!$F$16=Currency!$D$33,Currency!D39,IF(Currency!$F$16=Currency!$E$33,Currency!E39,1)))) -> 2 | S116: =IF(Unemployment!$F$16=Unemployment!$B$33,Unemployment!B39,IF(Unemployment!$F$16=Unemployment!$C$33,Unemployment!C39,IF(Unemployment!$F$16=Unemployment!$D$33,Unemployment!D39,IF(Unemployment!$F$16=Unemployment!$E$33,Unemployment!E39,1)))) -> 4 | T116: =AVERAGE(L116*0.2222 + M116*0.3056 + N116*0.1667 + O116*0.1389 + R116*0.0556 + S116*0.1111) -> 2.0835
B117: Consumer Staples | C117: =IF(PMI!$F$11=PMI!$B$43,PMI!$B50,IF(PMI!$F$11=PMI!$C$43,PMI!$C50,IF(PMI!$F$11=PMI!$D$43,PMI!$D50,IF(PMI!$F$11=PMI!$E$43,PMI!$E50,1)))) -> 2 | D117: =BNP!I118 -> 4 | E117: =IF('10 yr rate'!$E$10='10 yr rate'!$B$35,'10 yr rate'!$B42,IF('10 yr rate'!$E$10='10 yr rate'!$C$35,'10 yr rate'!$C42,IF('10 yr rate'!$E$10='10 yr rate'!$D$35,'10 yr rate'!$D42,IF('10 yr rate'!$E$10='10 yr rate'!$E$35,'10 yr rate'!$E42,1)))) -> 4 | F117: =IF('CPI(Inflation)'!$E$29='CPI(Inflation)'!$B$33,'CPI(Inflation)'!$B40,IF('CPI(Inflation)'!$E$29='CPI(Inflation)'!$C$33,'CPI(Inflation)'!$C40,IF('CPI(Inflation)'!$E$29='CPI(Inflation)'!$D$33,'CPI(Inflation)'!$D40,IF('CPI(Inflation)'!$E$29='CPI(Inflation)'!$E$33,'CPI(Inflation)'!$E40,1)))) -> 2 | G117: ='Baltic Dry Index'!B40 -> 2 | H117: =IF(VIX!$F$15=VIX!$B$33,VIX!B40,IF(VIX!$F$15=VIX!$C$33,VIX!C40,IF(VIX!$F$15=VIX!$D$33,VIX!D40,IF(VIX!$F$15=VIX!$E$33,VIX!E40,1)))) -> 2 | I117: =IF(Currency!$F$15=Currency!$B$33,Currency!B40,IF(Currency!$F$15=Currency!$C$33,Currency!C40,IF(Currency!$F$15=Currency!$D$33,Currency!D40,IF(Currency!$F$15=Currency!$E$33,Currency!E40,1)))) -> 4 | J117: =IF(Unemployment!$F$15=Unemployment!$B$33,Unemployment!B40,IF(Unemployment!$F$15=Unemployment!$C$33,Unemployment!C40,IF(Unemployment!$F$15=Unemployment!$D$33,Unemployment!D40,IF(Unemployment!$F$15=Unemployment!$E$33,Unemployment!E40,1)))) -> 2 | K117: =AVERAGE(C117*0.2222 + D117*0.3056 + E117*0.1667 + F117*0.1389 + I117*0.0556 + J117*0.1111) -> 3.056 | L117: =IF(PMI!$F$12=PMI!$B$43,PMI!$B50,IF(PMI!$F$12=PMI!$C$43,PMI!$C50,IF(PMI!$F$12=PMI!$D$44,PMI!$D50,IF(PMI!$F$12=PMI!$E$43,PMI!$E50,1)))) -> 2 | M117: =BNP!J118 -> 2 | N117: =IF('10 yr rate'!$E$11='10 yr rate'!$B$35,'10 yr rate'!$B42,IF('10 yr rate'!$E$11='10 yr rate'!$C$35,'10 yr rate'!$C42,IF('10 yr rate'!$E$11='10 yr rate'!$D$35,'10 yr rate'!$D42,IF('10 yr rate'!$E$11='10 yr rate'!$E$35,'10 yr rate'!$E42,1)))) -> 4 | O117: =IF('CPI(Inflation)'!$E$30='CPI(Inflation)'!$B$33,'CPI(Inflation)'!$B40,IF('CPI(Inflation)'!$E$30='CPI(Inflation)'!$C$33,'CPI(Inflation)'!$C40,IF('CPI(Inflation)'!$E$30='CPI(Inflation)'!$D$33,'CPI(Inflation)'!$D40,IF('CPI(Inflation)'!$E$30='CPI(Inflation)'!$E$33,'CPI(Inflation)'!$E40,1)))) -> 2 | P117: ='Baltic Dry Index'!B40 -> 2 | Q117: =IF(VIX!$F$16=VIX!$B$33,VIX!B40,IF(VIX!$F$16=VIX!$C$33,VIX!C40,IF(VIX!$F$16=VIX!$D$33,VIX!D40,IF(VIX!$F$16=VIX!$E$33,VIX!E40,1)))) -> 5 | R117: =IF(Currency!$F$16=Currency!$B$33,Currency!B40,IF(Currency!$F$16=Currency!$C$33,Currency!C40,IF(Currency!$F$16=Currency!$D$33,Currency!D40,IF(Currency!$F$16=Currency!$E$33,Currency!E40,1)))) -> 2 | S117: =IF(Unemployment!$F$16=Unemployment!$B$33,Unemployment!B40,IF(Unemployment!$F$16=Unemployment!$C$33,Unemployment!C40,IF(Unemployment!$F$16=Unemployment!$D$33,Unemployment!D40,IF(Unemployment!$F$16=Unemployment!$E$33,Unemployment!E40,1)))) -> 2 | T117: =AVERAGE(L117*0.2222 + M117*0.3056 + N117*0.1667 + O117*0.1389 + R117*0.0556 + S117*0.1111) -> 2.3336
B118: Health Care | C118: =IF(PMI!$F$11=PMI!$B$43,PMI!$B51,IF(PMI!$F$11=PMI!$C$43,PMI!$C51,IF(PMI!$F$11=PMI!$D$43,PMI!$D51,IF(PMI!$F$11=PMI!$E$43,PMI!$E51,1)))) -> 3 | D118: =BNP!I123 -> 3 | E118: =IF('10 yr rate'!$E$10='10 yr rate'!$B$35,'10 yr rate'!$B43,IF('10 yr rate'!$E$10='10 yr rate'!$C$35,'10 yr rate'!$C43,IF('10 yr rate'!$E$10='10 yr rate'!$D$35,'10 yr rate'!$D43,IF('10 yr rate'!$E$10='10 yr rate'!$E$35,'10 yr rate'!$E43,1)))) -> 3 | F118: =IF('CPI(Inflation)'!$E$29='CPI(Inflation)'!$B$33,'CPI(Inflation)'!$B41,IF('CPI(Inflation)'!$E$29='CPI(Inflation)'!$C$33,'CPI(Inflation)'!$C41,IF('CPI(Inflation)'!$E$29='CPI(Inflation)'!$D$33,'CPI(Inflation)'!$D41,IF('CPI(Inflation)'!$E$29='CPI(Inflation)'!$E$33,'CPI(Inflation)'!$E41,1)))) -> 3 | G118: ='Baltic Dry Index'!B41 -> 2 | H118: =IF(VIX!$F$15=VIX!$B$33,VIX!B41,IF(VIX!$F$15=VIX!$C$33,VIX!C41,IF(VIX!$F$15=VIX!$D$33,VIX!D41,IF(VIX!$F$15=VIX!$E$33,VIX!E41,1)))) -> 2 | I118: =IF(Currency!$F$15=Currency!$B$33,Currency!B41,IF(Currency!$F$15=Currency!$C$33,Currency!C41,IF(Currency!$F$15=Currency!$D$33,Currency!D41,IF(Currency!$F$15=Currency!$E$33,Currency!E41,1)))) -> 3 | J118: =IF(Unemployment!$F$15=Unemployment!$B$33,Unemployment!B41,IF(Unemployment!$F$15=Unemployment!$C$33,Unemployment!C41,IF(Unemployment!$F$15=Unemployment!$D$33,Unemployment!D41,IF(Unemployment!$F$15=Unemployment!$E$33,Unemployment!E41,1)))) -> 2 | K118: =AVERAGE(C118*0.2222 + D118*0.3056 + E118*0.1667 + F118*0.1389 + I118*0.0556 + J118*0.1111) -> 2.8892 | L118: =IF(PMI!$F$12=PMI!$B$43,PMI!$B51,IF(PMI!$F$12=PMI!$C$43,PMI!$C51,IF(PMI!$F$12=PMI!$D$44,PMI!$D51,IF(PMI!$F$12=PMI!$E$43,PMI!$E51,1)))) -> 3 | M118: =BNP!J123 -> 3 | N118: =IF('10 yr rate'!$E$11='10 yr rate'!$B$35,'10 yr rate'!$B43,IF('10 yr rate'!$E$11='10 yr rate'!$C$35,'10 yr rate'!$C43,IF('10 yr rate'!$E$11='10 yr rate'!$D$35,'10 yr rate'!$D43,IF('10 yr rate'!$E$11='10 yr rate'!$E$35,'10 yr rate'!$E43,1)))) -> 3 | O118: =IF('CPI(Inflation)'!$E$30='CPI(Inflation)'!$B$33,'CPI(Inflation)'!$B41,IF('CPI(Inflation)'!$E$30='CPI(Inflation)'!$C$33,'CPI(Inflation)'!$C41,IF('CPI(Inflation)'!$E$30='CPI(Inflation)'!$D$33,'CPI(Inflation)'!$D41,IF('CPI(Inflation)'!$E$30='CPI(Inflation)'!$E$33,'CPI(Inflation)'!$E41,1)))) -> 3 | P118: ='Baltic Dry Index'!B41 -> 2 | Q118: =IF(VIX!$F$16=VIX!$B$33,VIX!B41,IF(VIX!$F$16=VIX!$C$33,VIX!C41,IF(VIX!$F$16=VIX!$D$33,VIX!D41,IF(VIX!$F$16=VIX!$E$33,VIX!E41,1)))) -> 5 | R118: =IF(Currency!$F$16=Currency!$B$33,Currency!B41,IF(Currency!$F$16=Currency!$C$33,Currency!C41,IF(Currency!$F$16=Currency!$D$33,Currency!D41,IF(Currency!$F$16=Currency!$E$33,Currency!E41,1)))) -> 3 | S118: =IF(Unemployment!$F$16=Unemployment!$B$33,Unemployment!B41,IF(Unemployment!$F$16=Unemployment!$C$33,Unemployment!C41,IF(Unemployment!$F$16=Unemployment!$D$33,Unemployment!D41,IF(Unemployment!$F$16=Unemployment!$E$33,Unemployment!E41,1)))) -> 2 | T118: =AVERAGE(L118*0.2222 + M118*0.3056 + N118*0.1667 + O118*0.1389 + R118*0.0556 + S118*0.1111) -> 2.8892
B119: Energy | C119: =IF(PMI!$F$11=PMI!$B$43,PMI!$B52,IF(PMI!$F$11=PMI!$C$43,PMI!$C52,IF(PMI!$F$11=PMI!$D$43,PMI!$D52,IF(PMI!$F$11=PMI!$E$43,PMI!$E52,1)))) -> 3 | D119: =BNP!I128 -> 5 | E119: =IF('10 yr rate'!$E$10='10 yr rate'!$B$35,'10 yr rate'!$B44,IF('10 yr rate'!$E$10='10 yr rate'!$C$35,'10 yr rate'!$C44,IF('10 yr rate'!$E$10='10 yr rate'!$D$35,'10 yr rate'!$D44,IF('10 yr rate'!$E$10='10 yr rate'!$E$35,'10 yr rate'!$E44,1)))) -> 5 | F119: =IF('CPI(Inflation)'!$E$29='CPI(Inflation)'!$B$33,'CPI(Inflation)'!$B42,IF('CPI(Inflation)'!$E$29='CPI(Inflation)'!$C$33,'CPI(Inflation)'!$C42,IF('CPI(Inflation)'!$E$29='CPI(Inflation)'!$D$33,'CPI(Inflation)'!$D42,IF('CPI(Inflation)'!$E$29='CPI(Inflation)'!$E$33,'CPI(Inflation)'!$E42,1)))) -> 3 | G119: ='Baltic Dry Index'!B42 -> 2 | H119: =IF(VIX!$F$15=VIX!$B$33,VIX!B42,IF(VIX!$F$15=VIX!$C$33,VIX!C42,IF(VIX!$F$15=VIX!$D$33,VIX!D42,IF(VIX!$F$15=VIX!$E$33,VIX!E42,1)))) -> 2 | I119: =IF(Currency!$F$15=Currency!$B$33,Currency!B42,IF(Currency!$F$15=Currency!$C$33,Currency!C42,IF(Currency!$F$15=Currency!$D$33,Currency!D42,IF(Currency!$F$15=Currency!$E$33,Currency!E42,1)))) -> 5 | J119: =IF(Unemployment!$F$15=Unemployment!$B$33,Unemployment!B42,IF(Unemployment!$F$15=Unemployment!$C$33,Unemployment!C42,IF(Unemployment!$F$15=Unemployment!$D$33,Unemployment!D42,IF(Unemployment!$F$15=Unemployment!$E$33,Unemployment!E42,1)))) -> 2 | K119: =AVERAGE(C119*0.2222 + D119*0.3056 + E119*0.1667 + F119*0.1389 + I119*0.0556 + J119*0.1111) -> 3.945 | L119: =IF(PMI!$F$12=PMI!$B$43,PMI!$B52,IF(PMI!$F$12=PMI!$C$43,PMI!$C52,IF(PMI!$F$12=PMI!$D$44,PMI!$D52,IF(PMI!$F$12=PMI!$E$43,PMI!$E52,1)))) -> 3 | M119: =BNP!J128 -> 3 | N119: =IF('10 yr rate'!$E$11='10 yr rate'!$B$35,'10 yr rate'!$B44,IF('10 yr rate'!$E$11='10 yr rate'!$C$35,'10 yr rate'!$C44,IF('10 yr rate'!$E$11='10 yr rate'!$D$35,'10 yr rate'!$D44,IF('10 yr rate'!$E$11='10 yr rate'!$E$35,'10 yr rate'!$E44,1)))) -> 5 | O119: =IF('CPI(Inflation)'!$E$30='CPI(Inflation)'!$B$33,'CPI(Inflation)'!$B42,IF('CPI(Inflation)'!$E$30='CPI(Inflation)'!$C$33,'CPI(Inflation)'!$C42,IF('CPI(Inflation)'!$E$30='CPI(Inflation)'!$D$33,'CPI(Inflation)'!$D42,IF('CPI(Inflation)'!$E$30='CPI(Inflation)'!$E$33,'CPI(Inflation)'!$E42,1)))) -> 3 | P119: ='Baltic Dry Index'!B42 -> 2 | Q119: =IF(VIX!$F$16=VIX!$B$33,VIX!B42,IF(VIX!$F$16=VIX!$C$33,VIX!C42,IF(VIX!$F$16=VIX!$D$33,VIX!D42,IF(VIX!$F$16=VIX!$E$33,VIX!E42,1)))) -> 1 | R119: =IF(Currency!$F$16=Currency!$B$33,Currency!B42,IF(Currency!$F$16=Currency!$C$33,Currency!C42,IF(Currency!$F$16=Currency!$D$33,Currency!D42,IF(Currency!$F$16=Currency!$E$33,Currency!E42,1)))) -> 3 | S119: =IF(Unemployment!$F$16=Unemployment!$B$33,Unemployment!B42,IF(Unemployment!$F$16=Unemployment!$C$33,Unemployment!C42,IF(Unemployment!$F$16=Unemployment!$D$33,Unemployment!D42,IF(Unemployment!$F$16=Unemployment!$E$33,Unemployment!E42,1)))) -> 2 | T119: =AVERAGE(L119*0.2222 + M119*0.3056 + N119*0.1667 + O119*0.1389 + R119*0.0556 + S119*0.1111) -> 3.2226
B120: Communications Services | C120: =IF(PMI!$F$11=PMI!$B$43,PMI!$B53,IF(PMI!$F$11=PMI!$C$43,PMI!$C53,IF(PMI!$F$11=PMI!$D$43,PMI!$D53,IF(PMI!$F$11=PMI!$E$43,PMI!$E53,1)))) -> 4 | D120: =BNP!I133 -> 3 | E120: =IF('10 yr rate'!$E$10='10 yr rate'!$B$35,'10 yr rate'!$B45,IF('10 yr rate'!$E$10='10 yr rate'!$C$35,'10 yr rate'!$C45,IF('10 yr rate'!$E$10='10 yr rate'!$D$35,'10 yr rate'!$D45,IF('10 yr rate'!$E$10='10 yr rate'!$E$35,'10 yr rate'!$E45,1)))) -> 3 | F120: =IF('CPI(Inflation)'!$E$29='CPI(Inflation)'!$B$33,'CPI(Inflation)'!$B43,IF('CPI(Inflation)'!$E$29='CPI(Inflation)'!$C$33,'CPI(Inflation)'!$C43,IF('CPI(Inflation)'!$E$29='CPI(Inflation)'!$D$33,'CPI(Inflation)'!$D43,IF('CPI(Inflation)'!$E$29='CPI(Inflation)'!$E$33,'CPI(Inflation)'!$E43,1)))) -> 4 | G120: ='Baltic Dry Index'!B43 -> 3 | H120: =IF(VIX!$F$15=VIX!$B$33,VIX!B43,IF(VIX!$F$15=VIX!$C$33,VIX!C43,IF(VIX!$F$15=VIX!$D$33,VIX!D43,IF(VIX!$F$15=VIX!$E$33,VIX!E43,1)))) -> 3 | I120: =IF(Currency!$F$15=Currency!$B$33,Currency!B43,IF(Currency!$F$15=Currency!$C$33,Currency!C43,IF(Currency!$F$15=Currency!$D$33,Currency!D43,IF(Currency!$F$15=Currency!$E$33,Currency!E43,1)))) -> 3 | J120: =IF(Unemployment!$F$15=Unemployment!$B$33,Unemployment!B43,IF(Unemployment!$F$15=Unemployment!$C$33,Unemployment!C43,IF(Unemployment!$F$15=Unemployment!$D$33,Unemployment!D43,IF(Unemployment!$F$15=Unemployment!$E$33,Unemployment!E43,1)))) -> 3 | K120: =AVERAGE(C120*0.2222 + D120*0.3056 + E120*0.1667 + F120*0.1389 + I120*0.0556 + J120*0.1111) -> 3.3614 | L120: =IF(PMI!$F$12=PMI!$B$43,PMI!$B53,IF(PMI!$F$12=PMI!$C$43,PMI!$C53,IF(PMI!$F$12=PMI!$D$44,PMI!$D53,IF(PMI!$F$12=PMI!$E$43,PMI!$E53,1)))) -> 4 | M120: =BNP!J133 -> 4 | N120: =IF('10 yr rate'!$E$11='10 yr rate'!$B$35,'10 yr rate'!$B45,IF('10 yr rate'!$E$11='10 yr rate'!$C$35,'10 yr rate'!$C45,IF('10 yr rate'!$E$11='10 yr rate'!$D$35,'10 yr rate'!$D45,IF('10 yr rate'!$E$11='10 yr rate'!$E$35,'10 yr rate'!$E45,1)))) -> 3 | O120: =IF('CPI(Inflation)'!$E$30='CPI(Inflation)'!$B$33,'CPI(Inflation)'!$B43,IF('CPI(Inflation)'!$E$30='CPI(Inflation)'!$C$33,'CPI(Inflation)'!$C43,IF('CPI(Inflation)'!$E$30='CPI(Inflation)'!$D$33,'CPI(Inflation)'!$D43,IF('CPI(Inflation)'!$E$30='CPI(Inflation)'!$E$33,'CPI(Inflation)'!$E43,1)))) -> 4 | P120: ='Baltic Dry Index'!B43 -> 3 | Q120: =IF(VIX!$F$16=VIX!$B$33,VIX!B43,IF(VIX!$F$16=VIX!$C$33,VIX!C43,IF(VIX!$F$16=VIX!$D$33,VIX!D43,IF(VIX!$F$16=VIX!$E$33,VIX!E43,1)))) -> 2 | R120: =IF(Currency!$F$16=Currency!$B$33,Currency!B43,IF(Currency!$F$16=Currency!$C$33,Currency!C43,IF(Currency!$F$16=Currency!$D$33,Currency!D43,IF(Currency!$F$16=Currency!$E$33,Currency!E43,1)))) -> 4 | S120: =IF(Unemployment!$F$16=Unemployment!$B$33,Unemployment!B43,IF(Unemployment!$F$16=Unemployment!$C$33,Unemployment!C43,IF(Unemployment!$F$16=Unemployment!$D$33,Unemployment!D43,IF(Unemployment!$F$16=Unemployment!$E$33,Unemployment!E43,1)))) -> 3 | T120: =AVERAGE(L120*0.2222 + M120*0.3056 + N120*0.1667 + O120*0.1389 + R120*0.0556 + S120*0.1111) -> 3.7226
B121: Utilities | C121: =IF(PMI!$F$11=PMI!$B$43,PMI!$B54,IF(PMI!$F$11=PMI!$C$43,PMI!$C54,IF(PMI!$F$11=PMI!$D$43,PMI!$D54,IF(PMI!$F$11=PMI!$E$43,PMI!$E54,1)))) -> 2 | D121: =BNP!I138 -> 4 | E121: =IF('10 yr rate'!$E$10='10 yr rate'!$B$35,'10 yr rate'!$B46,IF('10 yr rate'!$E$10='10 yr rate'!$C$35,'10 yr rate'!$C46,IF('10 yr rate'!$E$10='10 yr rate'!$D$35,'10 yr rate'!$D46,IF('10 yr rate'!$E$10='10 yr rate'!$E$35,'10 yr rate'!$E46,1)))) -> 4 | F121: =IF('CPI(Inflation)'!$E$29='CPI(Inflation)'!$B$33,'CPI(Inflation)'!$B44,IF('CPI(Inflation)'!$E$29='CPI(Inflation)'!$C$33,'CPI(Inflation)'!$C44,IF('CPI(Inflation)'!$E$29='CPI(Inflation)'!$D$33,'CPI(Inflation)'!$D44,IF('CPI(Inflation)'!$E$29='CPI(Inflation)'!$E$33,'CPI(Inflation)'!$E44,1)))) -> 2 | G121: ='Baltic Dry Index'!B44 -> 2 | H121: =IF(VIX!$F$15=VIX!$B$33,VIX!B44,IF(VIX!$F$15=VIX!$C$33,VIX!C44,IF(VIX!$F$15=VIX!$D$33,VIX!D44,IF(VIX!$F$15=VIX!$E$33,VIX!E44,1)))) -> 2 | I121: =IF(Currency!$F$15=Currency!$B$33,Currency!B44,IF(Currency!$F$15=Currency!$C$33,Currency!C44,IF(Currency!$F$15=Currency!$D$33,Currency!D44,IF(Currency!$F$15=Currency!$E$33,Currency!E44,1)))) -> 4 | J121: =IF(Unemployment!$F$15=Unemployment!$B$33,Unemployment!B44,IF(Unemployment!$F$15=Unemployment!$C$33,Unemployment!C44,IF(Unemployment!$F$15=Unemployment!$D$33,Unemployment!D44,IF(Unemployment!$F$15=Unemployment!$E$33,Unemployment!E44,1)))) -> 2 | K121: =AVERAGE(C121*0.2222 + D121*0.3056 + E121*0.1667 + F121*0.1389 + I121*0.0556 + J121*0.1111) -> 3.056 | L121: =IF(PMI!$F$12=PMI!$B$43,PMI!$B54,IF(PMI!$F$12=PMI!$C$43,PMI!$C54,IF(PMI!$F$12=PMI!$D$44,PMI!$D54,IF(PMI!$F$12=PMI!$E$43,PMI!$E54,1)))) -> 2 | M121: =BNP!J138 -> 2 | N121: =IF('10 yr rate'!$E$11='10 yr rate'!$B$35,'10 yr rate'!$B46,IF('10 yr rate'!$E$11='10 yr rate'!$C$35,'10 yr rate'!$C46,IF('10 yr rate'!$E$11='10 yr rate'!$D$35,'10 yr rate'!$D46,IF('10 yr rate'!$E$11='10 yr rate'!$E$35,'10 yr rate'!$E46,1)))) -> 4 | O121: =IF('CPI(Inflation)'!$E$30='CPI(Inflation)'!$B$33,'CPI(Inflation)'!$B44,IF('CPI(Inflation)'!$E$30='CPI(Inflation)'!$C$33,'CPI(Inflation)'!$C44,IF('CPI(Inflation)'!$E$30='CPI(Inflation)'!$D$33,'CPI(Inflation)'!$D44,IF('CPI(Inflation)'!$E$30='CPI(Inflation)'!$E$33,'CPI(Inflation)'!$E44,1)))) -> 2 | P121: ='Baltic Dry Index'!B44 -> 2 | Q121: =IF(VIX!$F$16=VIX!$B$33,VIX!B44,IF(VIX!$F$16=VIX!$C$33,VIX!C44,IF(VIX!$F$16=VIX!$D$33,VIX!D44,IF(VIX!$F$16=VIX!$E$33,VIX!E44,1)))) -> 5 | R121: =IF(Currency!$F$16=Currency!$B$33,Currency!B44,IF(Currency!$F$16=Currency!$C$33,Currency!C44,IF(Currency!$F$16=Currency!$D$33,Currency!D44,IF(Currency!$F$16=Currency!$E$33,Currency!E44,1)))) -> 2 | S121: =IF(Unemployment!$F$16=Unemployment!$B$33,Unemployment!B44,IF(Unemployment!$F$16=Unemployment!$C$33,Unemployment!C44,IF(Unemployment!$F$16=Unemployment!$D$33,Unemployment!D44,IF(Unemployment!$F$16=Unemployment!$E$33,Unemployment!E44,1)))) -> 2 | T121: =AVERAGE(L121*0.2222 + M121*0.3056 + N121*0.1667 + O121*0.1389 + R121*0.0556 + S121*0.1111) -> 2.3336

Sheet Makro analyse (historisk)
C29: Q1 2024 | G29: Q1 2024 | L29: Q2 2024 | Q29: Q3 2024 | V29: Q4 2024 | AA29: Q1 2025 | AF29: Q2 2025 | AO29: Q3 2025 | AX29: Q4 2025
B30: Danmark | C30: PMI | D30: BNP | E30: 10 YR | F30: CPI | G30: Makro score | H30: PMI | I30: BNP | J30: 10 YR | K30: CPI | L30: Makro score | M30: PMI | N30: BNP | O30: 10 YR | P30: CPI | Q30: Makro score | R30: PMI | S30: BNP | T30: 10 YR | U30: CPI | V30: Makro score | W30: PMI | X30: BNP | Y30: 10 YR | Z30: CPI | AA30: Makro score | AB30: PMI | AC30: BNP | AD30: 10 YR | AE30: CPI | AF30: Makro score | AG30: PMI | AH30: BNP | AI30: 10 YR | AJ30: CPI | AK30: Baltic Dry Index | AL30: VIX | AM30: Currency | AN30: Unemployment | AO30: Makro score | AP30: PMI | AQ30: BNP | AR30: 10 YR | AS30: CPI | AT30: Baltic Dry Index | AU30: VIX | AV30: Currency | AW30: Unemployment | AX30: Makro score
B31: Financials | C31: =IF(PMI!$F$25=PMI!$B$43,PMI!B44,IF(PMI!$F$25=PMI!$C$43,PMI!C44,IF(PMI!$F$25=PMI!$D$43,PMI!D44,IF(PMI!$F$25=PMI!$E$43,PMI!E44,1)))) -> 4 | D31: =BNP!C86 -> 3 | E31: =IF('10 yr rate'!$E$24='10 yr rate'!$B$35,'10 yr rate'!$B36,IF('10 yr rate'!$E$24='10 yr rate'!$C$35,'10 yr rate'!$C36,IF('10 yr rate'!$E$24='10 yr rate'!$D$35,'10 yr rate'!$D36,IF('10 yr rate'!$E$24='10 yr rate'!$E$35,'10 yr rate'!$E36,1)))) -> 4 | F31: =IF('CPI(Inflation)'!$E$3='CPI(Inflation)'!$B$33,'CPI(Inflation)'!$B34,IF('CPI(Inflation)'!$E$3='CPI(Inflation)'!$C$33,'CPI(Inflation)'!$C34,IF('CPI(Inflation)'!$E$3='CPI(Inflation)'!$D$33,'CPI(Inflation)'!$D34,IF('CPI(Inflation)'!$E$3='CPI(Inflation)'!$E$33,'CPI(Inflation)'!$E34,1)))) -> 4 | G31: =AVERAGE(C31*0.3 + D31*0.2 + E31*0.2 + F31*0.3) -> 3.8 | H31: =IF(PMI!$F$26=PMI!$B$43,PMI!$B44,IF(PMI!$F$26=PMI!$C$43,PMI!$C44,IF(PMI!$F$26=PMI!$D$43,PMI!$D44,IF(PMI!$F$26=PMI!$E$43,PMI!$E44,1)))) -> 4 | I31: =BNP!D86 -> 3 | J31: =IF('10 yr rate'!$E$25='10 yr rate'!$B$35,'10 yr rate'!$B36,IF('10 yr rate'!$E$25='10 yr rate'!$C$35,'10 yr rate'!$C36,IF('10 yr rate'!$E$25='10 yr rate'!$D$35,'10 yr rate'!$D36,IF('10 yr rate'!$E$25='10 yr rate'!$E$35,'10 yr rate'!$E36,1)))) -> 4 | K31: =IF('CPI(Inflation)'!$E$4='CPI(Inflation)'!$B$33,'CPI(Inflation)'!$B34,IF('CPI(Inflation)'!$E$4='CPI(Inflation)'!$C$33,'CPI(Inflation)'!$C34,IF('CPI(Inflation)'!$E$4='CPI(Inflation)'!$D$33,'CPI(Inflation)'!$D34,IF('CPI(Inflation)'!$E$4='CPI(Inflation)'!$E$33,'CPI(Inflation)'!$E34,1)))) -> 4 | L31: =AVERAGE(H31*0.3 + I31*0.2 + J31*0.2 + K31*0.3) -> 3.8 | M31: =IF(PMI!$F$27=PMI!$B$43,PMI!$B44,IF(PMI!$F$27=PMI!$C$43,PMI!$C44,IF(PMI!$F$27=PMI!$D$43,PMI!$D44,IF(PMI!$F$27=PMI!$E$43,PMI!$E44,1)))) -> 4 | N31: =BNP!E86 -> 3 | O31: =IF('10 yr rate'!$E$26='10 yr rate'!$B$35,'10 yr rate'!$B36,IF('10 yr rate'!$E$26='10 yr rate'!$C$35,'10 yr rate'!$C36,IF('10 yr rate'!$E$26='10 yr rate'!$D$35,'10 yr rate'!$D36,IF('10 yr rate'!$E$26='10 yr rate'!$E$35,'10 yr rate'!$E36,1)))) -> 4 | P31: =IF('CPI(Inflation)'!$E$5='CPI(Inflation)'!$B$33,'CPI(Inflation)'!$B34,IF('CPI(Inflation)'!$E$5='CPI(Inflation)'!$C$33,'CPI(Inflation)'!$C34,IF('CPI(Inflation)'!$E$5='CPI(Inflation)'!$D$33,'CPI(Inflation)'!$D34,IF('CPI(Inflation)'!$E$5='CPI(Inflation)'!$E$33,'CPI(Inflation)'!$E34,1)))) -> 1 | Q31: =AVERAGE(M31*0.3 + N31*0.2 + O31*0.2 + P31*0.3) -> 2.9 | R31: =IF(PMI!$F$28=PMI!$B$43,PMI!$B44,IF(PMI!$F$28=PMI!$C$43,PMI!$C44,IF(PMI!$F$28=PMI!$D$43,PMI!$D44,IF(PMI!$F$28=PMI!$E$43,PMI!$E44,1)))) -> 4 | S31: =BNP!F86 -> 3 | T31: =IF('10 yr rate'!$E$27='10 yr rate'!$B$35,'10 yr rate'!$B36,IF('10 yr rate'!$E$27='10 yr rate'!$C$35,'10 yr rate'!$C36,IF('10 yr rate'!$E$27='10 yr rate'!$D$35,'10 yr rate'!$D36,IF('10 yr rate'!$E$27='10 yr rate'!$E$35,'10 yr rate'!$E36,1)))) -> 4 | U31: =IF('CPI(Inflation)'!$E$6='CPI(Inflation)'!$B$33,'CPI(Inflation)'!$B34,IF('CPI(Inflation)'!$E$6='CPI(Inflation)'!$C$33,'CPI(Inflation)'!$C34,IF('CPI(Inflation)'!$E$6='CPI(Inflation)'!$D$33,'CPI(Inflation)'!$D34,IF('CPI(Inflation)'!$E$6='CPI(Inflation)'!$E$33,'CPI(Inflation)'!$E34,1)))) -> 4 | V31: =AVERAGE(R31*0.3 + S31*0.2 + T31*0.2 + U31*0.3) -> 3.8 | W31: =IF(PMI!$F$29=PMI!$B$43,PMI!$B44,IF(PMI!$F$29=PMI!$C$43,PMI!$C44,IF(PMI!$F$29=PMI!$D$43,PMI!$D44,IF(PMI!$F$29=PMI!$E$43,PMI!$E44,1)))) -> 4 | X31: =BNP!G86 -> 2 | Y31: =IF('10 yr rate'!$E$28='10 yr rate'!$B$35,'10 yr rate'!$B36,IF('10 yr rate'!$E$28='10 yr rate'!$C$35,'10 yr rate'!$C36,IF('10 yr rate'!$E$28='10 yr rate'!$D$35,'10 yr rate'!$D36,IF('10 yr rate'!$E$28='10 yr rate'!$E$35,'10 yr rate'!$E36,1)))) -> 4 | Z31: =IF('CPI(Inflation)'!$E$7='CPI(Inflation)'!$B$33,'CPI(Inflation)'!$B34,IF('CPI(Inflation)'!$E$7='CPI(Inflation)'!$C$33,'CPI(Inflation)'!$C34,IF('CPI(Inflation)'!$E$7='CPI(Inflation)'!$D$33,'CPI(Inflation)'!$D34,IF('CPI(Inflation)'!$E$7='CPI(Inflation)'!$E$33,'CPI(Inflation)'!$E34,1)))) -> 4 | AA31: =AVERAGE(W31*0.3 + X31*0.2 + Y31*0.2 + Z31*0.3) -> 3.6 | AB31: =IF(PMI!$F$30=PMI!$B$43,PMI!$B44,IF(PMI!$F$30=PMI!$C$43,PMI!$C44,IF(PMI!$F$30=PMI!$D$43,PMI!$D44,IF(PMI!$F$30=PMI!$E$43,PMI!$E44,1)))) -> 4 | AC31: =BNP!H86 -> 4 | AD31: =IF('10 yr rate'!$E$29='10 yr rate'!$B$35,'10 yr rate'!$B36,IF('10 yr rate'!$E$29='10 yr rate'!$C$35,'10 yr rate'!$C36,IF('10 yr rate'!$E$29='10 yr rate'!$D$35,'10 yr rate'!$D36,IF('10 yr rate'!$E$29='10 yr rate'!$E$35,'10 yr rate'!$E36,1)))) -> 4 | AE31: =IF('CPI(Inflation)'!$E$8='CPI(Inflation)'!$B$33,'CPI(Inflation)'!$B34,IF('CPI(Inflation)'!$E$8='CPI(Inflation)'!$C$33,'CPI(Inflation)'!$C34,IF('CPI(Inflation)'!$E$8='CPI(Inflation)'!$D$33,'CPI(Inflation)'!$D34,IF('CPI(Inflation)'!$E$8='CPI(Inflation)'!$E$33,'CPI(Inflation)'!$E34,1)))) -> 4 | AF31: =AVERAGE(AB31*0.3 + AC31*0.2 + AD31*0.2 + AE31*0.3) -> 4 | AG31: =IF(PMI!$F$31=PMI!$B$43,PMI!$B44,IF(PMI!$F$31=PMI!$C$43,PMI!$C44,IF(PMI!$F$31=PMI!$D$43,PMI!$D44,IF(PMI!$F$31=PMI!$E$43,PMI!$E44,1)))) -> 4 | AH31: =BNP!I86 -> 3 | AI31: =IF('10 yr rate'!$E$30='10 yr rate'!$B$35,'10 yr rate'!$B36,IF('10 yr rate'!$E$30='10 yr rate'!$C$35,'10 yr rate'!$C36,IF('10 yr rate'!$E$30='10 yr rate'!$D$35,'10 yr rate'!$D36,IF('10 yr rate'!$E$30='10 yr rate'!$E$35,'10 yr rate'!$E36,1)))) -> 4 | AJ31: =IF('CPI(Inflation)'!$E$9='CPI(Inflation)'!$B$33,'CPI(Inflation)'!$B34,IF('CPI(Inflation)'!$E$9='CPI(Inflation)'!$C$33,'CPI(Inflation)'!$C34,IF('CPI(Inflation)'!$E$9='CPI(Inflation)'!$D$33,'CPI(Inflation)'!$D34,IF('CPI(Inflation)'!$E$9='CPI(Inflation)'!$E$33,'CPI(Inflation)'!$E34,1)))) -> 4 | AK31: ='Baltic Dry Index'!B34 -> 4 | AL31: =IF(VIX!$F$25=VIX!$B$33,VIX!B34,IF(VIX!$F$25=VIX!$C$33,VIX!C34,IF(VIX!$F$25=VIX!$D$33,VIX!D34,IF(VIX!$F$25=VIX!$E$33,VIX!E34,1)))) -> 4 | AM31: =IF(Currency!$F$25=Currency!$B$33,Currency!B34,IF(Currency!$F$25=Currency!$C$33,Currency!C34,IF(Currency!$F$25=Currency!$D$33,Currency!D34,IF(Currency!$F$25=Currency!$E$33,Currency!E34,1)))) -> 2 | AN31: =IF(Unemployment!$F$25=Unemployment!$B$33,Unemployment!B34,IF(Unemployment!$F$25=Unemployment!$C$33,Unemployment!C34,IF(Unemployment!$F$25=Unemployment!$D$33,Unemployment!D34,IF(Unemployment!$F$25=Unemployment!$E$33,Unemployment!E34,1)))) -> 4 | AO31: =AVERAGE(AG31*0.2222 + AH31*0.1944 + AI31*0.1667 + AJ31*0.1389 + AK31*0.0556 + AL31*0.0556 + AM31*0.0556 + AN31*0.1111) -> 3.6948 | AP31: =IF(PMI!$F$32=PMI!$B$43,PMI!$B44,IF(PMI!$F$32=PMI!$C$43,PMI!$C44,IF(PMI!$F$32=PMI!$D$43,PMI!$D44,IF(PMI!$F$32=PMI!$E$43,PMI!$E44,1)))) -> 4 | AQ31: =BNP!J86 -> 3 | AR31: =IF('10 yr rate'!$E$31='10 yr rate'!$B$35,'10 yr rate'!$B36,IF('10 yr rate'!$E$31='10 yr rate'!$C$35,'10 yr rate'!$C36,IF('10 yr rate'!$E$31='10 yr rate'!$D$35,'10 yr rate'!$D36,IF('10 yr rate'!$E$31='10 yr rate'!$E$35,'10 yr rate'!$E36,1)))) -> 4 | AS31: =IF('CPI(Inflation)'!$E$10='CPI(Inflation)'!$B$33,'CPI(Inflation)'!$B34,IF('CPI(Inflation)'!$E$10='CPI(Inflation)'!$C$33,'CPI(Inflation)'!$C34,IF('CPI(Inflation)'!$E$10='CPI(Inflation)'!$D$33,'CPI(Inflation)'!$D34,IF('CPI(Inflation)'!$E$10='CPI(Inflation)'!$E$33,'CPI(Inflation)'!$E34,1)))) -> 4 | AT31: ='Baltic Dry Index'!B34 -> 4 | AU31: =IF(VIX!$F$26=VIX!$B$33,VIX!B34,IF(VIX!$F$26=VIX!$C$33,VIX!C34,IF(VIX!$F$26=VIX!$D$33,VIX!D34,IF(VIX!$F$26=VIX!$E$33,VIX!E34,1)))) -> 1 | AV31: =IF(Currency!$F$26=Currency!$B$33,Currency!B34,IF(Currency!$F$26=Currency!$C$33,Currency!C34,IF(Currency!$F$26=Currency!$D$33,Currency!D34,IF(Currency!$F$26=Currency!$E$33,Currency!E34,1)))) -> 4 | AW31: =IF(Unemployment!$F$26=Unemployment!$B$33,Unemployment!B34,IF(Unemployment!$F$26=Unemployment!$C$33,Unemployment!C34,IF(Unemployment!$F$26=Unemployment!$D$33,Unemployment!D34,IF(Unemployment!$F$26=Unemployment!$E$33,Unemployment!E34,1)))) -> 4 | AX31: =AVERAGE(AP31*0.2222 + AQ31*0.1944 + AR31*0.1667 + AS31*0.1389 + AT31*0.0556 + AU31*0.0556 + AV31*0.0556 + AW31*0.1111) -> 3.6392
B32: Real Estate | C32: =IF(PMI!$F$25=PMI!$B$43,PMI!B45,IF(PMI!$F$25=PMI!$C$43,PMI!C45,IF(PMI!$F$25=PMI!$D$43,PMI!D45,IF(PMI!$F$25=PMI!$E$43,PMI!E45,1)))) -> 5 | D32: =BNP!C91 -> 3 | E32: =IF('10 yr rate'!$E$24='10 yr rate'!$B$35,'10 yr rate'!B37,IF('10 yr rate'!$E$24='10 yr rate'!$C$35,'10 yr rate'!C37,IF('10 yr rate'!$E$24='10 yr rate'!$D$35,'10 yr rate'!D37,IF('10 yr rate'!$E$24='10 yr rate'!$E$35,'10 yr rate'!E37,1)))) -> 5 | F32: =IF('CPI(Inflation)'!$E$3='CPI(Inflation)'!$B$33,'CPI(Inflation)'!B35,IF('CPI(Inflation)'!$E$3='CPI(Inflation)'!$C$33,'CPI(Inflation)'!C35,IF('CPI(Inflation)'!$E$3='CPI(Inflation)'!$D$33,'CPI(Inflation)'!D35,IF('CPI(Inflation)'!$E$3='CPI(Inflation)'!$E$33,'CPI(Inflation)'!E35,1)))) -> 5 | G32: =AVERAGE(C32*0.3 + D32*0.2 + E32*0.2 + F32*0.3) -> 4.6 | H32: =IF(PMI!$F$26=PMI!$B$43,PMI!$B45,IF(PMI!$F$26=PMI!$C$43,PMI!$C45,IF(PMI!$F$26=PMI!$D$43,PMI!$D45,IF(PMI!$F$26=PMI!$E$43,PMI!$E45,1)))) -> 5 | I32: =BNP!D91 -> 2 | J32: =IF('10 yr rate'!$E$25='10 yr rate'!$B$35,'10 yr rate'!$B37,IF('10 yr rate'!$E$25='10 yr rate'!$C$35,'10 yr rate'!$C37,IF('10 yr rate'!$E$25='10 yr rate'!$D$35,'10 yr rate'!$D37,IF('10 yr rate'!$E$25='10 yr rate'!$E$35,'10 yr rate'!$E37,1)))) -> 2 | K32: =IF('CPI(Inflation)'!$E$4='CPI(Inflation)'!$B$33,'CPI(Inflation)'!$B35,IF('CPI(Inflation)'!$E$4='CPI(Inflation)'!$C$33,'CPI(Inflation)'!$C35,IF('CPI(Inflation)'!$E$4='CPI(Inflation)'!$D$33,'CPI(Inflation)'!$D35,IF('CPI(Inflation)'!$E$4='CPI(Inflation)'!$E$33,'CPI(Inflation)'!$E35,1)))) -> 5 | L32: =AVERAGE(H32*0.3 + I32*0.2 + J32*0.2 + K32*0.3) -> 3.8 | M32: =IF(PMI!$F$27=PMI!$B$43,PMI!$B45,IF(PMI!$F$27=PMI!$C$43,PMI!$C45,IF(PMI!$F$27=PMI!$D$43,PMI!$D45,IF(PMI!$F$27=PMI!$E$43,PMI!$E45,1)))) -> 5 | N32: =BNP!E91 -> 4 | O32: =IF('10 yr rate'!$E$26='10 yr rate'!$B$35,'10 yr rate'!$B37,IF('10 yr rate'!$E$26='10 yr rate'!$C$35,'10 yr rate'!$C37,IF('10 yr rate'!$E$26='10 yr rate'!$D$35,'10 yr rate'!$D37,IF('10 yr rate'!$E$26='10 yr rate'!$E$35,'10 yr rate'!$E37,1)))) -> 5 | P32: =IF('CPI(Inflation)'!$E$5='CPI(Inflation)'!$B$33,'CPI(Inflation)'!$B35,IF('CPI(Inflation)'!$E$5='CPI(Inflation)'!$C$33,'CPI(Inflation)'!$C35,IF('CPI(Inflation)'!$E$5='CPI(Inflation)'!$D$33,'CPI(Inflation)'!$D35,IF('CPI(Inflation)'!$E$5='CPI(Inflation)'!$E$33,'CPI(Inflation)'!$E35,1)))) -> 1 | Q32: =AVERAGE(M32*0.3 + N32*0.2 + O32*0.2 + P32*0.3) -> 3.6 | R32: =IF(PMI!$F$28=PMI!$B$43,PMI!$B45,IF(PMI!$F$28=PMI!$C$43,PMI!$C45,IF(PMI!$F$28=PMI!$D$43,PMI!$D45,IF(PMI!$F$28=PMI!$E$43,PMI!$E45,1)))) -> 5 | S32: =BNP!F91 -> 2 | T32: =IF('10 yr rate'!$E$27='10 yr rate'!$B$35,'10 yr rate'!$B37,IF('10 yr rate'!$E$27='10 yr rate'!$C$35,'10 yr rate'!$C37,IF('10 yr rate'!$E$27='10 yr rate'!$D$35,'10 yr rate'!$D37,IF('10 yr rate'!$E$27='10 yr rate'!$E$35,'10 yr rate'!$E37,1)))) -> 5 | U32: =IF('CPI(Inflation)'!$E$6='CPI(Inflation)'!$B$33,'CPI(Inflation)'!$B35,IF('CPI(Inflation)'!$E$6='CPI(Inflation)'!$C$33,'CPI(Inflation)'!$C35,IF('CPI(Inflation)'!$E$6='CPI(Inflation)'!$D$33,'CPI(Inflation)'!$D35,IF('CPI(Inflation)'!$E$6='CPI(Inflation)'!$E$33,'CPI(Inflation)'!$E35,1)))) -> 5 | V32: =AVERAGE(R32*0.3 + S32*0.2 + T32*0.2 + U32*0.3) -> 4.4 | W32: =IF(PMI!$F$29=PMI!$B$43,PMI!$B45,IF(PMI!$F$29=PMI!$C$43,PMI!$C45,IF(PMI!$F$29=PMI!$D$43,PMI!$D45,IF(PMI!$F$29=PMI!$E$43,PMI!$E45,1)))) -> 2 | X32: =BNP!G91 -> 1 | Y32: =IF('10 yr rate'!$E$28='10 yr rate'!$B$35,'10 yr rate'!$B37,IF('10 yr rate'!$E$28='10 yr rate'!$C$35,'10 yr rate'!$C37,IF('10 yr rate'!$E$28='10 yr rate'!$D$35,'10 yr rate'!$D37,IF('10 yr rate'!$E$28='10 yr rate'!$E$35,'10 yr rate'!$E37,1)))) -> 5 | Z32: =IF('CPI(Inflation)'!$E$7='CPI(Inflation)'!$B$33,'CPI(Inflation)'!$B35,IF('CPI(Inflation)'!$E$7='CPI(Inflation)'!$C$33,'CPI(Inflation)'!$C35,IF('CPI(Inflation)'!$E$7='CPI(Inflation)'!$D$33,'CPI(Inflation)'!$D35,IF('CPI(Inflation)'!$E$7='CPI(Inflation)'!$E$33,'CPI(Inflation)'!$E35,1)))) -> 5 | AA32: =AVERAGE(W32*0.3 + X32*0.2 + Y32*0.2 + Z32*0.3) -> 3.3 | AB32: =IF(PMI!$F$30=PMI!$B$43,PMI!$B45,IF(PMI!$F$30=PMI!$C$43,PMI!$C45,IF(PMI!$F$30=PMI!$D$43,PMI!$D45,IF(PMI!$F$30=PMI!$E$43,PMI!$E45,1)))) -> 5 | AC32: =BNP!H91 -> 5 | AD32: =IF('10 yr rate'!$E$29='10 yr rate'!$B$35,'10 yr rate'!$B37,IF('10 yr rate'!$E$29='10 yr rate'!$C$35,'10 yr rate'!$C37,IF('10 yr rate'!$E$29='10 yr rate'!$D$35,'10 yr rate'!$D37,IF('10 yr rate'!$E$29='10 yr rate'!$E$35,'10 yr rate'!$E37,1)))) -> 5 | AE32: =IF('CPI(Inflation)'!$E$8='CPI(Inflation)'!$B$33,'CPI(Inflation)'!$B35,IF('CPI(Inflation)'!$E$8='CPI(Inflation)'!$C$33,'CPI(Inflation)'!$C35,IF('CPI(Inflation)'!$E$8='CPI(Inflation)'!$D$33,'CPI(Inflation)'!$D35,IF('CPI(Inflation)'!$E$8='CPI(Inflation)'!$E$33,'CPI(Inflation)'!$E35,1)))) -> 5 | AF32: =AVERAGE(AB32*0.3 + AC32*0.2 + AD32*0.2 + AE32*0.3) -> 5 | AG32: =IF(PMI!$F$31=PMI!$B$43,PMI!$B45,IF(PMI!$F$31=PMI!$C$43,PMI!$C45,IF(PMI!$F$31=PMI!$D$43,PMI!$D45,IF(PMI!$F$31=PMI!$E$43,PMI!$E45,1)))) -> 2 | AH32: =BNP!I91 -> 2 | AI32: =IF('10 yr rate'!$E$30='10 yr rate'!$B$35,'10 yr rate'!$B37,IF('10 yr rate'!$E$30='10 yr rate'!$C$35,'10 yr rate'!$C37,IF('10 yr rate'!$E$30='10 yr rate'!$D$35,'10 yr rate'!$D37,IF('10 yr rate'!$E$30='10 yr rate'!$E$35,'10 yr rate'!$E37,1)))) -> 2 | AJ32: =IF('CPI(Inflation)'!$E$9='CPI(Inflation)'!$B$33,'CPI(Inflation)'!$B35,IF('CPI(Inflation)'!$E$9='CPI(Inflation)'!$C$33,'CPI(Inflation)'!$C35,IF('CPI(Inflation)'!$E$9='CPI(Inflation)'!$D$33,'CPI(Inflation)'!$D35,IF('CPI(Inflation)'!$E$9='CPI(Inflation)'!$E$33,'CPI(Inflation)'!$E35,1)))) -> 2 | AK32: ='Baltic Dry Index'!B35 -> 5 | AL32: =IF(VIX!$F$25=VIX!$B$33,VIX!B35,IF(VIX!$F$25=VIX!$C$33,VIX!C35,IF(VIX!$F$25=VIX!$D$33,VIX!D35,IF(VIX!$F$25=VIX!$E$33,VIX!E35,1)))) -> 5 | AM32: =IF(Currency!$F$25=Currency!$B$33,Currency!B35,IF(Currency!$F$25=Currency!$C$33,Currency!C35,IF(Currency!$F$25=Currency!$D$33,Currency!D35,IF(Currency!$F$25=Currency!$E$33,Currency!E35,1)))) -> 3 | AN32: =IF(Unemployment!$F$25=Unemployment!$B$33,Unemployment!B35,IF(Unemployment!$F$25=Unemployment!$C$33,Unemployment!C35,IF(Unemployment!$F$25=Unemployment!$D$33,Unemployment!D35,IF(Unemployment!$F$25=Unemployment!$E$33,Unemployment!E35,1)))) -> 5 | AO32: =AVERAGE(AG32*0.2222 + AH32*0.1944 + AI32*0.1667 + AJ32*0.1389 + AK32*0.0556 + AL32*0.0556 + AM32*0.0556 + AN32*0.1111) -> 2.7227 | AP32: =IF(PMI!$F$32=PMI!$B$43,PMI!$B45,IF(PMI!$F$32=PMI!$C$43,PMI!$C45,IF(PMI!$F$32=PMI!$D$43,PMI!$D45,IF(PMI!$F$32=PMI!$E$43,PMI!$E45,1)))) -> 2 | AQ32: =BNP!J91 -> 4 | AR32: =IF('10 yr rate'!$E$31='10 yr rate'!$B$35,'10 yr rate'!$B37,IF('10 yr rate'!$E$31='10 yr rate'!$C$35,'10 yr rate'!$C37,IF('10 yr rate'!$E$31='10 yr rate'!$D$35,'10 yr rate'!$D37,IF('10 yr rate'!$E$31='10 yr rate'!$E$35,'10 yr rate'!$E37,1)))) -> 2 | AS32: =IF('CPI(Inflation)'!$E$10='CPI(Inflation)'!$B$33,'CPI(Inflation)'!$B35,IF('CPI(Inflation)'!$E$10='CPI(Inflation)'!$C$33,'CPI(Inflation)'!$C35,IF('CPI(Inflation)'!$E$10='CPI(Inflation)'!$D$33,'CPI(Inflation)'!$D35,IF('CPI(Inflation)'!$E$10='CPI(Inflation)'!$E$33,'CPI(Inflation)'!$E35,1)))) -> 5 | AT32: ='Baltic Dry Index'!B35 -> 5 | AU32: =IF(VIX!$F$26=VIX!$B$33,VIX!B35,IF(VIX!$F$26=VIX!$C$33,VIX!C35,IF(VIX!$F$26=VIX!$D$33,VIX!D35,IF(VIX!$F$26=VIX!$E$33,VIX!E35,1)))) -> 1 | AV32: =IF(Currency!$F$26=Currency!$B$33,Currency!B35,IF(Currency!$F$26=Currency!$C$33,Currency!C35,IF(Currency!$F$26=Currency!$D$33,Currency!D35,IF(Currency!$F$26=Currency!$E$33,Currency!E35,1)))) -> 2 | AW32: =IF(Unemployment!$F$26=Unemployment!$B$33,Unemployment!B35,IF(Unemployment!$F$26=Unemployment!$C$33,Unemployment!C35,IF(Unemployment!$F$26=Unemployment!$D$33,Unemployment!D35,IF(Unemployment!$F$26=Unemployment!$E$33,Unemployment!E35,1)))) -> 5 | AX32: =AVERAGE(AP32*0.2222 + AQ32*0.1944 + AR32*0.1667 + AS32*0.1389 + AT32*0.0556 + AU32*0.0556 + AV32*0.0556 + AW32*0.1111) -> 3.2502
B33: Consumer Discretionary | C33: =IF(PMI!$F$25=PMI!$B$43,PMI!B46,IF(PMI!$F$25=PMI!$C$43,PMI!C46,IF(PMI!$F$25=PMI!$D$43,PMI!D46,IF(PMI!$F$25=PMI!$E$43,PMI!E46,1)))) -> 5 | D33: =BNP!C96 -> 3 | E33: =IF('10 yr rate'!$E$24='10 yr rate'!$B$35,'10 yr rate'!B38,IF('10 yr rate'!$E$24='10 yr rate'!$C$35,'10 yr rate'!C38,IF('10 yr rate'!$E$24='10 yr rate'!$D$35,'10 yr rate'!D38,IF('10 yr rate'!$E$24='10 yr rate'!$E$35,'10 yr rate'!E38,1)))) -> 5 | F33: =IF('CPI(Inflation)'!$E$3='CPI(Inflation)'!$B$33,'CPI(Inflation)'!B36,IF('CPI(Inflation)'!$E$3='CPI(Inflation)'!$C$33,'CPI(Inflation)'!C36,IF('CPI(Inflation)'!$E$3='CPI(Inflation)'!$D$33,'CPI(Inflation)'!D36,IF('CPI(Inflation)'!$E$3='CPI(Inflation)'!$E$33,'CPI(Inflation)'!E36,1)))) -> 5 | G33: =AVERAGE(C33*0.3 + D33*0.2 + E33*0.2 + F33*0.3) -> 4.6 | H33: =IF(PMI!$F$26=PMI!$B$43,PMI!$B46,IF(PMI!$F$26=PMI!$C$43,PMI!$C46,IF(PMI!$F$26=PMI!$D$43,PMI!$D46,IF(PMI!$F$26=PMI!$E$43,PMI!$E46,1)))) -> 5 | I33: =BNP!D96 -> 3 | J33: =IF('10 yr rate'!$E$25='10 yr rate'!$B$35,'10 yr rate'!$B38,IF('10 yr rate'!$E$25='10 yr rate'!$C$35,'10 yr rate'!$C38,IF('10 yr rate'!$E$25='10 yr rate'!$D$35,'10 yr rate'!$D38,IF('10 yr rate'!$E$25='10 yr rate'!$E$35,'10 yr rate'!$E38,1)))) -> 4 | K33: =IF('CPI(Inflation)'!$E$4='CPI(Inflation)'!$B$33,'CPI(Inflation)'!$B36,IF('CPI(Inflation)'!$E$4='CPI(Inflation)'!$C$33,'CPI(Inflation)'!$C36,IF('CPI(Inflation)'!$E$4='CPI(Inflation)'!$D$33,'CPI(Inflation)'!$D36,IF('CPI(Inflation)'!$E$4='CPI(Inflation)'!$E$33,'CPI(Inflation)'!$E36,1)))) -> 5 | L33: =AVERAGE(H33*0.3 + I33*0.2 + J33*0.2 + K33*0.3) -> 4.4 | M33: =IF(PMI!$F$27=PMI!$B$43,PMI!$B46,IF(PMI!$F$27=PMI!$C$43,PMI!$C46,IF(PMI!$F$27=PMI!$D$43,PMI!$D46,IF(PMI!$F$27=PMI!$E$43,PMI!$E46,1)))) -> 5 | N33: =BNP!E96 -> 1 | O33: =IF('10 yr rate'!$E$26='10 yr rate'!$B$35,'10 yr rate'!$B38,IF('10 yr rate'!$E$26='10 yr rate'!$C$35,'10 yr rate'!$C38,IF('10 yr rate'!$E$26='10 yr rate'!$D$35,'10 yr rate'!$D38,IF('10 yr rate'!$E$26='10 yr rate'!$E$35,'10 yr rate'!$E38,1)))) -> 5 | P33: =IF('CPI(Inflation)'!$E$5='CPI(Inflation)'!$B$33,'CPI(Inflation)'!$B36,IF('CPI(Inflation)'!$E$5='CPI(Inflation)'!$C$33,'CPI(Inflation)'!$C36,IF('CPI(Inflation)'!$E$5='CPI(Inflation)'!$D$33,'CPI(Inflation)'!$D36,IF('CPI(Inflation)'!$E$5='CPI(Inflation)'!$E$33,'CPI(Inflation)'!$E36,1)))) -> 1 | Q33: =AVERAGE(M33*0.3 + N33*0.2 + O33*0.2 + P33*0.3) -> 3 | R33: =IF(PMI!$F$28=PMI!$B$43,PMI!$B46,IF(PMI!$F$28=PMI!$C$43,PMI!$C46,IF(PMI!$F$28=PMI!$D$43,PMI!$D46,IF(PMI!$F$28=PMI!$E$43,PMI!$E46,1)))) -> 5 | S33: =BNP!F96 -> 3 | T33: =IF('10 yr rate'!$E$27='10 yr rate'!$B$35,'10 yr rate'!$B38,IF('10 yr rate'!$E$27='10 yr rate'!$C$35,'10 yr rate'!$C38,IF('10 yr rate'!$E$27='10 yr rate'!$D$35,'10 yr rate'!$D38,IF('10 yr rate'!$E$27='10 yr rate'!$E$35,'10 yr rate'!$E38,1)))) -> 5 | U33: =IF('CPI(Inflation)'!$E$6='CPI(Inflation)'!$B$33,'CPI(Inflation)'!$B36,IF('CPI(Inflation)'!$E$6='CPI(Inflation)'!$C$33,'CPI(Inflation)'!$C36,IF('CPI(Inflation)'!$E$6='CPI(Inflation)'!$D$33,'CPI(Inflation)'!$D36,IF('CPI(Inflation)'!$E$6='CPI(Inflation)'!$E$33,'CPI(Inflation)'!$E36,1)))) -> 5 | V33: =AVERAGE(R33*0.3 + S33*0.2 + T33*0.2 + U33*0.3) -> 4.6 | W33: =IF(PMI!$F$29=PMI!$B$43,PMI!$B46,IF(PMI!$F$29=PMI!$C$43,PMI!$C46,IF(PMI!$F$29=PMI!$D$43,PMI!$D46,IF(PMI!$F$29=PMI!$E$43,PMI!$E46,1)))) -> 4 | X33: =BNP!G96 -> 3 | Y33: =IF('10 yr rate'!$E$28='10 yr rate'!$B$35,'10 yr rate'!$B38,IF('10 yr rate'!$E$28='10 yr rate'!$C$35,'10 yr rate'!$C38,IF('10 yr rate'!$E$28='10 yr rate'!$D$35,'10 yr rate'!$D38,IF('10 yr rate'!$E$28='10 yr rate'!$E$35,'10 yr rate'!$E38,1)))) -> 5 | Z33: =IF('CPI(Inflation)'!$E$7='CPI(Inflation)'!$B$33,'CPI(Inflation)'!$B36,IF('CPI(Inflation)'!$E$7='CPI(Inflation)'!$C$33,'CPI(Inflation)'!$C36,IF('CPI(Inflation)'!$E$7='CPI(Inflation)'!$D$33,'CPI(Inflation)'!$D36,IF('CPI(Inflation)'!$E$7='CPI(Inflation)'!$E$33,'CPI(Inflation)'!$E36,1)))) -> 5 | AA33: =AVERAGE(W33*0.3 + X33*0.2 + Y33*0.2 + Z33*0.3) -> 4.3 | AB33: =IF(PMI!$F$30=PMI!$B$43,PMI!$B46,IF(PMI!$F$30=PMI!$C$43,PMI!$C46,IF(PMI!$F$30=PMI!$D$43,PMI!$D46,IF(PMI!$F$30=PMI!$E$43,PMI!$E46,1)))) -> 5 | AC33: =BNP!H96 -> 5 | AD33: =IF('10 yr rate'!$E$29='10 yr rate'!$B$35,'10 yr rate'!$B38,IF('10 yr rate'!$E$29='10 yr rate'!$C$35,'10 yr rate'!$C38,IF('10 yr rate'!$E$29='10 yr rate'!$D$35,'10 yr rate'!$D38,IF('10 yr rate'!$E$29='10 yr rate'!$E$35,'10 yr rate'!$E38,1)))) -> 5 | AE33: =IF('CPI(Inflation)'!$E$8='CPI(Inflation)'!$B$33,'CPI(Inflation)'!$B36,IF('CPI(Inflation)'!$E$8='CPI(Inflation)'!$C$33,'CPI(Inflation)'!$C36,IF('CPI(Inflation)'!$E$8='CPI(Inflation)'!$D$33,'CPI(Inflation)'!$D36,IF('CPI(Inflation)'!$E$8='CPI(Inflation)'!$E$33,'CPI(Inflation)'!$E36,1)))) -> 5 | AF33: =AVERAGE(AB33*0.3 + AC33*0.2 + AD33*0.2 + AE33*0.3) -> 5 | AG33: =IF(PMI!$F$31=PMI!$B$43,PMI!$B46,IF(PMI!$F$31=PMI!$C$43,PMI!$C46,IF(PMI!$F$31=PMI!$D$43,PMI!$D46,IF(PMI!$F$31=PMI!$E$43,PMI!$E46,1)))) -> 4 | AH33: =BNP!I96 -> 3 | AI33: =IF('10 yr rate'!$E$30='10 yr rate'!$B$35,'10 yr rate'!$B38,IF('10 yr rate'!$E$30='10 yr rate'!$C$35,'10 yr rate'!$C38,IF('10 yr rate'!$E$30='10 yr rate'!$D$35,'10 yr rate'!$D38,IF('10 yr rate'!$E$30='10 yr rate'!$E$35,'10 yr rate'!$E38,1)))) -> 4 | AJ33: =IF('CPI(Inflation)'!$E$9='CPI(Inflation)'!$B$33,'CPI(Inflation)'!$B36,IF('CPI(Inflation)'!$E$9='CPI(Inflation)'!$C$33,'CPI(Inflation)'!$C36,IF('CPI(Inflation)'!$E$9='CPI(Inflation)'!$D$33,'CPI(Inflation)'!$D36,IF('CPI(Inflation)'!$E$9='CPI(Inflation)'!$E$33,'CPI(Inflation)'!$E36,1)))) -> 4 | AK33: ='Baltic Dry Index'!B36 -> 5 | AL33: =IF(VIX!$F$25=VIX!$B$33,VIX!B36,IF(VIX!$F$25=VIX!$C$33,VIX!C36,IF(VIX!$F$25=VIX!$D$33,VIX!D36,IF(VIX!$F$25=VIX!$E$33,VIX!E36,1)))) -> 5 | AM33: =IF(Currency!$F$25=Currency!$B$33,Currency!B36,IF(Currency!$F$25=Currency!$C$33,Currency!C36,IF(Currency!$F$25=Currency!$D$33,Currency!D36,IF(Currency!$F$25=Currency!$E$33,Currency!E36,1)))) -> 2 | AN33: =IF(Unemployment!$F$25=Unemployment!$B$33,Unemployment!B36,IF(Unemployment!$F$25=Unemployment!$C$33,Unemployment!C36,IF(Unemployment!$F$25=Unemployment!$D$33,Unemployment!D36,IF(Unemployment!$F$25=Unemployment!$E$33,Unemployment!E36,1)))) -> 5 | AO33: =AVERAGE(AG33*0.2222 + AH33*0.1944 + AI33*0.1667 + AJ33*0.1389 + AK33*0.0556 + AL33*0.0556 + AM33*0.0556 + AN33*0.1111) -> 3.9171 | AP33: =IF(PMI!$F$32=PMI!$B$43,PMI!$B46,IF(PMI!$F$32=PMI!$C$43,PMI!$C46,IF(PMI!$F$32=PMI!$D$43,PMI!$D46,IF(PMI!$F$32=PMI!$E$43,PMI!$E46,1)))) -> 4 | AQ33: =BNP!J96 -> 1 | AR33: =IF('10 yr rate'!$E$31='10 yr rate'!$B$35,'10 yr rate'!$B38,IF('10 yr rate'!$E$31='10 yr rate'!$C$35,'10 yr rate'!$C38,IF('10 yr rate'!$E$31='10 yr rate'!$D$35,'10 yr rate'!$D38,IF('10 yr rate'!$E$31='10 yr rate'!$E$35,'10 yr rate'!$E38,1)))) -> 4 | AS33: =IF('CPI(Inflation)'!$E$10='CPI(Inflation)'!$B$33,'CPI(Inflation)'!$B36,IF('CPI(Inflation)'!$E$10='CPI(Inflation)'!$C$33,'CPI(Inflation)'!$C36,IF('CPI(Inflation)'!$E$10='CPI(Inflation)'!$D$33,'CPI(Inflation)'!$D36,IF('CPI(Inflation)'!$E$10='CPI(Inflation)'!$E$33,'CPI(Inflation)'!$E36,1)))) -> 5 | AT33: ='Baltic Dry Index'!B36 -> 5 | AU33: =IF(VIX!$F$26=VIX!$B$33,VIX!B36,IF(VIX!$F$26=VIX!$C$33,VIX!C36,IF(VIX!$F$26=VIX!$D$33,VIX!D36,IF(VIX!$F$26=VIX!$E$33,VIX!E36,1)))) -> 1 | AV33: =IF(Currency!$F$26=Currency!$B$33,Currency!B36,IF(Currency!$F$26=Currency!$C$33,Currency!C36,IF(Currency!$F$26=Currency!$D$33,Currency!D36,IF(Currency!$F$26=Currency!$E$33,Currency!E36,1)))) -> 4 | AW33: =IF(Unemployment!$F$26=Unemployment!$B$33,Unemployment!B36,IF(Unemployment!$F$26=Unemployment!$C$33,Unemployment!C36,IF(Unemployment!$F$26=Unemployment!$D$33,Unemployment!D36,IF(Unemployment!$F$26=Unemployment!$E$33,Unemployment!E36,1)))) -> 5 | AX33: =AVERAGE(AP33*0.2222 + AQ33*0.1944 + AR33*0.1667 + AS33*0.1389 + AT33*0.0556 + AU33*0.0556 + AV33*0.0556 + AW33*0.1111) -> 3.556
B34: Information Technology | C34: =IF(PMI!$F$25=PMI!$B$43,PMI!B47,IF(PMI!$F$25=PMI!$C$43,PMI!C47,IF(PMI!$F$25=PMI!$D$43,PMI!D47,IF(PMI!$F$25=PMI!$E$43,PMI!E47,1)))) -> 4 | D34: =BNP!C101 -> 3 | E34: =IF('10 yr rate'!$E$24='10 yr rate'!$B$35,'10 yr rate'!B39,IF('10 yr rate'!$E$24='10 yr rate'!$C$35,'10 yr rate'!C39,IF('10 yr rate'!$E$24='10 yr rate'!$D$35,'10 yr rate'!D39,IF('10 yr rate'!$E$24='10 yr rate'!$E$35,'10 yr rate'!E39,1)))) -> 4 | F34: =IF('CPI(Inflation)'!$E$3='CPI(Inflation)'!$B$33,'CPI(Inflation)'!B37,IF('CPI(Inflation)'!$E$3='CPI(Inflation)'!$C$33,'CPI(Inflation)'!C37,IF('CPI(Inflation)'!$E$3='CPI(Inflation)'!$D$33,'CPI(Inflation)'!D37,IF('CPI(Inflation)'!$E$3='CPI(Inflation)'!$E$33,'CPI(Inflation)'!E37,1)))) -> 4 | G34: =AVERAGE(C34*0.3 + D34*0.2 + E34*0.2 + F34*0.3) -> 3.8 | H34: =IF(PMI!$F$26=PMI!$B$43,PMI!$B47,IF(PMI!$F$26=PMI!$C$43,PMI!$C47,IF(PMI!$F$26=PMI!$D$43,PMI!$D47,IF(PMI!$F$26=PMI!$E$43,PMI!$E47,1)))) -> 4 | I34: =BNP!H101 -> 4 | J34: =IF('10 yr rate'!$E$25='10 yr rate'!$B$35,'10 yr rate'!$B39,IF('10 yr rate'!$E$25='10 yr rate'!$C$35,'10 yr rate'!$C39,IF('10 yr rate'!$E$25='10 yr rate'!$D$35,'10 yr rate'!$D39,IF('10 yr rate'!$E$25='10 yr rate'!$E$35,'10 yr rate'!$E39,1)))) -> 5 | K34: =IF('CPI(Inflation)'!$E$4='CPI(Inflation)'!$B$33,'CPI(Inflation)'!$B37,IF('CPI(Inflation)'!$E$4='CPI(Inflation)'!$C$33,'CPI(Inflation)'!$C37,IF('CPI(Inflation)'!$E$4='CPI(Inflation)'!$D$33,'CPI(Inflation)'!$D37,IF('CPI(Inflation)'!$E$4='CPI(Inflation)'!$E$33,'CPI(Inflation)'!$E37,1)))) -> 4 | L34: =AVERAGE(H34*0.3 + I34*0.2 + J34*0.2 + K34*0.3) -> 4.2 | M34: =IF(PMI!$F$27=PMI!$B$43,PMI!$B47,IF(PMI!$F$27=PMI!$C$43,PMI!$C47,IF(PMI!$F$27=PMI!$D$43,PMI!$D47,IF(PMI!$F$27=PMI!$E$43,PMI!$E47,1)))) -> 4 | N34: =BNP!E101 -> 2 | O34: =IF('10 yr rate'!$E$26='10 yr rate'!$B$35,'10 yr rate'!$B39,IF('10 yr rate'!$E$26='10 yr rate'!$C$35,'10 yr rate'!$C39,IF('10 yr rate'!$E$26='10 yr rate'!$D$35,'10 yr rate'!$D39,IF('10 yr rate'!$E$26='10 yr rate'!$E$35,'10 yr rate'!$E39,1)))) -> 4 | P34: =IF('CPI(Inflation)'!$E$5='CPI(Inflation)'!$B$33,'CPI(Inflation)'!$B37,IF('CPI(Inflation)'!$E$5='CPI(Inflation)'!$C$33,'CPI(Inflation)'!$C37,IF('CPI(Inflation)'!$E$5='CPI(Inflation)'!$D$33,'CPI(Inflation)'!$D37,IF('CPI(Inflation)'!$E$5='CPI(Inflation)'!$E$33,'CPI(Inflation)'!$E37,1)))) -> 1 | Q34: =AVERAGE(M34*0.3 + N34*0.2 + O34*0.2 + P34*0.3) -> 2.7 | R34: =IF(PMI!$F$28=PMI!$B$43,PMI!$B47,IF(PMI!$F$28=PMI!$C$43,PMI!$C47,IF(PMI!$F$28=PMI!$D$43,PMI!$D47,IF(PMI!$F$28=PMI!$E$43,PMI!$E47,1)))) -> 4 | S34: =BNP!F101 -> 4 | T34: =IF('10 yr rate'!$E$27='10 yr rate'!$B$35,'10 yr rate'!$B39,IF('10 yr rate'!$E$27='10 yr rate'!$C$35,'10 yr rate'!$C39,IF('10 yr rate'!$E$27='10 yr rate'!$D$35,'10 yr rate'!$D39,IF('10 yr rate'!$E$27='10 yr rate'!$E$35,'10 yr rate'!$E39,1)))) -> 4 | U34: =IF('CPI(Inflation)'!$E$6='CPI(Inflation)'!$B$33,'CPI(Inflation)'!$B37,IF('CPI(Inflation)'!$E$6='CPI(Inflation)'!$C$33,'CPI(Inflation)'!$C37,IF('CPI(Inflation)'!$E$6='CPI(Inflation)'!$D$33,'CPI(Inflation)'!$D37,IF('CPI(Inflation)'!$E$6='CPI(Inflation)'!$E$33,'CPI(Inflation)'!$E37,1)))) -> 4 | V34: =AVERAGE(R34*0.3 + S34*0.2 + T34*0.2 + U34*0.3) -> 4 | W34: =IF(PMI!$F$29=PMI!$B$43,PMI!$B47,IF(PMI!$F$29=PMI!$C$43,PMI!$C47,IF(PMI!$F$29=PMI!$D$43,PMI!$D47,IF(PMI!$F$29=PMI!$E$43,PMI!$E47,1)))) -> 5 | X34: =BNP!G101 -> 1 | Y34: =IF('10 yr rate'!$E$28='10 yr rate'!$B$35,'10 yr rate'!$B39,IF('10 yr rate'!$E$28='10 yr rate'!$C$35,'10 yr rate'!$C39,IF('10 yr rate'!$E$28='10 yr rate'!$D$35,'10 yr rate'!$D39,IF('10 yr rate'!$E$28='10 yr rate'!$E$35,'10 yr rate'!$E39,1)))) -> 4 | Z34: =IF('CPI(Inflation)'!$E$7='CPI(Inflation)'!$B$33,'CPI(Inflation)'!$B37,IF('CPI(Inflation)'!$E$7='CPI(Inflation)'!$C$33,'CPI(Inflation)'!$C37,IF('CPI(Inflation)'!$E$7='CPI(Inflation)'!$D$33,'CPI(Inflation)'!$D37,IF('CPI(Inflation)'!$E$7='CPI(Inflation)'!$E$33,'CPI(Inflation)'!$E37,1)))) -> 4 | AA34: =AVERAGE(W34*0.3 + X34*0.2 + Y34*0.2 + Z34*0.3) -> 3.7 | AB34: =IF(PMI!$F$30=PMI!$B$43,PMI!$B47,IF(PMI!$F$30=PMI!$C$43,PMI!$C47,IF(PMI!$F$30=PMI!$D$43,PMI!$D47,IF(PMI!$F$30=PMI!$E$43,PMI!$E47,1)))) -> 4 | AC34: =BNP!H101 -> 4 | AD34: =IF('10 yr rate'!$E$29='10 yr rate'!$B$35,'10 yr rate'!$B39,IF('10 yr rate'!$E$29='10 yr rate'!$C$35,'10 yr rate'!$C39,IF('10 yr rate'!$E$29='10 yr rate'!$D$35,'10 yr rate'!$D39,IF('10 yr rate'!$E$29='10 yr rate'!$E$35,'10 yr rate'!$E39,1)))) -> 4 | AE34: =IF('CPI(Inflation)'!$E$8='CPI(Inflation)'!$B$33,'CPI(Inflation)'!$B37,IF('CPI(Inflation)'!$E$8='CPI(Inflation)'!$C$33,'CPI(Inflation)'!$C37,IF('CPI(Inflation)'!$E$8='CPI(Inflation)'!$D$33,'CPI(Inflation)'!$D37,IF('CPI(Inflation)'!$E$8='CPI(Inflation)'!$E$33,'CPI(Inflation)'!$E37,1)))) -> 4 | AF34: =AVERAGE(AB34*0.3 + AC34*0.2 + AD34*0.2 + AE34*0.3) -> 4 | AG34: =IF(PMI!$F$31=PMI!$B$43,PMI!$B47,IF(PMI!$F$31=PMI!$C$43,PMI!$C47,IF(PMI!$F$31=PMI!$D$43,PMI!$D47,IF(PMI!$F$31=PMI!$E$43,PMI!$E47,1)))) -> 5 | AH34: =BNP!I101 -> 4 | AI34: =IF('10 yr rate'!$E$30='10 yr rate'!$B$35,'10 yr rate'!$B39,IF('10 yr rate'!$E$30='10 yr rate'!$C$35,'10 yr rate'!$C39,IF('10 yr rate'!$E$30='10 yr rate'!$D$35,'10 yr rate'!$D39,IF('10 yr rate'!$E$30='10 yr rate'!$E$35,'10 yr rate'!$E39,1)))) -> 5 | AJ34: =IF('CPI(Inflation)'!$E$9='CPI(Inflation)'!$B$33,'CPI(Inflation)'!$B37,IF('CPI(Inflation)'!$E$9='CPI(Inflation)'!$C$33,'CPI(Inflation)'!$C37,IF('CPI(Inflation)'!$E$9='CPI(Inflation)'!$D$33,'CPI(Inflation)'!$D37,IF('CPI(Inflation)'!$E$9='CPI(Inflation)'!$E$33,'CPI(Inflation)'!$E37,1)))) -> 5 | AK34: ='Baltic Dry Index'!B37 -> 4 | AL34: =IF(VIX!$F$25=VIX!$B$33,VIX!B37,IF(VIX!$F$25=VIX!$C$33,VIX!C37,IF(VIX!$F$25=VIX!$D$33,VIX!D37,IF(VIX!$F$25=VIX!$E$33,VIX!E37,1)))) -> 4 | AM34: =IF(Currency!$F$25=Currency!$B$33,Currency!B37,IF(Currency!$F$25=Currency!$C$33,Currency!C37,IF(Currency!$F$25=Currency!$D$33,Currency!D37,IF(Currency!$F$25=Currency!$E$33,Currency!E37,1)))) -> 3 | AN34: =IF(Unemployment!$F$25=Unemployment!$B$33,Unemployment!B37,IF(Unemployment!$F$25=Unemployment!$C$33,Unemployment!C37,IF(Unemployment!$F$25=Unemployment!$D$33,Unemployment!D37,IF(Unemployment!$F$25=Unemployment!$E$33,Unemployment!E37,1)))) -> 4 | AO34: =AVERAGE(AG34*0.2222 + AH34*0.1944 + AI34*0.1667 + AJ34*0.1389 + AK34*0.0556 + AL34*0.0556 + AM34*0.0556 + AN34*0.1111) -> 4.4726 | AP34: =IF(PMI!$F$32=PMI!$B$43,PMI!$B47,IF(PMI!$F$32=PMI!$C$43,PMI!$C47,IF(PMI!$F$32=PMI!$D$43,PMI!$D47,IF(PMI!$F$32=PMI!$E$43,PMI!$E47,1)))) -> 5 | AQ34: =BNP!J101 -> 2 | AR34: =IF('10 yr rate'!$E$31='10 yr rate'!$B$35,'10 yr rate'!$B39,IF('10 yr rate'!$E$31='10 yr rate'!$C$35,'10 yr rate'!$C39,IF('10 yr rate'!$E$31='10 yr rate'!$D$35,'10 yr rate'!$D39,IF('10 yr rate'!$E$31='10 yr rate'!$E$35,'10 yr rate'!$E39,1)))) -> 5 | AS34: =IF('CPI(Inflation)'!$E$10='CPI(Inflation)'!$B$33,'CPI(Inflation)'!$B37,IF('CPI(Inflation)'!$E$10='CPI(Inflation)'!$C$33,'CPI(Inflation)'!$C37,IF('CPI(Inflation)'!$E$10='CPI(Inflation)'!$D$33,'CPI(Inflation)'!$D37,IF('CPI(Inflation)'!$E$10='CPI(Inflation)'!$E$33,'CPI(Inflation)'!$E37,1)))) -> 4 | AT34: ='Baltic Dry Index'!B37 -> 4 | AU34: =IF(VIX!$F$26=VIX!$B$33,VIX!B37,IF(VIX!$F$26=VIX!$C$33,VIX!C37,IF(VIX!$F$26=VIX!$D$33,VIX!D37,IF(VIX!$F$26=VIX!$E$33,VIX!E37,1)))) -> 1 | AV34: =IF(Currency!$F$26=Currency!$B$33,Currency!B37,IF(Currency!$F$26=Currency!$C$33,Currency!C37,IF(Currency!$F$26=Currency!$D$33,Currency!D37,IF(Currency!$F$26=Currency!$E$33,Currency!E37,1)))) -> 5 | AW34: =IF(Unemployment!$F$26=Unemployment!$B$33,Unemployment!B37,IF(Unemployment!$F$26=Unemployment!$C$33,Unemployment!C37,IF(Unemployment!$F$26=Unemployment!$D$33,Unemployment!D37,IF(Unemployment!$F$26=Unemployment!$E$33,Unemployment!E37,1)))) -> 4 | AX34: =AVERAGE(AP34*0.2222 + AQ34*0.1944 + AR34*0.1667 + AS34*0.1389 + AT34*0.0556 + AU34*0.0556 + AV34*0.0556 + AW34*0.1111) -> 3.8893
B35: Industrials | C35: =IF(PMI!$F$25=PMI!$B$43,PMI!B48,IF(PMI!$F$25=PMI!$C$43,PMI!C48,IF(PMI!$F$25=PMI!$D$43,PMI!D48,IF(PMI!$F$25=PMI!$E$43,PMI!E48,1)))) -> 5 | D35: =BNP!C106 -> 3 | E35: =IF('10 yr rate'!$E$24='10 yr rate'!$B$35,'10 yr rate'!B40,IF('10 yr rate'!$E$24='10 yr rate'!$C$35,'10 yr rate'!C40,IF('10 yr rate'!$E$24='10 yr rate'!$D$35,'10 yr rate'!D40,IF('10 yr rate'!$E$24='10 yr rate'!$E$35,'10 yr rate'!E40,1)))) -> 5 | F35: =IF('CPI(Inflation)'!$E$3='CPI(Inflation)'!$B$33,'CPI(Inflation)'!B38,IF('CPI(Inflation)'!$E$3='CPI(Inflation)'!$C$33,'CPI(Inflation)'!C38,IF('CPI(Inflation)'!$E$3='CPI(Inflation)'!$D$33,'CPI(Inflation)'!D38,IF('CPI(Inflation)'!$E$3='CPI(Inflation)'!$E$33,'CPI(Inflation)'!E38,1)))) -> 5 | G35: =AVERAGE(C35*0.3 + D35*0.2 + E35*0.2 + F35*0.3) -> 4.6 | H35: =IF(PMI!$F$26=PMI!$B$43,PMI!$B48,IF(PMI!$F$26=PMI!$C$43,PMI!$C48,IF(PMI!$F$26=PMI!$D$43,PMI!$D48,IF(PMI!$F$26=PMI!$E$43,PMI!$E48,1)))) -> 5 | I35: =BNP!H106 -> 5 | J35: =IF('10 yr rate'!$E$25='10 yr rate'!$B$35,'10 yr rate'!$B40,IF('10 yr rate'!$E$25='10 yr rate'!$C$35,'10 yr rate'!$C40,IF('10 yr rate'!$E$25='10 yr rate'!$D$35,'10 yr rate'!$D40,IF('10 yr rate'!$E$25='10 yr rate'!$E$35,'10 yr rate'!$E40,1)))) -> 4 | K35: =IF('CPI(Inflation)'!$E$4='CPI(Inflation)'!$B$33,'CPI(Inflation)'!$B38,IF('CPI(Inflation)'!$E$4='CPI(Inflation)'!$C$33,'CPI(Inflation)'!$C38,IF('CPI(Inflation)'!$E$4='CPI(Inflation)'!$D$33,'CPI(Inflation)'!$D38,IF('CPI(Inflation)'!$E$4='CPI(Inflation)'!$E$33,'CPI(Inflation)'!$E38,1)))) -> 5 | L35: =AVERAGE(H35*0.3 + I35*0.2 + J35*0.2 + K35*0.3) -> 4.8 | M35: =IF(PMI!$F$27=PMI!$B$43,PMI!$B48,IF(PMI!$F$27=PMI!$C$43,PMI!$C48,IF(PMI!$F$27=PMI!$D$43,PMI!$D48,IF(PMI!$F$27=PMI!$E$43,PMI!$E48,1)))) -> 5 | N35: =BNP!E106 -> 3 | O35: =IF('10 yr rate'!$E$26='10 yr rate'!$B$35,'10 yr rate'!$B40,IF('10 yr rate'!$E$26='10 yr rate'!$C$35,'10 yr rate'!$C40,IF('10 yr rate'!$E$26='10 yr rate'!$D$35,'10 yr rate'!$D40,IF('10 yr rate'!$E$26='10 yr rate'!$E$35,'10 yr rate'!$E40,1)))) -> 5 | P35: =IF('CPI(Inflation)'!$E$5='CPI(Inflation)'!$B$33,'CPI(Inflation)'!$B38,IF('CPI(Inflation)'!$E$5='CPI(Inflation)'!$C$33,'CPI(Inflation)'!$C38,IF('CPI(Inflation)'!$E$5='CPI(Inflation)'!$D$33,'CPI(Inflation)'!$D38,IF('CPI(Inflation)'!$E$5='CPI(Inflation)'!$E$33,'CPI(Inflation)'!$E38,1)))) -> 1 | Q35: =AVERAGE(M35*0.3 + N35*0.2 + O35*0.2 + P35*0.3) -> 3.4 | R35: =IF(PMI!$F$28=PMI!$B$43,PMI!$B48,IF(PMI!$F$28=PMI!$C$43,PMI!$C48,IF(PMI!$F$28=PMI!$D$43,PMI!$D48,IF(PMI!$F$28=PMI!$E$43,PMI!$E48,1)))) -> 5 | S35: =BNP!F106 -> 3 | T35: =IF('10 yr rate'!$E$27='10 yr rate'!$B$35,'10 yr rate'!$B40,IF('10 yr rate'!$E$27='10 yr rate'!$C$35,'10 yr rate'!$C40,IF('10 yr rate'!$E$27='10 yr rate'!$D$35,'10 yr rate'!$D40,IF('10 yr rate'!$E$27='10 yr rate'!$E$35,'10 yr rate'!$E40,1)))) -> 5 | U35: =IF('CPI(Inflation)'!$E$6='CPI(Inflation)'!$B$33,'CPI(Inflation)'!$B38,IF('CPI(Inflation)'!$E$6='CPI(Inflation)'!$C$33,'CPI(Inflation)'!$C38,IF('CPI(Inflation)'!$E$6='CPI(Inflation)'!$D$33,'CPI(Inflation)'!$D38,IF('CPI(Inflation)'!$E$6='CPI(Inflation)'!$E$33,'CPI(Inflation)'!$E38,1)))) -> 5 | V35: =AVERAGE(R35*0.3 + S35*0.2 + T35*0.2 + U35*0.3) -> 4.6 | W35: =IF(PMI!$F$29=PMI!$B$43,PMI!$B48,IF(PMI!$F$29=PMI!$C$43,PMI!$C48,IF(PMI!$F$29=PMI!$D$43,PMI!$D48,IF(PMI!$F$29=PMI!$E$43,PMI!$E48,1)))) -> 4 | X35: =BNP!G106 -> 1 | Y35: =IF('10 yr rate'!$E$28='10 yr rate'!$B$35,'10 yr rate'!$B40,IF('10 yr rate'!$E$28='10 yr rate'!$C$35,'10 yr rate'!$C40,IF('10 yr rate'!$E$28='10 yr rate'!$D$35,'10 yr rate'!$D40,IF('10 yr rate'!$E$28='10 yr rate'!$E$35,'10 yr rate'!$E40,1)))) -> 5 | Z35: =IF('CPI(Inflation)'!$E$7='CPI(Inflation)'!$B$33,'CPI(Inflation)'!$B38,IF('CPI(Inflation)'!$E$7='CPI(Inflation)'!$C$33,'CPI(Inflation)'!$C38,IF('CPI(Inflation)'!$E$7='CPI(Inflation)'!$D$33,'CPI(Inflation)'!$D38,IF('CPI(Inflation)'!$E$7='CPI(Inflation)'!$E$33,'CPI(Inflation)'!$E38,1)))) -> 5 | AA35: =AVERAGE(W35*0.3 + X35*0.2 + Y35*0.2 + Z35*0.3) -> 3.9 | AB35: =IF(PMI!$F$30=PMI!$B$43,PMI!$B48,IF(PMI!$F$30=PMI!$C$43,PMI!$C48,IF(PMI!$F$30=PMI!$D$43,PMI!$D48,IF(PMI!$F$30=PMI!$E$43,PMI!$E48,1)))) -> 5 | AC35: =BNP!H106 -> 5 | AD35: =IF('10 yr rate'!$E$29='10 yr rate'!$B$35,'10 yr rate'!$B40,IF('10 yr rate'!$E$29='10 yr rate'!$C$35,'10 yr rate'!$C40,IF('10 yr rate'!$E$29='10 yr rate'!$D$35,'10 yr rate'!$D40,IF('10 yr rate'!$E$29='10 yr rate'!$E$35,'10 yr rate'!$E40,1)))) -> 5 | AE35: =IF('CPI(Inflation)'!$E$8='CPI(Inflation)'!$B$33,'CPI(Inflation)'!$B38,IF('CPI(Inflation)'!$E$8='CPI(Inflation)'!$C$33,'CPI(Inflation)'!$C38,IF('CPI(Inflation)'!$E$8='CPI(Inflation)'!$D$33,'CPI(Inflation)'!$D38,IF('CPI(Inflation)'!$E$8='CPI(Inflation)'!$E$33,'CPI(Inflation)'!$E38,1)))) -> 5 | AF35: =AVERAGE(AB35*0.3 + AC35*0.2 + AD35*0.2 + AE35*0.3) -> 5 | AG35: =IF(PMI!$F$31=PMI!$B$43,PMI!$B48,IF(PMI!$F$31=PMI!$C$43,PMI!$C48,IF(PMI!$F$31=PMI!$D$43,PMI!$D48,IF(PMI!$F$31=PMI!$E$43,PMI!$E48,1)))) -> 4 | AH35: =BNP!I106 -> 3 | AI35: =IF('10 yr rate'!$E$30='10 yr rate'!$B$35,'10 yr rate'!$B40,IF('10 yr rate'!$E$30='10 yr rate'!$C$35,'10 yr rate'!$C40,IF('10 yr rate'!$E$30='10 yr rate'!$D$35,'10 yr rate'!$D40,IF('10 yr rate'!$E$30='10 yr rate'!$E$35,'10 yr rate'!$E40,1)))) -> 4 | AJ35: =IF('CPI(Inflation)'!$E$9='CPI(Inflation)'!$B$33,'CPI(Inflation)'!$B38,IF('CPI(Inflation)'!$E$9='CPI(Inflation)'!$C$33,'CPI(Inflation)'!$C38,IF('CPI(Inflation)'!$E$9='CPI(Inflation)'!$D$33,'CPI(Inflation)'!$D38,IF('CPI(Inflation)'!$E$9='CPI(Inflation)'!$E$33,'CPI(Inflation)'!$E38,1)))) -> 4 | AK35: ='Baltic Dry Index'!B38 -> 5 | AL35: =IF(VIX!$F$25=VIX!$B$33,VIX!B38,IF(VIX!$F$25=VIX!$C$33,VIX!C38,IF(VIX!$F$25=VIX!$D$33,VIX!D38,IF(VIX!$F$25=VIX!$E$33,VIX!E38,1)))) -> 5 | AM35: =IF(Currency!$F$25=Currency!$B$33,Currency!B38,IF(Currency!$F$25=Currency!$C$33,Currency!C38,IF(Currency!$F$25=Currency!$D$33,Currency!D38,IF(Currency!$F$25=Currency!$E$33,Currency!E38,1)))) -> 2 | AN35: =IF(Unemployment!$F$25=Unemployment!$B$33,Unemployment!B38,IF(Unemployment!$F$25=Unemployment!$C$33,Unemployment!C38,IF(Unemployment!$F$25=Unemployment!$D$33,Unemployment!D38,IF(Unemployment!$F$25=Unemployment!$E$33,Unemployment!E38,1)))) -> 5 | AO35: =AVERAGE(AG35*0.2222 + AH35*0.1944 + AI35*0.1667 + AJ35*0.1389 + AK35*0.0556 + AL35*0.0556 + AM35*0.0556 + AN35*0.1111) -> 3.9171 | AP35: =IF(PMI!$F$32=PMI!$B$43,PMI!$B48,IF(PMI!$F$32=PMI!$C$43,PMI!$C48,IF(PMI!$F$32=PMI!$D$43,PMI!$D48,IF(PMI!$F$32=PMI!$E$43,PMI!$E48,1)))) -> 4 | AQ35: =BNP!J106 -> 3 | AR35: =IF('10 yr rate'!$E$31='10 yr rate'!$B$35,'10 yr rate'!$B40,IF('10 yr rate'!$E$31='10 yr rate'!$C$35,'10 yr rate'!$C40,IF('10 yr rate'!$E$31='10 yr rate'!$D$35,'10 yr rate'!$D40,IF('10 yr rate'!$E$31='10 yr rate'!$E$35,'10 yr rate'!$E40,1)))) -> 4 | AS35: =IF('CPI(Inflation)'!$E$10='CPI(Inflation)'!$B$33,'CPI(Inflation)'!$B38,IF('CPI(Inflation)'!$E$10='CPI(Inflation)'!$C$33,'CPI(Inflation)'!$C38,IF('CPI(Inflation)'!$E$10='CPI(Inflation)'!$D$33,'CPI(Inflation)'!$D38,IF('CPI(Inflation)'!$E$10='CPI(Inflation)'!$E$33,'CPI(Inflation)'!$E38,1)))) -> 5 | AT35: ='Baltic Dry Index'!B38 -> 5 | AU35: =IF(VIX!$F$26=VIX!$B$33,VIX!B38,IF(VIX!$F$26=VIX!$C$33,VIX!C38,IF(VIX!$F$26=VIX!$D$33,VIX!D38,IF(VIX!$F$26=VIX!$E$33,VIX!E38,1)))) -> 1 | AV35: =IF(Currency!$F$26=Currency!$B$33,Currency!B38,IF(Currency!$F$26=Currency!$C$33,Currency!C38,IF(Currency!$F$26=Currency!$D$33,Currency!D38,IF(Currency!$F$26=Currency!$E$33,Currency!E38,1)))) -> 4 | AW35: =IF(Unemployment!$F$26=Unemployment!$B$33,Unemployment!B38,IF(Unemployment!$F$26=Unemployment!$C$33,Unemployment!C38,IF(Unemployment!$F$26=Unemployment!$D$33,Unemployment!D38,IF(Unemployment!$F$26=Unemployment!$E$33,Unemployment!E38,1)))) -> 5 | AX35: =AVERAGE(AP35*0.2222 + AQ35*0.1944 + AR35*0.1667 + AS35*0.1389 + AT35*0.0556 + AU35*0.0556 + AV35*0.0556 + AW35*0.1111) -> 3.9448
B36: Materials | C36: =IF(PMI!$F$25=PMI!$B$43,PMI!B49,IF(PMI!$F$25=PMI!$C$43,PMI!C49,IF(PMI!$F$25=PMI!$D$43,PMI!D49,IF(PMI!$F$25=PMI!$E$43,PMI!E49,1)))) -> 4 | D36: =BNP!C116 -> 3 | E36: =IF('10 yr rate'!$E$24='10 yr rate'!$B$35,'10 yr rate'!B41,IF('10 yr rate'!$E$24='10 yr rate'!$C$35,'10 yr rate'!C41,IF('10 yr rate'!$E$24='10 yr rate'!$D$35,'10 yr rate'!D41,IF('10 yr rate'!$E$24='10 yr rate'!$E$35,'10 yr rate'!E41,1)))) -> 4 | F36: =IF('CPI(Inflation)'!$E$3='CPI(Inflation)'!$B$33,'CPI(Inflation)'!B39,IF('CPI(Inflation)'!$E$3='CPI(Inflation)'!$C$33,'CPI(Inflation)'!C39,IF('CPI(Inflation)'!$E$3='CPI(Inflation)'!$D$33,'CPI(Inflation)'!D39,IF('CPI(Inflation)'!$E$3='CPI(Inflation)'!$E$33,'CPI(Inflation)'!E39,1)))) -> 4 | G36: =AVERAGE(C36*0.3 + D36*0.2 + E36*0.2 + F36*0.3) -> 3.8 | H36: =IF(PMI!$F$26=PMI!$B$43,PMI!$B49,IF(PMI!$F$26=PMI!$C$43,PMI!$C49,IF(PMI!$F$26=PMI!$D$43,PMI!$D49,IF(PMI!$F$26=PMI!$E$43,PMI!$E49,1)))) -> 4 | I36: =BNP!H116 -> 3 | J36: =IF('10 yr rate'!$E$25='10 yr rate'!$B$35,'10 yr rate'!$B41,IF('10 yr rate'!$E$25='10 yr rate'!$C$35,'10 yr rate'!$C41,IF('10 yr rate'!$E$25='10 yr rate'!$D$35,'10 yr rate'!$D41,IF('10 yr rate'!$E$25='10 yr rate'!$E$35,'10 yr rate'!$E41,1)))) -> 2 | K36: =IF('CPI(Inflation)'!$E$4='CPI(Inflation)'!$B$33,'CPI(Inflation)'!$B39,IF('CPI(Inflation)'!$E$4='CPI(Inflation)'!$C$33,'CPI(Inflation)'!$C39,IF('CPI(Inflation)'!$E$4='CPI(Inflation)'!$D$33,'CPI(Inflation)'!$D39,IF('CPI(Inflation)'!$E$4='CPI(Inflation)'!$E$33,'CPI(Inflation)'!$E39,1)))) -> 4 | L36: =AVERAGE(H36*0.3 + I36*0.2 + J36*0.2 + K36*0.3) -> 3.4 | M36: =IF(PMI!$F$27=PMI!$B$43,PMI!$B49,IF(PMI!$F$27=PMI!$C$43,PMI!$C49,IF(PMI!$F$27=PMI!$D$43,PMI!$D49,IF(PMI!$F$27=PMI!$E$43,PMI!$E49,1)))) -> 4 | N36: =BNP!E116 -> 4 | O36: =IF('10 yr rate'!$E$26='10 yr rate'!$B$35,'10 yr rate'!$B41,IF('10 yr rate'!$E$26='10 yr rate'!$C$35,'10 yr rate'!$C41,IF('10 yr rate'!$E$26='10 yr rate'!$D$35,'10 yr rate'!$D41,IF('10 yr rate'!$E$26='10 yr rate'!$E$35,'10 yr rate'!$E41,1)))) -> 4 | P36: =IF('CPI(Inflation)'!$E$5='CPI(Inflation)'!$B$33,'CPI(Inflation)'!$B39,IF('CPI(Inflation)'!$E$5='CPI(Inflation)'!$C$33,'CPI(Inflation)'!$C39,IF('CPI(Inflation)'!$E$5='CPI(Inflation)'!$D$33,'CPI(Inflation)'!$D39,IF('CPI(Inflation)'!$E$5='CPI(Inflation)'!$E$33,'CPI(Inflation)'!$E39,1)))) -> 2 | Q36: =AVERAGE(M36*0.3 + N36*0.2 + O36*0.2 + P36*0.3) -> 3.4 | R36: =IF(PMI!$F$28=PMI!$B$43,PMI!$B49,IF(PMI!$F$28=PMI!$C$43,PMI!$C49,IF(PMI!$F$28=PMI!$D$43,PMI!$D49,IF(PMI!$F$28=PMI!$E$43,PMI!$E49,1)))) -> 4 | S36: =BNP!F116 -> 2 | T36: =IF('10 yr rate'!$E$27='10 yr rate'!$B$35,'10 yr rate'!$B41,IF('10 yr rate'!$E$27='10 yr rate'!$C$35,'10 yr rate'!$C41,IF('10 yr rate'!$E$27='10 yr rate'!$D$35,'10 yr rate'!$D41,IF('10 yr rate'!$E$27='10 yr rate'!$E$35,'10 yr rate'!$E41,1)))) -> 4 | U36: =IF('CPI(Inflation)'!$E$6='CPI(Inflation)'!$B$33,'CPI(Inflation)'!$B39,IF('CPI(Inflation)'!$E$6='CPI(Inflation)'!$C$33,'CPI(Inflation)'!$C39,IF('CPI(Inflation)'!$E$6='CPI(Inflation)'!$D$33,'CPI(Inflation)'!$D39,IF('CPI(Inflation)'!$E$6='CPI(Inflation)'!$E$33,'CPI(Inflation)'!$E39,1)))) -> 4 | V36: =AVERAGE(R36*0.3 + S36*0.2 + T36*0.2 + U36*0.3) -> 3.6 | W36: =IF(PMI!$F$29=PMI!$B$43,PMI!$B49,IF(PMI!$F$29=PMI!$C$43,PMI!$C49,IF(PMI!$F$29=PMI!$D$43,PMI!$D49,IF(PMI!$F$29=PMI!$E$43,PMI!$E49,1)))) -> 2 | X36: =BNP!G116 -> 5 | Y36: =IF('10 yr rate'!$E$28='10 yr rate'!$B$35,'10 yr rate'!$B41,IF('10 yr rate'!$E$28='10 yr rate'!$C$35,'10 yr rate'!$C41,IF('10 yr rate'!$E$28='10 yr rate'!$D$35,'10 yr rate'!$D41,IF('10 yr rate'!$E$28='10 yr rate'!$E$35,'10 yr rate'!$E41,1)))) -> 4 | Z36: =IF('CPI(Inflation)'!$E$7='CPI(Inflation)'!$B$33,'CPI(Inflation)'!$B39,IF('CPI(Inflation)'!$E$7='CPI(Inflation)'!$C$33,'CPI(Inflation)'!$C39,IF('CPI(Inflation)'!$E$7='CPI(Inflation)'!$D$33,'CPI(Inflation)'!$D39,IF('CPI(Inflation)'!$E$7='CPI(Inflation)'!$E$33,'CPI(Inflation)'!$E39,1)))) -> 4 | AA36: =AVERAGE(W36*0.3 + X36*0.2 + Y36*0.2 + Z36*0.3) -> 3.6 | AB36: =IF(PMI!$F$30=PMI!$B$43,PMI!$B49,IF(PMI!$F$30=PMI!$C$43,PMI!$C49,IF(PMI!$F$30=PMI!$D$43,PMI!$D49,IF(PMI!$F$30=PMI!$E$43,PMI!$E49,1)))) -> 4 | AC36: =BNP!H116 -> 3 | AD36: =IF('10 yr rate'!$E$29='10 yr rate'!$B$35,'10 yr rate'!$B41,IF('10 yr rate'!$E$29='10 yr rate'!$C$35,'10 yr rate'!$C41,IF('10 yr rate'!$E$29='10 yr rate'!$D$35,'10 yr rate'!$D41,IF('10 yr rate'!$E$29='10 yr rate'!$E$35,'10 yr rate'!$E41,1)))) -> 4 | AE36: =IF('CPI(Inflation)'!$E$8='CPI(Inflation)'!$B$33,'CPI(Inflation)'!$B39,IF('CPI(Inflation)'!$E$8='CPI(Inflation)'!$C$33,'CPI(Inflation)'!$C39,IF('CPI(Inflation)'!$E$8='CPI(Inflation)'!$D$33,'CPI(Inflation)'!$D39,IF('CPI(Inflation)'!$E$8='CPI(Inflation)'!$E$33,'CPI(Inflation)'!$E39,1)))) -> 4 | AF36: =AVERAGE(AB36*0.3 + AC36*0.2 + AD36*0.2 + AE36*0.3) -> 3.8 | AG36: =IF(PMI!$F$31=PMI!$B$43,PMI!$B49,IF(PMI!$F$31=PMI!$C$43,PMI!$C49,IF(PMI!$F$31=PMI!$D$43,PMI!$D49,IF(PMI!$F$31=PMI!$E$43,PMI!$E49,1)))) -> 2 | AH36: =BNP!I116 -> 2 | AI36: =IF('10 yr rate'!$E$30='10 yr rate'!$B$35,'10 yr rate'!$B41,IF('10 yr rate'!$E$30='10 yr rate'!$C$35,'10 yr rate'!$C41,IF('10 yr rate'!$E$30='10 yr rate'!$D$35,'10 yr rate'!$D41,IF('10 yr rate'!$E$30='10 yr rate'!$E$35,'10 yr rate'!$E41,1)))) -> 2 | AJ36: =IF('CPI(Inflation)'!$E$9='CPI(Inflation)'!$B$33,'CPI(Inflation)'!$B39,IF('CPI(Inflation)'!$E$9='CPI(Inflation)'!$C$33,'CPI(Inflation)'!$C39,IF('CPI(Inflation)'!$E$9='CPI(Inflation)'!$D$33,'CPI(Inflation)'!$D39,IF('CPI(Inflation)'!$E$9='CPI(Inflation)'!$E$33,'CPI(Inflation)'!$E39,1)))) -> 2 | AK36: ='Baltic Dry Index'!B39 -> 4 | AL36: =IF(VIX!$F$25=VIX!$B$33,VIX!B39,IF(VIX!$F$25=VIX!$C$33,VIX!C39,IF(VIX!$F$25=VIX!$D$33,VIX!D39,IF(VIX!$F$25=VIX!$E$33,VIX!E39,1)))) -> 4 | AM36: =IF(Currency!$F$25=Currency!$B$33,Currency!B39,IF(Currency!$F$25=Currency!$C$33,Currency!C39,IF(Currency!$F$25=Currency!$D$33,Currency!D39,IF(Currency!$F$25=Currency!$E$33,Currency!E39,1)))) -> 3 | AN36: =IF(Unemployment!$F$25=Unemployment!$B$33,Unemployment!B39,IF(Unemployment!$F$25=Unemployment!$C$33,Unemployment!C39,IF(Unemployment!$F$25=Unemployment!$D$33,Unemployment!D39,IF(Unemployment!$F$25=Unemployment!$E$33,Unemployment!E39,1)))) -> 4 | AO36: =AVERAGE(AG36*0.2222 + AH36*0.1944 + AI36*0.1667 + AJ36*0.1389 + AK36*0.0556 + AL36*0.0556 + AM36*0.0556 + AN36*0.1111) -> 2.5004 | AP36: =IF(PMI!$F$32=PMI!$B$43,PMI!$B49,IF(PMI!$F$32=PMI!$C$43,PMI!$C49,IF(PMI!$F$32=PMI!$D$43,PMI!$D49,IF(PMI!$F$32=PMI!$E$43,PMI!$E49,1)))) -> 2 | AQ36: =BNP!J116 -> 4 | AR36: =IF('10 yr rate'!$E$31='10 yr rate'!$B$35,'10 yr rate'!$B41,IF('10 yr rate'!$E$31='10 yr rate'!$C$35,'10 yr rate'!$C41,IF('10 yr rate'!$E$31='10 yr rate'!$D$35,'10 yr rate'!$D41,IF('10 yr rate'!$E$31='10 yr rate'!$E$35,'10 yr rate'!$E41,1)))) -> 2 | AS36: =IF('CPI(Inflation)'!$E$10='CPI(Inflation)'!$B$33,'CPI(Inflation)'!$B39,IF('CPI(Inflation)'!$E$10='CPI(Inflation)'!$C$33,'CPI(Inflation)'!$C39,IF('CPI(Inflation)'!$E$10='CPI(Inflation)'!$D$33,'CPI(Inflation)'!$D39,IF('CPI(Inflation)'!$E$10='CPI(Inflation)'!$E$33,'CPI(Inflation)'!$E39,1)))) -> 4 | AT36: ='Baltic Dry Index'!B39 -> 4 | AU36: =IF(VIX!$F$26=VIX!$B$33,VIX!B39,IF(VIX!$F$26=VIX!$C$33,VIX!C39,IF(VIX!$F$26=VIX!$D$33,VIX!D39,IF(VIX!$F$26=VIX!$E$33,VIX!E39,1)))) -> 2 | AV36: =IF(Currency!$F$26=Currency!$B$33,Currency!B39,IF(Currency!$F$26=Currency!$C$33,Currency!C39,IF(Currency!$F$26=Currency!$D$33,Currency!D39,IF(Currency!$F$26=Currency!$E$33,Currency!E39,1)))) -> 2 | AW36: =IF(Unemployment!$F$26=Unemployment!$B$33,Unemployment!B39,IF(Unemployment!$F$26=Unemployment!$C$33,Unemployment!C39,IF(Unemployment!$F$26=Unemployment!$D$33,Unemployment!D39,IF(Unemployment!$F$26=Unemployment!$E$33,Unemployment!E39,1)))) -> 4 | AX36: =AVERAGE(AP36*0.2222 + AQ36*0.1944 + AR36*0.1667 + AS36*0.1389 + AT36*0.0556 + AU36*0.0556 + AV36*0.0556 + AW36*0.1111) -> 3.0002
B37: Consumer Staples | C37: =IF(PMI!$F$25=PMI!$B$43,PMI!B50,IF(PMI!$F$25=PMI!$C$43,PMI!C50,IF(PMI!$F$25=PMI!$D$43,PMI!D50,IF(PMI!$F$25=PMI!$E$43,PMI!E50,1)))) -> 2 | D37: =BNP!C121 -> 3 | E37: =IF('10 yr rate'!$E$24='10 yr rate'!$B$35,'10 yr rate'!B42,IF('10 yr rate'!$E$24='10 yr rate'!$C$35,'10 yr rate'!C42,IF('10 yr rate'!$E$24='10 yr rate'!$D$35,'10 yr rate'!D42,IF('10 yr rate'!$E$24='10 yr rate'!$E$35,'10 yr rate'!E42,1)))) -> 2 | F37: =IF('CPI(Inflation)'!$E$3='CPI(Inflation)'!$B$33,'CPI(Inflation)'!B40,IF('CPI(Inflation)'!$E$3='CPI(Inflation)'!$C$33,'CPI(Inflation)'!C40,IF('CPI(Inflation)'!$E$3='CPI(Inflation)'!$D$33,'CPI(Inflation)'!D40,IF('CPI(Inflation)'!$E$3='CPI(Inflation)'!$E$33,'CPI(Inflation)'!E40,1)))) -> 2 | G37: =AVERAGE(C37*0.3 + D37*0.2 + E37*0.2 + F37*0.3) -> 2.2 | H37: =IF(PMI!$F$26=PMI!$B$43,PMI!$B50,IF(PMI!$F$26=PMI!$C$43,PMI!$C50,IF(PMI!$F$26=PMI!$D$43,PMI!$D50,IF(PMI!$F$26=PMI!$E$43,PMI!$E50,1)))) -> 2 | I37: =BNP!H121 -> 1 | J37: =IF('10 yr rate'!$E$25='10 yr rate'!$B$35,'10 yr rate'!$B42,IF('10 yr rate'!$E$25='10 yr rate'!$C$35,'10 yr rate'!$C42,IF('10 yr rate'!$E$25='10 yr rate'!$D$35,'10 yr rate'!$D42,IF('10 yr rate'!$E$25='10 yr rate'!$E$35,'10 yr rate'!$E42,1)))) -> 2 | K37: =IF('CPI(Inflation)'!$E$4='CPI(Inflation)'!$B$33,'CPI(Inflation)'!$B40,IF('CPI(Inflation)'!$E$4='CPI(Inflation)'!$C$33,'CPI(Inflation)'!$C40,IF('CPI(Inflation)'!$E$4='CPI(Inflation)'!$D$33,'CPI(Inflation)'!$D40,IF('CPI(Inflation)'!$E$4='CPI(Inflation)'!$E$33,'CPI(Inflation)'!$E40,1)))) -> 2 | L37: =AVERAGE(H37*0.3 + I37*0.2 + J37*0.2 + K37*0.3) -> 1.8 | M37: =IF(PMI!$F$27=PMI!$B$43,PMI!$B50,IF(PMI!$F$27=PMI!$C$43,PMI!$C50,IF(PMI!$F$27=PMI!$D$43,PMI!$D50,IF(PMI!$F$27=PMI!$E$43,PMI!$E50,1)))) -> 2 | N37: =BNP!E121 -> 3 | O37: =IF('10 yr rate'!$E$26='10 yr rate'!$B$35,'10 yr rate'!$B42,IF('10 yr rate'!$E$26='10 yr rate'!$C$35,'10 yr rate'!$C42,IF('10 yr rate'!$E$26='10 yr rate'!$D$35,'10 yr rate'!$D42,IF('10 yr rate'!$E$26='10 yr rate'!$E$35,'10 yr rate'!$E42,1)))) -> 2 | P37: =IF('CPI(Inflation)'!$E$5='CPI(Inflation)'!$B$33,'CPI(Inflation)'!$B40,IF('CPI(Inflation)'!$E$5='CPI(Inflation)'!$C$33,'CPI(Inflation)'!$C40,IF('CPI(Inflation)'!$E$5='CPI(Inflation)'!$D$33,'CPI(Inflation)'!$D40,IF('CPI(Inflation)'!$E$5='CPI(Inflation)'!$E$33,'CPI(Inflation)'!$E40,1)))) -> 5 | Q37: =AVERAGE(M37*0.3 + N37*0.2 + O37*0.2 + P37*0.3) -> 3.1 | R37: =IF(PMI!$F$28=PMI!$B$43,PMI!$B50,IF(PMI!$F$28=PMI!$C$43,PMI!$C50,IF(PMI!$F$28=PMI!$D$43,PMI!$D50,IF(PMI!$F$28=PMI!$E$43,PMI!$E50,1)))) -> 2 | S37: =BNP!F121 -> 3 | T37: =IF('10 yr rate'!$E$27='10 yr rate'!$B$35,'10 yr rate'!$B42,IF('10 yr rate'!$E$27='10 yr rate'!$C$35,'10 yr rate'!$C42,IF('10 yr rate'!$E$27='10 yr rate'!$D$35,'10 yr rate'!$D42,IF('10 yr rate'!$E$27='10 yr rate'!$E$35,'10 yr rate'!$E42,1)))) -> 2 | U37: =IF('CPI(Inflation)'!$E$6='CPI(Inflation)'!$B$33,'CPI(Inflation)'!$B40,IF('CPI(Inflation)'!$E$6='CPI(Inflation)'!$C$33,'CPI(Inflation)'!$C40,IF('CPI(Inflation)'!$E$6='CPI(Inflation)'!$D$33,'CPI(Inflation)'!$D40,IF('CPI(Inflation)'!$E$6='CPI(Inflation)'!$E$33,'CPI(Inflation)'!$E40,1)))) -> 2 | V37: =AVERAGE(R37*0.3 + S37*0.2 + T37*0.2 + U37*0.3) -> 2.2 | W37: =IF(PMI!$F$29=PMI!$B$43,PMI!$B50,IF(PMI!$F$29=PMI!$C$43,PMI!$C50,IF(PMI!$F$29=PMI!$D$43,PMI!$D50,IF(PMI!$F$29=PMI!$E$43,PMI!$E50,1)))) -> 2 | X37: =BNP!G121 -> 5 | Y37: =IF('10 yr rate'!$E$28='10 yr rate'!$B$35,'10 yr rate'!$B42,IF('10 yr rate'!$E$28='10 yr rate'!$C$35,'10 yr rate'!$C42,IF('10 yr rate'!$E$28='10 yr rate'!$D$35,'10 yr rate'!$D42,IF('10 yr rate'!$E$28='10 yr rate'!$E$35,'10 yr rate'!$E42,1)))) -> 2 | Z37: =IF('CPI(Inflation)'!$E$7='CPI(Inflation)'!$B$33,'CPI(Inflation)'!$B40,IF('CPI(Inflation)'!$E$7='CPI(Inflation)'!$C$33,'CPI(Inflation)'!$C40,IF('CPI(Inflation)'!$E$7='CPI(Inflation)'!$D$33,'CPI(Inflation)'!$D40,IF('CPI(Inflation)'!$E$7='CPI(Inflation)'!$E$33,'CPI(Inflation)'!$E40,1)))) -> 2 | AA37: =AVERAGE(W37*0.3 + X37*0.2 + Y37*0.2 + Z37*0.3) -> 2.6 | AB37: =IF(PMI!$F$30=PMI!$B$43,PMI!$B50,IF(PMI!$F$30=PMI!$C$43,PMI!$C50,IF(PMI!$F$30=PMI!$D$43,PMI!$D50,IF(PMI!$F$30=PMI!$E$43,PMI!$E50,1)))) -> 2 | AC37: =BNP!H121 -> 1 | AD37: =IF('10 yr rate'!$E$29='10 yr rate'!$B$35,'10 yr rate'!$B42,IF('10 yr rate'!$E$29='10 yr rate'!$C$35,'10 yr rate'!$C42,IF('10 yr rate'!$E$29='10 yr rate'!$D$35,'10 yr rate'!$D42,IF('10 yr rate'!$E$29='10 yr rate'!$E$35,'10 yr rate'!$E42,1)))) -> 2 | AE37: =IF('CPI(Inflation)'!$E$8='CPI(Inflation)'!$B$33,'CPI(Inflation)'!$B40,IF('CPI(Inflation)'!$E$8='CPI(Inflation)'!$C$33,'CPI(Inflation)'!$C40,IF('CPI(Inflation)'!$E$8='CPI(Inflation)'!$D$33,'CPI(Inflation)'!$D40,IF('CPI(Inflation)'!$E$8='CPI(Inflation)'!$E$33,'CPI(Inflation)'!$E40,1)))) -> 2 | AF37: =AVERAGE(AB37*0.3 + AC37*0.2 + AD37*0.2 + AE37*0.3) -> 1.8 | AG37: =IF(PMI!$F$31=PMI!$B$43,PMI!$B50,IF(PMI!$F$31=PMI!$C$43,PMI!$C50,IF(PMI!$F$31=PMI!$D$43,PMI!$D50,IF(PMI!$F$31=PMI!$E$43,PMI!$E50,1)))) -> 2 | AH37: =BNP!I121 -> 3 | AI37: =IF('10 yr rate'!$E$30='10 yr rate'!$B$35,'10 yr rate'!$B42,IF('10 yr rate'!$E$30='10 yr rate'!$C$35,'10 yr rate'!$C42,IF('10 yr rate'!$E$30='10 yr rate'!$D$35,'10 yr rate'!$D42,IF('10 yr rate'!$E$30='10 yr rate'!$E$35,'10 yr rate'!$E42,1)))) -> 2 | AJ37: =IF('CPI(Inflation)'!$E$9='CPI(Inflation)'!$B$33,'CPI(Inflation)'!$B40,IF('CPI(Inflation)'!$E$9='CPI(Inflation)'!$C$33,'CPI(Inflation)'!$C40,IF('CPI(Inflation)'!$E$9='CPI(Inflation)'!$D$33,'CPI(Inflation)'!$D40,IF('CPI(Inflation)'!$E$9='CPI(Inflation)'!$E$33,'CPI(Inflation)'!$E40,1)))) -> 2 | AK37: ='Baltic Dry Index'!B40 -> 2 | AL37: =IF(VIX!$F$25=VIX!$B$33,VIX!B40,IF(VIX!$F$25=VIX!$C$33,VIX!C40,IF(VIX!$F$25=VIX!$D$33,VIX!D40,IF(VIX!$F$25=VIX!$E$33,VIX!E40,1)))) -> 2 | AM37: =IF(Currency!$F$25=Currency!$B$33,Currency!B40,IF(Currency!$F$25=Currency!$C$33,Currency!C40,IF(Currency!$F$25=Currency!$D$33,Currency!D40,IF(Currency!$F$25=Currency!$E$33,Currency!E40,1)))) -> 4 | AN37: =IF(Unemployment!$F$25=Unemployment!$B$33,Unemployment!B40,IF(Unemployment!$F$25=Unemployment!$C$33,Unemployment!C40,IF(Unemployment!$F$25=Unemployment!$D$33,Unemployment!D40,IF(Unemployment!$F$25=Unemployment!$E$33,Unemployment!E40,1)))) -> 2 | AO37: =AVERAGE(AG37*0.2222 + AH37*0.1944 + AI37*0.1667 + AJ37*0.1389 + AK37*0.0556 + AL37*0.0556 + AM37*0.0556 + AN37*0.1111) -> 2.3058 | AP37: =IF(PMI!$F$32=PMI!$B$43,PMI!$B50,IF(PMI!$F$32=PMI!$C$43,PMI!$C50,IF(PMI!$F$32=PMI!$D$43,PMI!$D50,IF(PMI!$F$32=PMI!$E$43,PMI!$E50,1)))) -> 2 | AQ37: =BNP!J121 -> 3 | AR37: =IF('10 yr rate'!$E$31='10 yr rate'!$B$35,'10 yr rate'!$B42,IF('10 yr rate'!$E$31='10 yr rate'!$C$35,'10 yr rate'!$C42,IF('10 yr rate'!$E$31='10 yr rate'!$D$35,'10 yr rate'!$D42,IF('10 yr rate'!$E$31='10 yr rate'!$E$35,'10 yr rate'!$E42,1)))) -> 2 | AS37: =IF('CPI(Inflation)'!$E$10='CPI(Inflation)'!$B$33,'CPI(Inflation)'!$B40,IF('CPI(Inflation)'!$E$10='CPI(Inflation)'!$C$33,'CPI(Inflation)'!$C40,IF('CPI(Inflation)'!$E$10='CPI(Inflation)'!$D$33,'CPI(Inflation)'!$D40,IF('CPI(Inflation)'!$E$10='CPI(Inflation)'!$E$33,'CPI(Inflation)'!$E40,1)))) -> 2 | AT37: ='Baltic Dry Index'!B40 -> 2 | AU37: =IF(VIX!$F$26=VIX!$B$33,VIX!B40,IF(VIX!$F$26=VIX!$C$33,VIX!C40,IF(VIX!$F$26=VIX!$D$33,VIX!D40,IF(VIX!$F$26=VIX!$E$33,VIX!E40,1)))) -> 5 | AV37: =IF(Currency!$F$26=Currency!$B$33,Currency!B40,IF(Currency!$F$26=Currency!$C$33,Currency!C40,IF(Currency!$F$26=Currency!$D$33,Currency!D40,IF(Currency!$F$26=Currency!$E$33,Currency!E40,1)))) -> 2 | AW37: =IF(Unemployment!$F$26=Unemployment!$B$33,Unemployment!B40,IF(Unemployment!$F$26=Unemployment!$C$33,Unemployment!C40,IF(Unemployment!$F$26=Unemployment!$D$33,Unemployment!D40,IF(Unemployment!$F$26=Unemployment!$E$33,Unemployment!E40,1)))) -> 2 | AX37: =AVERAGE(AP37*0.2222 + AQ37*0.1944 + AR37*0.1667 + AS37*0.1389 + AT37*0.0556 + AU37*0.0556 + AV37*0.0556 + AW37*0.1111) -> 2.3614
B38: Health Care | C38: =IF(PMI!$F$25=PMI!$B$43,PMI!B51,IF(PMI!$F$25=PMI!$C$43,PMI!C51,IF(PMI!$F$25=PMI!$D$43,PMI!D51,IF(PMI!$F$25=PMI!$E$43,PMI!E51,1)))) -> 2 | D38: =BNP!C121 -> 3 | E38: =IF('10 yr rate'!$E$24='10 yr rate'!$B$35,'10 yr rate'!B43,IF('10 yr rate'!$E$24='10 yr rate'!$C$35,'10 yr rate'!C43,IF('10 yr rate'!$E$24='10 yr rate'!$D$35,'10 yr rate'!D43,IF('10 yr rate'!$E$24='10 yr rate'!$E$35,'10 yr rate'!E43,1)))) -> 2 | F38: =IF('CPI(Inflation)'!$E$3='CPI(Inflation)'!$B$33,'CPI(Inflation)'!B41,IF('CPI(Inflation)'!$E$3='CPI(Inflation)'!$C$33,'CPI(Inflation)'!C41,IF('CPI(Inflation)'!$E$3='CPI(Inflation)'!$D$33,'CPI(Inflation)'!D41,IF('CPI(Inflation)'!$E$3='CPI(Inflation)'!$E$33,'CPI(Inflation)'!E41,1)))) -> 2 | G38: =AVERAGE(C38*0.3 + D38*0.2 + E38*0.2 + F38*0.3) -> 2.2 | H38: =IF(PMI!$F$26=PMI!$B$43,PMI!$B51,IF(PMI!$F$26=PMI!$C$43,PMI!$C51,IF(PMI!$F$26=PMI!$D$43,PMI!$D51,IF(PMI!$F$26=PMI!$E$43,PMI!$E51,1)))) -> 2 | I38: =BNP!H121 -> 1 | J38: =IF('10 yr rate'!$E$25='10 yr rate'!$B$35,'10 yr rate'!$B43,IF('10 yr rate'!$E$25='10 yr rate'!$C$35,'10 yr rate'!$C43,IF('10 yr rate'!$E$25='10 yr rate'!$D$35,'10 yr rate'!$D43,IF('10 yr rate'!$E$25='10 yr rate'!$E$35,'10 yr rate'!$E43,1)))) -> 3 | K38: =IF('CPI(Inflation)'!$E$4='CPI(Inflation)'!$B$33,'CPI(Inflation)'!$B41,IF('CPI(Inflation)'!$E$4='CPI(Inflation)'!$C$33,'CPI(Inflation)'!$C41,IF('CPI(Inflation)'!$E$4='CPI(Inflation)'!$D$33,'CPI(Inflation)'!$D41,IF('CPI(Inflation)'!$E$4='CPI(Inflation)'!$E$33,'CPI(Inflation)'!$E41,1)))) -> 2 | L38: =AVERAGE(H38*0.3 + I38*0.2 + J38*0.2 + K38*0.3) -> 2 | M38: =IF(PMI!$F$27=PMI!$B$43,PMI!$B51,IF(PMI!$F$27=PMI!$C$43,PMI!$C51,IF(PMI!$F$27=PMI!$D$43,PMI!$D51,IF(PMI!$F$27=PMI!$E$43,PMI!$E51,1)))) -> 2 | N38: =BNP!E121 -> 3 | O38: =IF('10 yr rate'!$E$26='10 yr rate'!$B$35,'10 yr rate'!$B43,IF('10 yr rate'!$E$26='10 yr rate'!$C$35,'10 yr rate'!$C43,IF('10 yr rate'!$E$26='10 yr rate'!$D$35,'10 yr rate'!$D43,IF('10 yr rate'!$E$26='10 yr rate'!$E$35,'10 yr rate'!$E43,1)))) -> 2 | P38: =IF('CPI(Inflation)'!$E$5='CPI(Inflation)'!$B$33,'CPI(Inflation)'!$B41,IF('CPI(Inflation)'!$E$5='CPI(Inflation)'!$C$33,'CPI(Inflation)'!$C41,IF('CPI(Inflation)'!$E$5='CPI(Inflation)'!$D$33,'CPI(Inflation)'!$D41,IF('CPI(Inflation)'!$E$5='CPI(Inflation)'!$E$33,'CPI(Inflation)'!$E41,1)))) -> 5 | Q38: =AVERAGE(M38*0.3 + N38*0.2 + O38*0.2 + P38*0.3) -> 3.1 | R38: =IF(PMI!$F$28=PMI!$B$43,PMI!$B51,IF(PMI!$F$28=PMI!$C$43,PMI!$C51,IF(PMI!$F$28=PMI!$D$43,PMI!$D51,IF(PMI!$F$28=PMI!$E$43,PMI!$E51,1)))) -> 2 | S38: =BNP!F121 -> 3 | T38: =IF('10 yr rate'!$E$27='10 yr rate'!$B$35,'10 yr rate'!$B43,IF('10 yr rate'!$E$27='10 yr rate'!$C$35,'10 yr rate'!$C43,IF('10 yr rate'!$E$27='10 yr rate'!$D$35,'10 yr rate'!$D43,IF('10 yr rate'!$E$27='10 yr rate'!$E$35,'10 yr rate'!$E43,1)))) -> 2 | U38: =IF('CPI(Inflation)'!$E$6='CPI(Inflation)'!$B$33,'CPI(Inflation)'!$B41,IF('CPI(Inflation)'!$E$6='CPI(Inflation)'!$C$33,'CPI(Inflation)'!$C41,IF('CPI(Inflation)'!$E$6='CPI(Inflation)'!$D$33,'CPI(Inflation)'!$D41,IF('CPI(Inflation)'!$E$6='CPI(Inflation)'!$E$33,'CPI(Inflation)'!$E41,1)))) -> 2 | V38: =AVERAGE(R38*0.3 + S38*0.2 + T38*0.2 + U38*0.3) -> 2.2 | W38: =IF(PMI!$F$29=PMI!$B$43,PMI!$B51,IF(PMI!$F$29=PMI!$C$43,PMI!$C51,IF(PMI!$F$29=PMI!$D$43,PMI!$D51,IF(PMI!$F$29=PMI!$E$43,PMI!$E51,1)))) -> 3 | X38: =BNP!G121 -> 5 | Y38: =IF('10 yr rate'!$E$28='10 yr rate'!$B$35,'10 yr rate'!$B43,IF('10 yr rate'!$E$28='10 yr rate'!$C$35,'10 yr rate'!$C43,IF('10 yr rate'!$E$28='10 yr rate'!$D$35,'10 yr rate'!$D43,IF('10 yr rate'!$E$28='10 yr rate'!$E$35,'10 yr rate'!$E43,1)))) -> 2 | Z38: =IF('CPI(Inflation)'!$E$7='CPI(Inflation)'!$B$33,'CPI(Inflation)'!$B41,IF('CPI(Inflation)'!$E$7='CPI(Inflation)'!$C$33,'CPI(Inflation)'!$C41,IF('CPI(Inflation)'!$E$7='CPI(Inflation)'!$D$33,'CPI(Inflation)'!$D41,IF('CPI(Inflation)'!$E$7='CPI(Inflation)'!$E$33,'CPI(Inflation)'!$E41,1)))) -> 2 | AA38: =AVERAGE(W38*0.3 + X38*0.2 + Y38*0.2 + Z38*0.3) -> 2.9 | AB38: =IF(PMI!$F$30=PMI!$B$43,PMI!$B51,IF(PMI!$F$30=PMI!$C$43,PMI!$C51,IF(PMI!$F$30=PMI!$D$43,PMI!$D51,IF(PMI!$F$30=PMI!$E$43,PMI!$E51,1)))) -> 2 | AC38: =BNP!H121 -> 1 | AD38: =IF('10 yr rate'!$E$29='10 yr rate'!$B$35,'10 yr rate'!$B43,IF('10 yr rate'!$E$29='10 yr rate'!$C$35,'10 yr rate'!$C43,IF('10 yr rate'!$E$29='10 yr rate'!$D$35,'10 yr rate'!$D43,IF('10 yr rate'!$E$29='10 yr rate'!$E$35,'10 yr rate'!$E43,1)))) -> 2 | AE38: =IF('CPI(Inflation)'!$E$8='CPI(Inflation)'!$B$33,'CPI(Inflation)'!$B41,IF('CPI(Inflation)'!$E$8='CPI(Inflation)'!$C$33,'CPI(Inflation)'!$C41,IF('CPI(Inflation)'!$E$8='CPI(Inflation)'!$D$33,'CPI(Inflation)'!$D41,IF('CPI(Inflation)'!$E$8='CPI(Inflation)'!$E$33,'CPI(Inflation)'!$E41,1)))) -> 2 | AF38: =AVERAGE(AB38*0.3 + AC38*0.2 + AD38*0.2 + AE38*0.3) -> 1.8 | AG38: =IF(PMI!$F$31=PMI!$B$43,PMI!$B51,IF(PMI!$F$31=PMI!$C$43,PMI!$C51,IF(PMI!$F$31=PMI!$D$43,PMI!$D51,IF(PMI!$F$31=PMI!$E$43,PMI!$E51,1)))) -> 3 | AH38: =BNP!I121 -> 3 | AI38: =IF('10 yr rate'!$E$30='10 yr rate'!$B$35,'10 yr rate'!$B43,IF('10 yr rate'!$E$30='10 yr rate'!$C$35,'10 yr rate'!$C43,IF('10 yr rate'!$E$30='10 yr rate'!$D$35,'10 yr rate'!$D43,IF('10 yr rate'!$E$30='10 yr rate'!$E$35,'10 yr rate'!$E43,1)))) -> 3 | AJ38: =IF('CPI(Inflation)'!$E$9='CPI(Inflation)'!$B$33,'CPI(Inflation)'!$B41,IF('CPI(Inflation)'!$E$9='CPI(Inflation)'!$C$33,'CPI(Inflation)'!$C41,IF('CPI(Inflation)'!$E$9='CPI(Inflation)'!$D$33,'CPI(Inflation)'!$D41,IF('CPI(Inflation)'!$E$9='CPI(Inflation)'!$E$33,'CPI(Inflation)'!$E41,1)))) -> 3 | AK38: ='Baltic Dry Index'!B41 -> 2 | AL38: =IF(VIX!$F$25=VIX!$B$33,VIX!B41,IF(VIX!$F$25=VIX!$C$33,VIX!C41,IF(VIX!$F$25=VIX!$D$33,VIX!D41,IF(VIX!$F$25=VIX!$E$33,VIX!E41,1)))) -> 2 | AM38: =IF(Currency!$F$25=Currency!$B$33,Currency!B41,IF(Currency!$F$25=Currency!$C$33,Currency!C41,IF(Currency!$F$25=Currency!$D$33,Currency!D41,IF(Currency!$F$25=Currency!$E$33,Currency!E41,1)))) -> 3 | AN38: =IF(Unemployment!$F$25=Unemployment!$B$33,Unemployment!B41,IF(Unemployment!$F$25=Unemployment!$C$33,Unemployment!C41,IF(Unemployment!$F$25=Unemployment!$D$33,Unemployment!D41,IF(Unemployment!$F$25=Unemployment!$E$33,Unemployment!E41,1)))) -> 2 | AO38: =AVERAGE(AG38*0.2222 + AH38*0.1944 + AI38*0.1667 + AJ38*0.1389 + AK38*0.0556 + AL38*0.0556 + AM38*0.0556 + AN38*0.1111) -> 2.778 | AP38: =IF(PMI!$F$32=PMI!$B$43,PMI!$B51,IF(PMI!$F$32=PMI!$C$43,PMI!$C51,IF(PMI!$F$32=PMI!$D$43,PMI!$D51,IF(PMI!$F$32=PMI!$E$43,PMI!$E51,1)))) -> 3 | AQ38: =BNP!J121 -> 3 | AR38: =IF('10 yr rate'!$E$31='10 yr rate'!$B$35,'10 yr rate'!$B43,IF('10 yr rate'!$E$31='10 yr rate'!$C$35,'10 yr rate'!$C43,IF('10 yr rate'!$E$31='10 yr rate'!$D$35,'10 yr rate'!$D43,IF('10 yr rate'!$E$31='10 yr rate'!$E$35,'10 yr rate'!$E43,1)))) -> 3 | AS38: =IF('CPI(Inflation)'!$E$10='CPI(Inflation)'!$B$33,'CPI(Inflation)'!$B41,IF('CPI(Inflation)'!$E$10='CPI(Inflation)'!$C$33,'CPI(Inflation)'!$C41,IF('CPI(Inflation)'!$E$10='CPI(Inflation)'!$D$33,'CPI(Inflation)'!$D41,IF('CPI(Inflation)'!$E$10='CPI(Inflation)'!$E$33,'CPI(Inflation)'!$E41,1)))) -> 2 | AT38: ='Baltic Dry Index'!B41 -> 2 | AU38: =IF(VIX!$F$26=VIX!$B$33,VIX!B41,IF(VIX!$F$26=VIX!$C$33,VIX!C41,IF(VIX!$F$26=VIX!$D$33,VIX!D41,IF(VIX!$F$26=VIX!$E$33,VIX!E41,1)))) -> 5 | AV38: =IF(Currency!$F$26=Currency!$B$33,Currency!B41,IF(Currency!$F$26=Currency!$C$33,Currency!C41,IF(Currency!$F$26=Currency!$D$33,Currency!D41,IF(Currency!$F$26=Currency!$E$33,Currency!E41,1)))) -> 3 | AW38: =IF(Unemployment!$F$26=Unemployment!$B$33,Unemployment!B41,IF(Unemployment!$F$26=Unemployment!$C$33,Unemployment!C41,IF(Unemployment!$F$26=Unemployment!$D$33,Unemployment!D41,IF(Unemployment!$F$26=Unemployment!$E$33,Unemployment!E41,1)))) -> 2 | AX38: =AVERAGE(AP38*0.2222 + AQ38*0.1944 + AR38*0.1667 + AS38*0.1389 + AT38*0.0556 + AU38*0.0556 + AV38*0.0556 + AW38*0.1111) -> 2.8059
